{"frameRate":30,"isGlobal":0,"armature":[{"aabb":{"width":261.9704818499933,"y":-250.01552813793108,"height":289.7555281379311,"x":-121.2785079503126},"type":"Armature","bone":[{"name":"root","transform":{}},{"transform":{"y":-8.14,"x":-31.3},"name":"1","parent":"root"},{"transform":{"y":-9.21,"x":27.8},"name":"3","parent":"root"},{"transform":{"y":-48.41,"x":2.69},"name":"bone","parent":"root"},{"transform":{"scX":1.207,"y":-5.26,"x":-0.5},"name":"bone32","parent":"root"},{"length":27,"transform":{"y":0.31,"skX":130.11,"skY":130.11,"x":-12.64},"parent":"bone","name":"bone19"},{"transform":{"y":11.4,"x":13.15},"name":"4","parent":"3"},{"transform":{"y":8.69,"x":-10.75},"name":"2","parent":"1"},{"length":25,"transform":{"y":-3.96,"skX":-84.6,"skY":-84.6,"x":-0.44},"parent":"bone","name":"bone2"},{"length":23,"transform":{"y":2.64,"skX":52.06,"skY":52.06,"x":15.18},"parent":"bone","name":"bone22"},{"length":47,"transform":{"y":0.1,"skX":-3.15,"skY":-3.15,"x":25.11},"parent":"bone2","name":"bone3"},{"length":18,"transform":{"y":-0.11,"skX":53.2,"skY":53.2,"x":23.91},"parent":"bone22","name":"bone23"},{"length":19,"transform":{"y":0.03,"skX":-29.89,"skY":-29.89,"x":27.74},"parent":"bone19","name":"bone20"},{"length":60,"transform":{"y":-68.5,"skX":-143.83,"skY":-143.83,"x":42.17},"parent":"bone3","name":"bone13"},{"length":52,"transform":{"y":39.57,"skX":147.47,"skY":147.47,"x":48.46},"parent":"bone3","name":"bone16"},{"length":14,"transform":{"y":-0.13,"skX":41.6,"skY":41.6,"x":19.11},"parent":"bone20","name":"bone21"},{"length":17,"transform":{"y":-0.24,"skX":-64.71,"skY":-64.71,"x":18.69},"parent":"bone23","name":"bone24"},{"length":71,"transform":{"y":-30.29,"skX":-66.58,"skY":-66.58,"x":34.98},"parent":"bone3","name":"bone25"},{"length":52,"transform":{"y":-8.39,"skX":176.84,"skY":176.84,"x":45.73},"parent":"bone3","name":"bone26"},{"length":74,"transform":{"y":0.83,"skX":5.39,"skY":5.39,"x":34.29},"parent":"bone3","name":"bone4"},{"length":51,"transform":{"y":-41.89,"skX":179.54,"skY":179.54,"x":45.68},"parent":"bone3","name":"bone5"},{"length":46,"transform":{"y":34.17,"skX":174.6,"skY":174.6,"x":43.35},"parent":"bone3","name":"bone9"},{"length":42,"transform":{"skX":1.8,"skY":1.8,"x":52.21},"parent":"bone26","name":"bone27"},{"length":29,"transform":{"y":5.17,"skX":-146.51,"skY":-146.51,"x":68.73},"parent":"bone13","name":"bone14"},{"length":31,"transform":{"y":-0.27,"skX":-14.67,"skY":-14.67,"x":52.41},"parent":"bone16","name":"bone17"},{"length":32,"transform":{"y":-0.31,"skX":-8.57,"skY":-8.57,"x":46.6},"parent":"bone9","name":"bone10"},{"length":34,"transform":{"y":2.48,"skX":-96.73,"skY":-96.73,"x":110.9},"parent":"bone4","name":"bone29"},{"length":18,"transform":{"y":-52.31,"skX":-86.51,"skY":-86.51,"x":68.57},"parent":"bone4","name":"bone30"},{"length":35,"transform":{"y":-0.3,"skX":14.98,"skY":14.98,"x":51.1},"parent":"bone5","name":"bone6"},{"length":27,"transform":{"y":-0.19,"skX":-7.18,"skY":-7.18,"x":32.84},"parent":"bone10","name":"bone11"},{"length":36,"transform":{"y":-0.02,"skX":-2.87,"skY":-2.87,"x":18.77},"parent":"bone14","name":"bone15"},{"length":38,"transform":{"y":-0.01,"skX":19.51,"skY":19.51,"x":31.14},"parent":"bone17","name":"bone18"},{"length":30,"transform":{"y":0.18,"skX":-0.9,"skY":-0.9,"x":42.85},"parent":"bone27","name":"bone28"},{"length":27,"transform":{"y":0.23,"skX":15.82,"skY":15.82,"x":35.27},"parent":"bone6","name":"bone7"},{"length":20,"transform":{"y":-0.18,"skX":-13.71,"skY":-13.71,"x":27.38},"parent":"bone11","name":"bone12"},{"length":44,"transform":{"y":6.3,"skX":-81.49,"skY":-81.49,"x":-6.73},"parent":"bone18","name":"bone31"},{"length":24,"transform":{"y":0.12,"skX":19.65,"skY":19.65,"x":27.75},"parent":"bone7","name":"bone8"}],"defaultActions":[{"gotoAndPlay":"atk"}],"slot":[{"color":{},"name":"ty","parent":"bone32"},{"z":1,"color":{},"name":"zuobi","parent":"bone16"},{"z":2,"color":{},"name":"zuowan","parent":"bone17"},{"z":3,"color":{},"name":"houbai","parent":"bone26"},{"z":4,"color":{},"name":"zuoxiaotui","parent":"bone23"},{"z":5,"color":{},"name":"zuojiao","parent":"bone24"},{"z":6,"color":{},"name":"zuodatui","parent":"bone22"},{"z":7,"color":{},"name":"youxiaotui","parent":"bone20"},{"z":8,"color":{},"name":"youjiao","parent":"bone21"},{"z":9,"color":{},"name":"youdatui","parent":"bone19"},{"z":10,"color":{},"name":"shenti","parent":"bone2"},{"z":11,"color":{},"name":"pifeng","parent":"bone5"},{"z":12,"color":{},"name":"tou","parent":"bone4"},{"z":13,"color":{},"name":"youjianhou","parent":"bone25"},{"z":14,"color":{},"name":"youbi","parent":"bone13"},{"z":15,"color":{},"name":"youwan","parent":"bone14"},{"z":16,"color":{},"name":"youjian","parent":"bone25"},{"z":17,"color":{},"name":"youshou","parent":"bone15"},{"z":18,"color":{},"name":"wuqi","parent":"bone31"},{"z":19,"color":{},"name":"shihua","parent":"root","displayIndex":-1}],"animation":[{"duration":35,"frame":[{"duration":16,"tweenEasing":null},{"duration":0,"tweenEasing":null,"events":[{"name":"hit"}]}],"ik":[],"bone":[{"frame":[{"duration":7,"transform":{}},{"duration":7,"transform":{}},{"duration":2,"transform":{}},{"duration":12,"transform":{}},{"duration":7,"transform":{}},{"duration":0,"transform":{}}],"name":"root"},{"frame":[{"duration":7,"transform":{},"tweenEasing":0},{"duration":7,"transform":{"skX":-0.83,"skY":-0.83},"tweenEasing":0},{"duration":2,"transform":{"skX":-25.74,"skY":-25.74},"tweenEasing":0},{"duration":12,"transform":{"skX":-3.02,"skY":-3.02}},{"duration":7,"transform":{"skX":-3.02,"skY":-3.02},"tweenEasing":0},{"duration":0,"transform":{}}],"name":"bone2"},{"frame":[{"duration":5,"transform":{},"tweenEasing":0},{"duration":2,"transform":{"skX":-5.27,"skY":-5.27},"tweenEasing":0},{"duration":3,"transform":{"skX":-3.15,"skY":-3.15},"tweenEasing":0},{"duration":4,"transform":{"skX":-1.2,"skY":-1.2},"tweenEasing":0},{"duration":2,"transform":{"skX":-7.62,"skY":-7.62},"tweenEasing":0},{"duration":2,"transform":{"skX":7.47,"skY":7.47},"tweenEasing":0},{"duration":10,"transform":{"skX":-14.25,"skY":-14.25},"tweenEasing":0},{"duration":7,"transform":{"skX":-7.26,"skY":-7.26},"tweenEasing":0},{"duration":0,"transform":{}}],"name":"bone4"},{"frame":[{"duration":7,"transform":{},"curve":[0.25,0,0.75,1]},{"duration":7,"transform":{"skX":-346.04,"skY":-346.04},"curve":[0.25,0,0.75,1]},{"duration":6,"transform":{"skX":-10.85,"skY":-10.85},"curve":[0.25,0,0.75,1]},{"duration":7,"transform":{"skX":-346.04,"skY":-346.04},"curve":[0.25,0,0.75,1]},{"duration":8,"transform":{"skX":-353.14,"skY":-353.14},"curve":[0.25,0,0.75,1]},{"duration":0,"transform":{}}],"name":"bone5"},{"frame":[{"duration":7,"transform":{},"tweenEasing":0},{"duration":7,"transform":{"skX":-32.16,"skY":-32.16},"tweenEasing":0},{"duration":2,"transform":{"skX":277.32,"skY":277.32},"tweenEasing":0},{"duration":2,"transform":{"skX":-2.2,"skY":-2.2},"tweenEasing":0},{"duration":10,"transform":{"skX":15.55,"skY":15.55},"tweenEasing":0},{"duration":7,"transform":{"skX":-2.2,"skY":-2.2},"tweenEasing":0},{"duration":0,"transform":{}}],"name":"bone13"},{"frame":[{"duration":7,"transform":{},"tweenEasing":0},{"duration":7,"transform":{"y":4.86,"skX":53.81,"skY":53.81,"x":-6.88},"tweenEasing":0},{"duration":2,"transform":{"y":-7.21,"skX":83.43,"skY":83.43,"x":-10.63},"tweenEasing":0},{"duration":3,"transform":{"y":4.69,"skX":49.2,"skY":49.2,"x":-9.77},"tweenEasing":0},{"duration":9,"transform":{"y":4.69,"skX":36.11,"skY":36.11,"x":-9.77},"tweenEasing":0},{"duration":7,"transform":{"y":4.69,"skX":49.2,"skY":49.2,"x":-9.77},"tweenEasing":0},{"duration":0,"transform":{}}],"name":"bone14"},{"frame":[{"duration":7,"transform":{},"tweenEasing":0},{"duration":7,"transform":{"skX":-11.17,"skY":-11.17}},{"duration":2,"transform":{"skX":-11.17,"skY":-11.17}},{"duration":12,"transform":{"skX":-11.17,"skY":-11.17}},{"duration":7,"transform":{"skX":-11.17,"skY":-11.17},"tweenEasing":0},{"duration":0,"transform":{}}],"name":"bone15"},{"frame":[{"duration":7,"transform":{},"tweenEasing":0},{"duration":7,"transform":{"skX":67.09,"skY":67.09}},{"duration":2,"transform":{"skX":67.09,"skY":67.09},"tweenEasing":0},{"duration":2,"transform":{"scX":1.065,"scY":1.065,"skX":-125.12,"skY":-125.12},"tweenEasing":0},{"duration":10,"transform":{"scX":1.065,"scY":1.065,"skX":-118.25,"skY":-118.25},"tweenEasing":0},{"duration":7,"transform":{"scX":1.065,"scY":1.065,"skX":-125.12,"skY":-125.12},"tweenEasing":0},{"duration":0,"transform":{}}],"name":"bone16"},{"frame":[{"duration":7,"transform":{},"tweenEasing":0},{"duration":7,"transform":{"skX":-57.19,"skY":-57.19}},{"duration":2,"transform":{"skX":-57.19,"skY":-57.19},"tweenEasing":0},{"duration":12,"transform":{"skX":-1.4,"skY":-1.4}},{"duration":7,"transform":{"skX":-1.4,"skY":-1.4},"tweenEasing":0},{"duration":0,"transform":{}}],"name":"bone17"},{"frame":[{"duration":7,"transform":{}},{"duration":7,"transform":{}},{"duration":2,"transform":{}},{"duration":12,"transform":{}},{"duration":7,"transform":{}},{"duration":0,"transform":{}}],"name":"bone31"},{"frame":[{"duration":7,"transform":{}},{"duration":7,"transform":{},"tweenEasing":0},{"duration":2,"transform":{"y":1.73,"skX":-35,"skY":-35,"x":8.44},"tweenEasing":0},{"duration":4,"transform":{},"tweenEasing":0},{"duration":8,"transform":{"skX":11.26,"skY":11.26},"tweenEasing":0},{"duration":7,"transform":{"skX":4.2,"skY":4.2},"tweenEasing":0},{"duration":0,"transform":{}}],"name":"bone25"},{"frame":[{"duration":7,"transform":{},"tweenEasing":0},{"duration":7,"transform":{"scX":0.952,"skX":-15.24,"skY":-15.24}},{"duration":2,"transform":{"scX":0.952,"skX":-15.24,"skY":-15.24},"tweenEasing":0},{"duration":7,"transform":{"scX":0.952,"skX":-0.85,"skY":-0.85},"tweenEasing":0},{"duration":5,"transform":{"scX":0.661,"skX":-0.85,"skY":-0.85},"tweenEasing":0},{"duration":7,"transform":{"scX":0.661,"skX":-15.24,"skY":-15.24},"tweenEasing":0},{"duration":0,"transform":{}}],"name":"bone26"},{"frame":[{"duration":7,"transform":{}},{"duration":7,"transform":{}},{"duration":2,"transform":{},"tweenEasing":0},{"duration":2,"transform":{"y":5,"x":-4},"tweenEasing":0},{"duration":10,"transform":{"y":11,"x":-4},"tweenEasing":0},{"duration":7,"transform":{"y":5,"x":-4},"tweenEasing":0},{"duration":0,"transform":{}}],"name":"bone19"},{"frame":[{"duration":7,"transform":{}},{"duration":7,"transform":{}},{"duration":2,"transform":{}},{"duration":12,"transform":{}},{"duration":7,"transform":{}},{"duration":0,"transform":{}}],"name":"bone20"},{"frame":[{"duration":7,"transform":{}},{"duration":7,"transform":{}},{"duration":2,"transform":{}},{"duration":12,"transform":{}},{"duration":7,"transform":{}},{"duration":0,"transform":{}}],"name":"bone21"},{"frame":[{"duration":7,"transform":{}},{"duration":7,"transform":{}},{"duration":2,"transform":{}},{"duration":2,"transform":{},"tweenEasing":0},{"duration":10,"transform":{"y":6},"tweenEasing":0},{"duration":7,"transform":{}},{"duration":0,"transform":{}}],"name":"bone22"},{"frame":[{"duration":7,"transform":{}},{"duration":7,"transform":{}},{"duration":2,"transform":{}},{"duration":12,"transform":{}},{"duration":7,"transform":{}},{"duration":0,"transform":{}}],"name":"bone23"},{"frame":[{"duration":7,"transform":{}},{"duration":7,"transform":{}},{"duration":2,"transform":{}},{"duration":12,"transform":{}},{"duration":7,"transform":{}},{"duration":0,"transform":{}}],"name":"bone24"},{"frame":[{"duration":7,"transform":{},"tweenEasing":0},{"duration":7,"transform":{"skX":-3.58,"skY":-3.58}},{"duration":2,"transform":{"skX":-3.58,"skY":-3.58},"tweenEasing":0},{"duration":12,"transform":{"skX":6.52,"skY":6.52},"tweenEasing":0},{"duration":7,"transform":{"skX":-3.58,"skY":-3.58},"tweenEasing":0},{"duration":0,"transform":{}}],"name":"bone28"},{"frame":[{"duration":7,"transform":{},"tweenEasing":0},{"duration":7,"transform":{"y":4.16,"skX":-18,"skY":-18,"x":-9.46},"tweenEasing":0},{"duration":2,"transform":{"y":1.55,"skX":-31.03,"skY":-31.03,"x":-15.18},"tweenEasing":0},{"duration":12,"transform":{"skX":6.26,"skY":6.26},"tweenEasing":0},{"duration":7,"transform":{"skX":-2.21,"skY":-2.21},"tweenEasing":0},{"duration":0,"transform":{}}],"name":"bone27"},{"frame":[{"duration":7,"transform":{}},{"duration":7,"transform":{}},{"duration":2,"transform":{},"tweenEasing":0},{"duration":12,"transform":{"y":12.89,"skX":71.35,"skY":71.35,"x":34.95}},{"duration":7,"transform":{"y":12.89,"skX":71.35,"skY":71.35,"x":34.95},"tweenEasing":0},{"duration":0,"transform":{}}],"name":"bone18"},{"frame":[{"duration":8,"transform":{},"curve":[0.25,0,0.75,1]},{"duration":3,"transform":{"skX":-38.6,"skY":-38.6},"curve":[0.264,0,0.617,0.42]},{"duration":3,"transform":{"skX":0.57,"skY":0.57},"curve":[0.325,0.3,0.675,0.69]},{"duration":2,"transform":{"skX":-9.64,"skY":-9.64},"curve":[0.36,0.43,0.701,0.8]},{"duration":1,"transform":{"skX":17.59,"skY":17.59},"curve":[0.361,0.63,0.697,1]},{"duration":6,"transform":{"skX":37.9,"skY":37.9},"curve":[0.25,0,0.75,1]},{"duration":12,"transform":{"skX":-21.97,"skY":-21.97},"curve":[0.244,0,0.706,0.81]},{"duration":0,"transform":{}}],"name":"bone12"},{"frame":[{"duration":7,"transform":{},"curve":[0.25,0,0.75,1]},{"duration":4,"transform":{"skX":-46.34,"skY":-46.34},"curve":[0.253,0,0.62,0.47]},{"duration":3,"transform":{"skX":-20.99,"skY":-20.99},"curve":[0.341,0.36,0.692,0.74]},{"duration":2,"transform":{"skX":-3.54,"skY":-3.54},"curve":[0.377,0.6,0.719,1]},{"duration":6,"transform":{"skX":23.36,"skY":23.36},"curve":[0.25,0,0.75,1]},{"duration":13,"transform":{"skX":-29.98,"skY":-29.98},"curve":[0.25,0,0.75,1]},{"duration":0,"transform":{}}],"name":"bone11"},{"frame":[{"duration":5,"transform":{},"curve":[0.25,0,0.75,1]},{"duration":6,"transform":{"skX":-27.56,"skY":-27.56},"curve":[0.243,0,0.648,0.6]},{"duration":3,"transform":{"skX":-27.89,"skY":-27.89},"curve":[0.382,0.57,0.735,1]},{"duration":2,"transform":{"skX":-37.89,"skY":-37.89},"curve":[0.264,0,0.617,0.42]},{"duration":4,"transform":{"skX":31.88,"skY":31.88},"curve":[0.351,0.4,0.756,1]},{"duration":15,"transform":{"skX":-27.56,"skY":-27.56},"curve":[0.25,0,0.75,1]},{"duration":0,"transform":{}}],"name":"bone10"},{"frame":[{"duration":7,"transform":{},"curve":[0.25,0,0.75,1]},{"duration":7,"transform":{"skX":-10.35,"skY":-10.35},"curve":[0.2495,0,0.6455,0.57]},{"duration":2,"transform":{"scX":0.874,"scY":0.874,"skX":-31.34,"skY":-31.34},"curve":[0.3695,0.52,0.7364999999999999,1]},{"duration":6,"transform":{"skX":-11.53,"skY":-11.53},"curve":[0.25,0,0.75,1]},{"duration":13,"transform":{"skX":-10.35,"skY":-10.35},"curve":[0.25,0,0.75,1]},{"duration":0,"transform":{}}],"name":"bone9"},{"frame":[{"duration":9,"transform":{},"curve":[0.25,0,0.75,1]},{"duration":7,"transform":{"skX":-25.67,"skY":-25.67},"curve":[0.25,0,0.75,1]},{"duration":6,"transform":{"skX":29.45,"skY":29.45},"curve":[0.25,0,0.75,1]},{"duration":7,"transform":{"skX":-25.67,"skY":-25.67},"curve":[0.25,0,0.75,1]},{"duration":6,"transform":{"skX":29.45,"skY":29.45},"curve":[0.25,0,0.75,1]},{"duration":0,"transform":{}}],"name":"bone8"},{"frame":[{"duration":7,"transform":{},"curve":[0.25,0,0.75,1]},{"duration":7,"transform":{"skX":-22.17,"skY":-22.17},"curve":[0.25,0,0.75,1]},{"duration":6,"transform":{"skX":16.88,"skY":16.88},"curve":[0.25,0,0.75,1]},{"duration":7,"transform":{"skX":-22.17,"skY":-22.17},"curve":[0.25,0,0.75,1]},{"duration":8,"transform":{"skX":16.88,"skY":16.88},"curve":[0.25,0,0.75,1]},{"duration":0,"transform":{}}],"name":"bone7"},{"frame":[{"duration":5,"transform":{},"curve":[0.25,0,0.75,1]},{"duration":7,"transform":{"skX":-27.9,"skY":-27.9},"curve":[0.25,0,0.75,1]},{"duration":6,"transform":{"skX":23.21,"skY":23.21},"curve":[0.25,0,0.75,1]},{"duration":7,"transform":{"skX":-27.9,"skY":-27.9},"curve":[0.25,0,0.75,1]},{"duration":10,"transform":{"skX":23.21,"skY":23.21},"curve":[0.25,0,0.75,1]},{"duration":0,"transform":{}}],"name":"bone6"},{"frame":[{"duration":7,"transform":{}},{"duration":7,"transform":{},"tweenEasing":0},{"duration":2,"transform":{"skX":-60.96,"skY":-60.96},"tweenEasing":0},{"duration":7,"transform":{},"tweenEasing":0},{"duration":5,"transform":{"y":-12.44,"skX":-51.64,"skY":-51.64,"x":-23.19},"tweenEasing":0},{"duration":7,"transform":{"y":-6.39,"skX":-56.97,"skY":-56.97,"x":-8.38},"tweenEasing":0},{"duration":0,"transform":{}}],"name":"bone30"},{"frame":[{"duration":7,"transform":{},"tweenEasing":0},{"duration":7,"transform":{"skX":23.31,"skY":23.31},"tweenEasing":0},{"duration":2,"transform":{"skX":-29.38,"skY":-29.38},"tweenEasing":0},{"duration":3,"transform":{"skX":-34.07,"skY":-34.07},"tweenEasing":0},{"duration":9,"transform":{"skX":26.35,"skY":26.35},"tweenEasing":0},{"duration":7,"transform":{"skX":-23.37,"skY":-23.37},"tweenEasing":0},{"duration":0,"transform":{}}],"name":"bone29"},{"frame":[{"duration":7,"transform":{},"tweenEasing":0},{"duration":7,"transform":{"y":-11.75,"skX":17.83,"skY":17.83,"x":0.08},"tweenEasing":0},{"duration":2,"transform":{"y":-11.75,"skX":46.39,"skY":46.39,"x":0.08},"tweenEasing":0},{"duration":2,"transform":{"scX":1.022,"y":-8.29,"scY":1.022,"skX":-9.34,"skY":-9.34,"x":8.29},"tweenEasing":0},{"duration":10,"transform":{"scX":1.022,"y":-8.56,"scY":1.022,"skX":-14.58,"skY":-14.58,"x":14.8},"tweenEasing":0},{"duration":7,"transform":{"scX":1.022,"y":-8.29,"scY":1.022,"skX":-9.34,"skY":-9.34,"x":8.29},"tweenEasing":0},{"duration":0,"transform":{}}],"name":"bone3"},{"frame":[{"duration":7,"transform":{},"tweenEasing":0},{"duration":3,"transform":{"y":15.76,"x":-15.74},"tweenEasing":0},{"duration":4,"transform":{"y":12.36,"x":-24.53},"tweenEasing":0},{"duration":2,"transform":{"y":10.76,"skX":15.7,"skY":15.7,"x":-16.86},"tweenEasing":0},{"duration":2,"transform":{"y":-5,"x":6.85},"tweenEasing":0},{"duration":10,"transform":{"y":-12,"x":6.85},"tweenEasing":0},{"duration":7,"transform":{"y":-5,"x":6.85},"tweenEasing":0},{"duration":0,"transform":{}}],"name":"bone"},{"frame":[{"duration":7,"transform":{}},{"duration":7,"transform":{}},{"duration":2,"transform":{}},{"duration":12,"transform":{}},{"duration":7,"transform":{}},{"duration":0,"transform":{}}],"name":"4"},{"frame":[{"duration":7,"transform":{}},{"duration":7,"transform":{}},{"duration":2,"transform":{}},{"duration":12,"transform":{}},{"duration":7,"transform":{}},{"duration":0,"transform":{}}],"name":"3"},{"frame":[{"duration":7,"transform":{}},{"duration":7,"transform":{}},{"duration":2,"transform":{}},{"duration":12,"transform":{}},{"duration":7,"transform":{}},{"duration":0,"transform":{}}],"name":"2"},{"frame":[{"duration":7,"transform":{}},{"duration":7,"transform":{}},{"duration":2,"transform":{}},{"duration":12,"transform":{}},{"duration":7,"transform":{}},{"duration":0,"transform":{}}],"name":"1"},{"frame":[{"duration":7,"transform":{},"tweenEasing":0},{"duration":7,"transform":{"scX":1.081,"x":-3.78}},{"duration":2,"transform":{"scX":1.081,"x":-3.78},"tweenEasing":0},{"duration":12,"transform":{}},{"duration":7,"transform":{}},{"duration":0,"transform":{}}],"name":"bone32"}],"slot":[{"frame":[{"tweenEasing":0,"duration":35},{"tweenEasing":null,"duration":0}],"name":"houbai"},{"frame":[{"tweenEasing":0,"duration":35},{"tweenEasing":null,"duration":0}],"name":"pifeng"},{"frame":[{"tweenEasing":0,"duration":35},{"tweenEasing":null,"duration":0}],"name":"shenti"},{"frame":[{"tweenEasing":0,"duration":35,"displayIndex":-1},{"tweenEasing":null,"duration":0,"displayIndex":-1}],"name":"shihua"},{"frame":[{"tweenEasing":0,"duration":35},{"tweenEasing":null,"duration":0}],"name":"tou"},{"frame":[{"tweenEasing":null,"duration":35}],"name":"ty"},{"frame":[{"tweenEasing":0,"duration":35},{"tweenEasing":null,"duration":0}],"name":"wuqi"},{"frame":[{"tweenEasing":0,"duration":35},{"tweenEasing":null,"duration":0}],"name":"youbi"},{"frame":[{"tweenEasing":0,"duration":35},{"tweenEasing":null,"duration":0}],"name":"youdatui"},{"frame":[{"tweenEasing":0,"duration":35},{"tweenEasing":null,"duration":0}],"name":"youjian"},{"frame":[{"tweenEasing":0,"duration":35},{"tweenEasing":null,"duration":0}],"name":"youjianhou"},{"frame":[{"tweenEasing":0,"duration":35},{"tweenEasing":null,"duration":0}],"name":"youjiao"},{"frame":[{"tweenEasing":0,"duration":35},{"tweenEasing":null,"duration":0}],"name":"youshou"},{"frame":[{"tweenEasing":0,"duration":35},{"tweenEasing":null,"duration":0}],"name":"youwan"},{"frame":[{"tweenEasing":0,"duration":35},{"tweenEasing":null,"duration":0}],"name":"youxiaotui"},{"frame":[{"tweenEasing":0,"duration":35},{"tweenEasing":null,"duration":0}],"name":"zuobi"},{"frame":[{"tweenEasing":0,"duration":35},{"tweenEasing":null,"duration":0}],"name":"zuodatui"},{"frame":[{"tweenEasing":0,"duration":35},{"tweenEasing":null,"duration":0}],"name":"zuojiao"},{"frame":[{"tweenEasing":0,"duration":35},{"tweenEasing":null,"duration":0}],"name":"zuowan"},{"frame":[{"tweenEasing":0,"duration":35},{"tweenEasing":null,"duration":0}],"name":"zuoxiaotui"}],"ffd":[{"frame":[{"duration":35,"offset":0,"vertices":[],"tweenEasing":null},{"duration":0,"offset":0,"vertices":[],"tweenEasing":null}],"scale":1,"slot":"houbai","offset":0,"name":"houbai","skin":""},{"frame":[{"duration":35,"offset":0,"vertices":[],"tweenEasing":null},{"duration":0,"offset":0,"vertices":[],"tweenEasing":null}],"scale":1,"slot":"pifeng","offset":0,"name":"pifeng","skin":""},{"frame":[{"duration":35,"offset":0,"vertices":[],"tweenEasing":null},{"duration":0,"offset":0,"vertices":[],"tweenEasing":null}],"scale":1,"slot":"shenti","offset":0,"name":"shenti","skin":""},{"frame":[{"duration":14,"offset":0,"vertices":[],"tweenEasing":null},{"duration":2,"offset":0,"vertices":[],"tweenEasing":null},{"duration":4,"offset":0,"vertices":[],"tweenEasing":0},{"duration":15,"offset":72,"vertices":[5.12,1.37,-2.6,-3.32,-3.51,-0.37,-0.14,2.43,1.5,-1.81,5.83,-3.54,5.46,-0.88,2.86,-0.69],"tweenEasing":0},{"duration":0,"offset":0,"vertices":[],"tweenEasing":null}],"scale":1,"slot":"tou","offset":0,"name":"tou","skin":""},{"frame":[{"duration":7,"offset":0,"vertices":[],"tweenEasing":0},{"duration":3,"offset":2,"vertices":[1.38,-6.11,0,0,0,0,0,0,0,0,0,0,0,0,0,0,0,0,0,0,0,0],"tweenEasing":0},{"duration":4,"offset":2,"vertices":[0.79,-3.49,2.92,1.66,0,0,0,0,0,0,0,0,0,0,0,0,0,0,0,0,0,0],"tweenEasing":0},{"duration":2,"offset":0,"vertices":[],"tweenEasing":0},{"duration":12,"offset":0,"vertices":[1.8,-4.75,4.64,-8.1,0.33,-0.22,0,0,0,0,0,0,0,0,0,0,0,0,0,0,0,0,0,0],"tweenEasing":null},{"duration":7,"offset":0,"vertices":[1.8,-4.75,4.64,-8.1,0.33,-0.22,0,0,0,0,0,0,0,0,0,0,0,0,0,0,0,0,0,0],"tweenEasing":0},{"duration":0,"offset":0,"vertices":[],"tweenEasing":null}],"scale":1,"slot":"youdatui","offset":0,"name":"youdatui","skin":""},{"frame":[{"duration":7,"offset":0,"vertices":[],"tweenEasing":0},{"duration":7,"offset":2,"vertices":[4.65,-3.85,0,0,0,0,0,0,0,0,0,0,0,0,0,0,0,0,0,0],"tweenEasing":0},{"duration":2,"offset":2,"vertices":[11.66,-5.66,0,0,0,0,0,0,0,0,0,0,0,0,0,0,0,0,0,0],"tweenEasing":0},{"duration":12,"offset":2,"vertices":[0.26,-0.54,0,0,0,0,0,0,0,0,0,0,0,0,0,0,0,0,0,0],"tweenEasing":null},{"duration":7,"offset":2,"vertices":[0.26,-0.54,0,0,0,0,0,0,0,0,0,0,0,0,0,0,0,0,0,0],"tweenEasing":0},{"duration":0,"offset":0,"vertices":[],"tweenEasing":null}],"scale":1,"slot":"zuodatui","offset":0,"name":"zuodatui","skin":""}],"name":"atk"},{"duration":15,"frame":[],"ik":[],"bone":[{"frame":[{"duration":15,"transform":{}},{"duration":0,"transform":{}}],"name":"root"},{"frame":[{"duration":2,"transform":{},"tweenEasing":0},{"duration":2,"transform":{"skX":-8.84,"skY":-8.84},"tweenEasing":0},{"duration":3,"transform":{"skX":-5.8,"skY":-5.8},"tweenEasing":0},{"duration":8,"transform":{"skX":-8.84,"skY":-8.84},"tweenEasing":0},{"duration":0,"transform":{}}],"name":"bone2"},{"frame":[{"duration":2,"transform":{},"tweenEasing":0},{"duration":2,"transform":{"skX":-5.95,"skY":-5.95},"tweenEasing":0},{"duration":3,"transform":{"skX":2.7,"skY":2.7},"tweenEasing":0},{"duration":8,"transform":{"skX":-5.95,"skY":-5.95},"tweenEasing":0},{"duration":0,"transform":{}}],"name":"bone4"},{"frame":[{"duration":2,"transform":{},"tweenEasing":0},{"duration":2,"transform":{"skX":-343.03,"skY":-343.03},"tweenEasing":0},{"duration":3,"transform":{"skX":-338.77,"skY":-338.77},"tweenEasing":0},{"duration":8,"transform":{"skX":-339.77,"skY":-339.77},"tweenEasing":0},{"duration":0,"transform":{}}],"name":"bone5"},{"frame":[{"duration":2,"transform":{},"tweenEasing":0},{"duration":5,"transform":{"skX":-21.54,"skY":-21.54},"tweenEasing":0},{"duration":8,"transform":{"skX":15.43,"skY":15.43},"tweenEasing":0},{"duration":0,"transform":{}}],"name":"bone13"},{"frame":[{"duration":2,"transform":{},"tweenEasing":0},{"duration":5,"transform":{"y":3.22,"skX":45.41,"skY":45.41,"x":-8.16},"tweenEasing":0},{"duration":8,"transform":{"y":11.14,"skX":37.3,"skY":37.3,"x":-9.41},"tweenEasing":0},{"duration":0,"transform":{}}],"name":"bone14"},{"frame":[{"duration":15,"transform":{}},{"duration":0,"transform":{}}],"name":"bone15"},{"frame":[{"duration":2,"transform":{},"tweenEasing":0},{"duration":5,"transform":{"skX":-323.85,"skY":-323.85},"tweenEasing":0},{"duration":8,"transform":{"skX":-297.39,"skY":-297.39},"tweenEasing":0},{"duration":0,"transform":{}}],"name":"bone16"},{"frame":[{"duration":2,"transform":{},"tweenEasing":0},{"duration":5,"transform":{"skX":-27.87,"skY":-27.87},"tweenEasing":0},{"duration":8,"transform":{"skX":-36.29,"skY":-36.29},"tweenEasing":0},{"duration":0,"transform":{}}],"name":"bone17"},{"frame":[{"duration":15,"transform":{}},{"duration":0,"transform":{}}],"name":"bone31"},{"frame":[{"duration":15,"transform":{}},{"duration":0,"transform":{}}],"name":"bone25"},{"frame":[{"duration":2,"transform":{},"tweenEasing":0},{"duration":5,"transform":{"skX":-0.07,"skY":-0.07},"tweenEasing":0},{"duration":8,"transform":{"skX":-335.68,"skY":-335.68},"tweenEasing":0},{"duration":0,"transform":{}}],"name":"bone26"},{"frame":[{"duration":15,"transform":{}},{"duration":0,"transform":{}}],"name":"bone19"},{"frame":[{"duration":15,"transform":{}},{"duration":0,"transform":{}}],"name":"bone20"},{"frame":[{"duration":15,"transform":{}},{"duration":0,"transform":{}}],"name":"bone21"},{"frame":[{"duration":15,"transform":{}},{"duration":0,"transform":{}}],"name":"bone22"},{"frame":[{"duration":15,"transform":{}},{"duration":0,"transform":{}}],"name":"bone23"},{"frame":[{"duration":15,"transform":{}},{"duration":0,"transform":{}}],"name":"bone24"},{"frame":[{"duration":2,"transform":{},"tweenEasing":0},{"duration":5,"transform":{"skX":-24.66,"skY":-24.66},"tweenEasing":0},{"duration":8,"transform":{"skX":17.39,"skY":17.39},"tweenEasing":0},{"duration":0,"transform":{}}],"name":"bone28"},{"frame":[{"duration":2,"transform":{},"tweenEasing":0},{"duration":5,"transform":{"skX":-16.46,"skY":-16.46},"tweenEasing":0},{"duration":8,"transform":{"skX":18.13,"skY":18.13},"tweenEasing":0},{"duration":0,"transform":{}}],"name":"bone27"},{"frame":[{"duration":15,"transform":{}},{"duration":0,"transform":{}}],"name":"bone18"},{"frame":[{"duration":2,"transform":{},"tweenEasing":0},{"duration":6,"transform":{"skX":32.79,"skY":32.79},"tweenEasing":0},{"duration":7,"transform":{"skX":-48,"skY":-48},"tweenEasing":0},{"duration":0,"transform":{}}],"name":"bone12"},{"frame":[{"duration":2,"transform":{},"tweenEasing":0},{"duration":6,"transform":{"skX":19.88,"skY":19.88},"tweenEasing":0},{"duration":7,"transform":{"skX":-31.27,"skY":-31.27},"tweenEasing":0},{"duration":0,"transform":{}}],"name":"bone11"},{"frame":[{"duration":2,"transform":{},"tweenEasing":0},{"duration":6,"transform":{"skX":17.97,"skY":17.97},"tweenEasing":0},{"duration":7,"transform":{"skX":-23.69,"skY":-23.69},"tweenEasing":0},{"duration":0,"transform":{}}],"name":"bone10"},{"frame":[{"duration":2,"transform":{},"tweenEasing":0},{"duration":6,"transform":{"skX":-3.75,"skY":-3.75},"tweenEasing":0},{"duration":7,"transform":{"y":4.96,"skX":-350.15,"skY":-350.15,"x":-1.28},"tweenEasing":0},{"duration":0,"transform":{}}],"name":"bone9"},{"frame":[{"duration":2,"transform":{},"tweenEasing":0},{"duration":2,"transform":{"skX":-23.06,"skY":-23.06},"tweenEasing":0},{"duration":3,"transform":{"skX":-59.73,"skY":-59.73},"tweenEasing":0},{"duration":8,"transform":{"skX":26.56,"skY":26.56},"tweenEasing":0},{"duration":0,"transform":{}}],"name":"bone8"},{"frame":[{"duration":2,"transform":{},"tweenEasing":0},{"duration":2,"transform":{"skX":-20.66,"skY":-20.66},"tweenEasing":0},{"duration":3,"transform":{"skX":-32.21,"skY":-32.21},"tweenEasing":0},{"duration":8,"transform":{"skX":22.62,"skY":22.62},"tweenEasing":0},{"duration":0,"transform":{}}],"name":"bone7"},{"frame":[{"duration":2,"transform":{},"tweenEasing":0},{"duration":2,"transform":{"skX":-15.75,"skY":-15.75},"tweenEasing":0},{"duration":3,"transform":{"skX":23.07,"skY":23.07},"tweenEasing":0},{"duration":8,"transform":{"skX":26.51,"skY":26.51},"tweenEasing":0},{"duration":0,"transform":{}}],"name":"bone6"},{"frame":[{"duration":2,"transform":{},"tweenEasing":0},{"duration":5,"transform":{"y":8.72,"skX":36.4,"skY":36.4,"x":13.52},"tweenEasing":0},{"duration":8,"transform":{"y":-13.82,"skX":-82.18,"skY":-82.18,"x":-14.66},"tweenEasing":0},{"duration":0,"transform":{}}],"name":"bone30"},{"frame":[{"duration":2,"transform":{},"tweenEasing":0},{"duration":5,"transform":{"skX":25.68,"skY":25.68},"tweenEasing":0},{"duration":8,"transform":{"skX":-27.94,"skY":-27.94},"tweenEasing":0},{"duration":0,"transform":{}}],"name":"bone29"},{"frame":[{"duration":2,"transform":{},"tweenEasing":0},{"duration":2,"transform":{"y":-2.71,"skX":-5.1,"skY":-5.1,"x":0.95},"tweenEasing":0},{"duration":3,"transform":{"y":-2.71,"skX":2.65,"skY":2.65,"x":0.95},"tweenEasing":0},{"duration":8,"transform":{"y":-2.71,"skX":-5.1,"skY":-5.1,"x":0.95},"tweenEasing":0},{"duration":0,"transform":{}}],"name":"bone3"},{"frame":[{"duration":2,"transform":{},"tweenEasing":0},{"duration":2,"transform":{"x":-10},"tweenEasing":0},{"duration":3,"transform":{"y":-1,"skX":0.4,"skY":0.4,"x":0.79},"tweenEasing":0},{"duration":8,"transform":{"skX":0.4,"skY":0.4,"x":-10},"tweenEasing":0},{"duration":0,"transform":{}}],"name":"bone"},{"frame":[{"duration":15,"transform":{}},{"duration":0,"transform":{}}],"name":"4"},{"frame":[{"duration":15,"transform":{}},{"duration":0,"transform":{}}],"name":"3"},{"frame":[{"duration":15,"transform":{}},{"duration":0,"transform":{}}],"name":"2"},{"frame":[{"duration":15,"transform":{}},{"duration":0,"transform":{}}],"name":"1"},{"frame":[{"duration":15,"transform":{}},{"duration":0,"transform":{}}],"name":"bone32"}],"slot":[{"frame":[{"tweenEasing":0,"duration":15},{"tweenEasing":null,"duration":0}],"name":"houbai"},{"frame":[{"tweenEasing":0,"duration":15},{"tweenEasing":null,"duration":0}],"name":"pifeng"},{"frame":[{"tweenEasing":0,"duration":15},{"tweenEasing":null,"duration":0}],"name":"shenti"},{"frame":[{"tweenEasing":0,"duration":15,"displayIndex":-1},{"tweenEasing":null,"duration":0,"displayIndex":-1}],"name":"shihua"},{"frame":[{"tweenEasing":0,"duration":15},{"tweenEasing":null,"duration":0}],"name":"tou"},{"frame":[{"tweenEasing":null,"duration":15}],"name":"ty"},{"frame":[{"tweenEasing":0,"duration":15},{"tweenEasing":null,"duration":0}],"name":"wuqi"},{"frame":[{"tweenEasing":0,"duration":15},{"tweenEasing":null,"duration":0}],"name":"youbi"},{"frame":[{"tweenEasing":0,"duration":15},{"tweenEasing":null,"duration":0}],"name":"youdatui"},{"frame":[{"tweenEasing":0,"duration":15},{"tweenEasing":null,"duration":0}],"name":"youjian"},{"frame":[{"tweenEasing":0,"duration":15},{"tweenEasing":null,"duration":0}],"name":"youjianhou"},{"frame":[{"tweenEasing":0,"duration":15},{"tweenEasing":null,"duration":0}],"name":"youjiao"},{"frame":[{"tweenEasing":0,"duration":15},{"tweenEasing":null,"duration":0}],"name":"youshou"},{"frame":[{"tweenEasing":0,"duration":15},{"tweenEasing":null,"duration":0}],"name":"youwan"},{"frame":[{"tweenEasing":0,"duration":15},{"tweenEasing":null,"duration":0}],"name":"youxiaotui"},{"frame":[{"tweenEasing":0,"duration":15},{"tweenEasing":null,"duration":0}],"name":"zuobi"},{"frame":[{"tweenEasing":0,"duration":15},{"tweenEasing":null,"duration":0}],"name":"zuodatui"},{"frame":[{"tweenEasing":0,"duration":15},{"tweenEasing":null,"duration":0}],"name":"zuojiao"},{"frame":[{"tweenEasing":0,"duration":15},{"tweenEasing":null,"duration":0}],"name":"zuowan"},{"frame":[{"tweenEasing":0,"duration":15},{"tweenEasing":null,"duration":0}],"name":"zuoxiaotui"}],"ffd":[{"frame":[{"duration":15,"offset":0,"vertices":[],"tweenEasing":null},{"duration":0,"offset":0,"vertices":[],"tweenEasing":null}],"scale":1,"slot":"houbai","offset":0,"name":"houbai","skin":""},{"frame":[{"duration":15,"offset":0,"vertices":[],"tweenEasing":null},{"duration":0,"offset":0,"vertices":[],"tweenEasing":null}],"scale":1,"slot":"pifeng","offset":0,"name":"pifeng","skin":""},{"frame":[{"duration":15,"offset":0,"vertices":[],"tweenEasing":null},{"duration":0,"offset":0,"vertices":[],"tweenEasing":null}],"scale":1,"slot":"shenti","offset":0,"name":"shenti","skin":""},{"frame":[{"duration":2,"offset":0,"vertices":[],"tweenEasing":0},{"duration":13,"offset":72,"vertices":[-0.04,0.1,-2.11,4.29,0.68,-1.25,1.99,-4.08,0.85,1.46,0.04,4.13,-0.48,-1.69,-0.53,-1.35],"tweenEasing":0},{"duration":0,"offset":0,"vertices":[],"tweenEasing":null}],"scale":1,"slot":"tou","offset":0,"name":"tou","skin":""}],"name":"byatk"},{"duration":27,"frame":[],"ik":[],"bone":[{"frame":[{"duration":27,"transform":{}}],"name":"root"},{"frame":[{"duration":2,"transform":{},"tweenEasing":0},{"duration":11,"transform":{"skX":7.65,"skY":7.65},"tweenEasing":0},{"duration":3,"transform":{"skX":-19.77,"skY":-19.77},"tweenEasing":0},{"duration":11,"transform":{"skX":-8.11,"skY":-8.11}}],"name":"bone2"},{"frame":[{"duration":2,"transform":{},"tweenEasing":0},{"duration":11,"transform":{"y":-11.2,"skX":31.18,"skY":31.18,"x":0.37},"tweenEasing":0},{"duration":4,"transform":{"y":-11.2,"skX":-27.69,"skY":-27.69,"x":0.37},"tweenEasing":0},{"duration":3,"transform":{"y":-11.2,"skX":14.55,"skY":14.55,"x":0.37},"tweenEasing":0},{"duration":3,"transform":{"y":-11.2,"skX":-0.6,"skY":-0.6,"x":0.37},"tweenEasing":0},{"duration":4,"transform":{"y":-11.2,"skX":7.2,"skY":7.2,"x":0.37}}],"name":"bone4"},{"frame":[{"duration":2,"transform":{},"curve":[0.0625,0,0.9375,1]},{"duration":6,"transform":{"skX":-347.54,"skY":-347.54},"curve":[0.25,0,0.75,1]},{"duration":5,"transform":{"skX":-1.97,"skY":-1.97},"tweenEasing":0},{"duration":6,"transform":{"skX":-331.41,"skY":-331.41},"curve":[0.25,0,0.75,1]},{"duration":7,"transform":{"skX":-11.55,"skY":-11.55},"tweenEasing":0},{"duration":1,"transform":{"skX":-10.22,"skY":-10.22}}],"name":"bone5"},{"frame":[{"duration":7,"transform":{},"tweenEasing":0},{"duration":6,"transform":{"skX":-0.4,"skY":-0.4},"tweenEasing":0},{"duration":3,"transform":{"skX":-4.82,"skY":-4.82},"tweenEasing":0},{"duration":3,"transform":{"skX":320.29,"skY":320.29},"tweenEasing":0},{"duration":3,"transform":{"skX":314.35,"skY":314.35},"tweenEasing":0},{"duration":5,"transform":{"skX":300.08,"skY":300.08}}],"name":"bone13"},{"frame":[{"duration":7,"transform":{},"tweenEasing":0},{"duration":6,"transform":{"skX":19.54,"skY":19.54},"tweenEasing":0},{"duration":2,"transform":{"skX":55.14,"skY":55.14},"tweenEasing":0},{"duration":7,"transform":{"skX":46.73,"skY":46.73},"tweenEasing":0},{"duration":5,"transform":{"skX":49.38,"skY":49.38}}],"name":"bone14"},{"frame":[{"duration":27,"transform":{}}],"name":"bone15"},{"frame":[{"duration":2,"transform":{},"tweenEasing":0},{"duration":6,"transform":{"skX":-25.32,"skY":-25.32},"tweenEasing":0},{"duration":5,"transform":{"skX":-318.19,"skY":-318.19},"tweenEasing":0},{"duration":14,"transform":{"skX":-279.82,"skY":-279.82}}],"name":"bone16"},{"frame":[{"duration":2,"transform":{},"tweenEasing":0},{"duration":25,"transform":{"y":2.46,"skX":-20.96,"skY":-20.96,"x":-6.79}}],"name":"bone17"},{"frame":[{"duration":27,"transform":{}}],"name":"bone31"},{"frame":[{"duration":27,"transform":{}}],"name":"bone25"},{"frame":[{"duration":27,"transform":{}}],"name":"bone26"},{"frame":[{"duration":27,"transform":{}}],"name":"bone19"},{"frame":[{"duration":27,"transform":{}}],"name":"bone20"},{"frame":[{"duration":27,"transform":{}}],"name":"bone21"},{"frame":[{"duration":27,"transform":{}}],"name":"bone22"},{"frame":[{"duration":27,"transform":{}}],"name":"bone23"},{"frame":[{"duration":27,"transform":{}}],"name":"bone24"},{"frame":[{"duration":27,"transform":{}}],"name":"bone28"},{"frame":[{"duration":27,"transform":{}}],"name":"bone27"},{"frame":[{"duration":2,"transform":{},"tweenEasing":0},{"duration":25,"transform":{"skX":45.11,"skY":45.11}}],"name":"bone18"},{"frame":[{"duration":2,"transform":{},"tweenEasing":0},{"duration":3,"transform":{"skX":-11.92,"skY":-11.92},"tweenEasing":0},{"duration":3,"transform":{"skX":-31.15,"skY":-31.15},"tweenEasing":0},{"duration":5,"transform":{"skX":37.44,"skY":37.44},"tweenEasing":0},{"duration":14,"transform":{"skX":-23.66,"skY":-23.66},"tweenEasing":0},{"duration":0,"transform":{"skX":-3.6,"skY":-3.6}}],"name":"bone12"},{"frame":[{"duration":2,"transform":{},"tweenEasing":0},{"duration":3,"transform":{"skX":-18.94,"skY":-18.94},"tweenEasing":0},{"duration":3,"transform":{"skX":-19.46,"skY":-19.46},"tweenEasing":0},{"duration":5,"transform":{"skX":26.49,"skY":26.49},"tweenEasing":0},{"duration":14,"transform":{"skX":32.04,"skY":32.04},"tweenEasing":0},{"duration":0,"transform":{"skX":0.81,"skY":0.81}}],"name":"bone11"},{"frame":[{"duration":2,"transform":{},"tweenEasing":0},{"duration":3,"transform":{"skX":-46.83,"skY":-46.83},"tweenEasing":0},{"duration":3,"transform":{"skX":12.7,"skY":12.7},"tweenEasing":0},{"duration":5,"transform":{"skX":33.64,"skY":33.64},"tweenEasing":0},{"duration":14,"transform":{"skX":42.84,"skY":42.84},"tweenEasing":0},{"duration":0,"transform":{"skX":20.74,"skY":20.74}}],"name":"bone10"},{"frame":[{"duration":2,"transform":{},"tweenEasing":0},{"duration":3,"transform":{"y":-6.65,"skX":-6.84,"skY":-6.84,"x":16.23},"tweenEasing":0},{"duration":3,"transform":{"y":-6.65,"skX":-3.87,"skY":-3.87,"x":16.23},"tweenEasing":0},{"duration":19,"transform":{"y":-0.31,"skX":-12.6,"skY":-12.6,"x":14.71},"tweenEasing":0},{"duration":0,"transform":{"y":-0.31,"skX":-353.53,"skY":-353.53,"x":14.71}}],"name":"bone9"},{"frame":[{"duration":3,"transform":{},"curve":[0.0625,0,0.9375,1]},{"duration":6,"transform":{"skX":-42.08,"skY":-42.08},"curve":[0.25,0,0.75,1]},{"duration":5,"transform":{"skX":33.32,"skY":33.32},"tweenEasing":0},{"duration":6,"transform":{"skX":-42.08,"skY":-42.08},"curve":[0.25,0,0.75,1]},{"duration":6,"transform":{"skX":33.32,"skY":33.32},"tweenEasing":0},{"duration":1,"transform":{"skX":-33.49,"skY":-33.49}}],"name":"bone8"},{"frame":[{"duration":2,"transform":{},"curve":[0.0625,0,0.9375,1]},{"duration":6,"transform":{"skX":-27.31,"skY":-27.31},"curve":[0.25,0,0.75,1]},{"duration":5,"transform":{"skX":26.64,"skY":26.64},"tweenEasing":0},{"duration":6,"transform":{"skX":-27.31,"skY":-27.31},"curve":[0.25,0,0.75,1]},{"duration":7,"transform":{"skX":26.64,"skY":26.64},"tweenEasing":0},{"duration":1,"transform":{"skX":-35.82,"skY":-35.82}}],"name":"bone7"},{"frame":[{"duration":1,"transform":{},"curve":[0.0625,0,0.9375,1]},{"duration":5,"transform":{"skX":-29.37,"skY":-29.37},"curve":[0.25,0,0.75,1]},{"duration":6,"transform":{"skX":18.84,"skY":18.84},"tweenEasing":0},{"duration":5,"transform":{"skX":-29.37,"skY":-29.37},"curve":[0.25,0,0.75,1]},{"duration":9,"transform":{"skX":-12.58,"skY":-12.58},"tweenEasing":0},{"duration":1,"transform":{"skX":-10.33,"skY":-10.33}}],"name":"bone6"},{"frame":[{"duration":15,"transform":{},"tweenEasing":0},{"duration":5,"transform":{"skX":-66.54,"skY":-66.54},"tweenEasing":0},{"duration":7,"transform":{"y":9.54,"skX":44.32,"skY":44.32,"x":12.56}}],"name":"bone30"},{"frame":[{"duration":5,"transform":{},"tweenEasing":0},{"duration":6,"transform":{"skX":45.23,"skY":45.23},"tweenEasing":0},{"duration":6,"transform":{"skX":-30.44,"skY":-30.44},"tweenEasing":0},{"duration":5,"transform":{"skX":13.1,"skY":13.1},"tweenEasing":0},{"duration":5,"transform":{"skX":-20.66,"skY":-20.66}}],"name":"bone29"},{"frame":[{"duration":2,"transform":{},"tweenEasing":0},{"duration":11,"transform":{"skX":31.21,"skY":31.21},"tweenEasing":0},{"duration":3,"transform":{"skX":-24.11,"skY":-24.11},"tweenEasing":0},{"duration":3,"transform":{"skX":5.69,"skY":5.69},"tweenEasing":0},{"duration":3,"transform":{"skX":-10.08,"skY":-10.08},"tweenEasing":0},{"duration":5,"transform":{"skX":-1.08,"skY":-1.08}}],"name":"bone3"},{"frame":[{"duration":2,"transform":{},"tweenEasing":0},{"duration":6,"transform":{"y":11.33,"skX":-8.33,"skY":-8.33,"x":-20.29},"tweenEasing":0},{"duration":5,"transform":{"y":-6.98,"skX":1.84,"skY":1.84,"x":14.72},"tweenEasing":0},{"duration":3,"transform":{"y":33.29,"skX":89.38,"skY":89.38,"x":48},"tweenEasing":0},{"duration":3,"transform":{"y":22.69,"skX":89.38,"skY":89.38,"x":53.08},"tweenEasing":0},{"duration":8,"transform":{"y":31.17,"skX":89.38,"skY":89.38,"x":61.56}}],"name":"bone"},{"frame":[{"duration":27,"transform":{}}],"name":"4"},{"frame":[{"duration":8,"transform":{},"tweenEasing":0},{"duration":5,"transform":{},"tweenEasing":0},{"duration":4,"transform":{"y":2.34,"skX":101.64,"skY":101.64,"x":-16.93},"tweenEasing":0},{"duration":3,"transform":{"y":-1.09,"skX":125.28,"skY":125.28,"x":-9.19},"tweenEasing":0},{"duration":7,"transform":{"y":3.2,"skX":125.28,"skY":125.28,"x":-6.61}}],"name":"3"},{"frame":[{"duration":27,"transform":{}}],"name":"2"},{"frame":[{"duration":6,"transform":{},"tweenEasing":0},{"duration":2,"transform":{},"tweenEasing":0},{"duration":5,"transform":{"y":-7.51,"skX":-24.05,"skY":-24.05,"x":14.18},"tweenEasing":0},{"duration":3,"transform":{"y":-11.24,"skX":16.14,"skY":16.14,"x":41.29},"tweenEasing":0},{"duration":2,"transform":{"y":-11.24,"skX":36.78,"skY":36.78,"x":41.29},"tweenEasing":0},{"duration":2,"transform":{"y":-2.64,"skX":36.78,"skY":36.78,"x":52.76},"tweenEasing":0},{"duration":7,"transform":{"y":-2.64,"skX":-7.16,"skY":-7.16,"x":52.76}}],"name":"1"},{"frame":[{"duration":7,"transform":{}},{"duration":8,"transform":{},"tweenEasing":0},{"duration":12,"transform":{"scX":1.365,"scY":1.252,"x":105.27}}],"name":"bone32"}],"slot":[{"frame":[{"tweenEasing":null,"duration":27}],"name":"houbai"},{"frame":[{"tweenEasing":null,"duration":27}],"name":"pifeng"},{"frame":[{"tweenEasing":null,"duration":27}],"name":"shenti"},{"frame":[{"tweenEasing":null,"duration":27,"displayIndex":-1}],"name":"shihua"},{"frame":[{"tweenEasing":null,"duration":27}],"name":"tou"},{"frame":[{"tweenEasing":null,"duration":27}],"name":"ty"},{"frame":[{"tweenEasing":null,"duration":27}],"name":"wuqi"},{"frame":[{"tweenEasing":null,"duration":27}],"name":"youbi"},{"frame":[{"tweenEasing":null,"duration":27}],"name":"youdatui"},{"frame":[{"tweenEasing":null,"duration":27}],"name":"youjian"},{"frame":[{"tweenEasing":null,"duration":27}],"name":"youjianhou"},{"frame":[{"tweenEasing":null,"duration":27}],"name":"youjiao"},{"frame":[{"tweenEasing":null,"duration":27}],"name":"youshou"},{"frame":[{"tweenEasing":null,"duration":27}],"name":"youwan"},{"frame":[{"tweenEasing":null,"duration":27}],"name":"youxiaotui"},{"frame":[{"tweenEasing":null,"duration":27}],"name":"zuobi"},{"frame":[{"tweenEasing":null,"duration":27}],"name":"zuodatui"},{"frame":[{"tweenEasing":null,"duration":27}],"name":"zuojiao"},{"frame":[{"tweenEasing":null,"duration":27}],"name":"zuowan"},{"frame":[{"tweenEasing":null,"duration":27}],"name":"zuoxiaotui"}],"ffd":[{"frame":[{"duration":27,"offset":0,"vertices":[],"tweenEasing":null}],"scale":1,"slot":"houbai","offset":0,"name":"houbai","skin":""},{"frame":[{"duration":27,"offset":0,"vertices":[],"tweenEasing":null}],"scale":1,"slot":"pifeng","offset":0,"name":"pifeng","skin":""},{"frame":[{"duration":27,"offset":0,"vertices":[],"tweenEasing":null}],"scale":1,"slot":"shenti","offset":0,"name":"shenti","skin":""},{"frame":[{"duration":1,"offset":0,"vertices":[],"tweenEasing":0},{"duration":26,"offset":72,"vertices":[-0.04,0.1,-2.11,4.29,0.68,-1.25,1.99,-4.08,0.85,1.46,0.04,4.13,-0.48,-1.69,-0.53,-1.35],"tweenEasing":null}],"scale":1,"slot":"tou","offset":0,"name":"tou","skin":""}],"name":"die"},{"duration":40,"frame":[],"ik":[],"bone":[{"frame":[{"duration":40,"transform":{}},{"duration":0,"transform":{}}],"name":"root"},{"frame":[{"duration":20,"transform":{},"curve":[0.25,0,0.75,1]},{"duration":20,"transform":{"y":1},"curve":[0.25,0,0.75,1]},{"duration":0,"transform":{}}],"name":"bone2"},{"frame":[{"duration":8,"transform":{},"curve":[0.316,0.51,0.75,1]},{"duration":20,"transform":{"skX":-2.62,"skY":-2.62},"curve":[0.25,0,0.75,1]},{"duration":12,"transform":{"skX":2.63,"skY":2.63},"curve":[0.25,0,0.591,0.51]},{"duration":0,"transform":{}}],"name":"bone4"},{"frame":[{"duration":20,"transform":{},"curve":[0.25,0,0.75,1]},{"duration":20,"transform":{"skX":-354.12,"skY":-354.12},"curve":[0.25,0,0.75,1]},{"duration":0,"transform":{}}],"name":"bone5"},{"frame":[{"duration":20,"transform":{},"curve":[0.25,0,0.75,1]},{"duration":20,"transform":{"skX":7.04,"skY":7.04},"curve":[0.25,0,0.75,1]},{"duration":0,"transform":{}}],"name":"bone13"},{"frame":[{"duration":20,"transform":{},"curve":[0.25,0,0.75,1]},{"duration":20,"transform":{"skX":5.82,"skY":5.82},"curve":[0.25,0,0.75,1]},{"duration":0,"transform":{}}],"name":"bone14"},{"frame":[{"duration":40,"transform":{}},{"duration":0,"transform":{}}],"name":"bone15"},{"frame":[{"duration":20,"transform":{},"curve":[0.25,0,0.75,1]},{"duration":20,"transform":{"skX":-4.46,"skY":-4.46},"curve":[0.25,0,0.75,1]},{"duration":0,"transform":{}}],"name":"bone16"},{"frame":[{"duration":8,"transform":{},"curve":[0.373,0.5,0.75,1]},{"duration":20,"transform":{"skX":2,"skY":2},"curve":[0.25,0,0.75,1]},{"duration":12,"transform":{"skX":-2.24,"skY":-2.24},"curve":[0.25,0,0.508,0.47]},{"duration":0,"transform":{}}],"name":"bone17"},{"frame":[{"duration":40,"transform":{}},{"duration":0,"transform":{}}],"name":"bone31"},{"frame":[{"duration":40,"transform":{}},{"duration":0,"transform":{}}],"name":"bone25"},{"frame":[{"duration":40,"transform":{}},{"duration":0,"transform":{}}],"name":"bone26"},{"frame":[{"duration":40,"transform":{}},{"duration":0,"transform":{}}],"name":"bone19"},{"frame":[{"duration":40,"transform":{}},{"duration":0,"transform":{}}],"name":"bone20"},{"frame":[{"duration":40,"transform":{}},{"duration":0,"transform":{}}],"name":"bone21"},{"frame":[{"duration":40,"transform":{}},{"duration":0,"transform":{}}],"name":"bone22"},{"frame":[{"duration":40,"transform":{}},{"duration":0,"transform":{}}],"name":"bone23"},{"frame":[{"duration":40,"transform":{}},{"duration":0,"transform":{}}],"name":"bone24"},{"frame":[{"duration":40,"transform":{}},{"duration":0,"transform":{}}],"name":"bone28"},{"frame":[{"duration":40,"transform":{}},{"duration":0,"transform":{}}],"name":"bone27"},{"frame":[{"duration":40,"transform":{}},{"duration":0,"transform":{}}],"name":"bone18"},{"frame":[{"duration":20,"transform":{},"curve":[0.25,0,0.75,1]},{"duration":20,"transform":{"skX":21.23,"skY":21.23},"curve":[0.25,0,0.75,1]},{"duration":0,"transform":{}}],"name":"bone12"},{"frame":[{"duration":14,"transform":{},"curve":[0.342,0.5,0.75,1]},{"duration":20,"transform":{"skX":8.82,"skY":8.82},"curve":[0.25,0,0.75,1]},{"duration":6,"transform":{"skX":-10.34,"skY":-10.34},"curve":[0.25,0,0.57,0.48]},{"duration":0,"transform":{}}],"name":"bone11"},{"frame":[{"duration":8,"transform":{},"curve":[0.342,0.5,0.75,1]},{"duration":20,"transform":{"skX":8.96,"skY":8.96},"curve":[0.25,0,0.75,1]},{"duration":12,"transform":{"skX":-5.56,"skY":-5.56},"curve":[0.25,0,0.57,0.48]},{"duration":0,"transform":{}}],"name":"bone10"},{"frame":[{"duration":20,"transform":{},"curve":[0.25,0,0.75,1]},{"duration":20,"transform":{"skX":-6.91,"skY":-6.91},"curve":[0.25,0,0.75,1]},{"duration":0,"transform":{}}],"name":"bone9"},{"frame":[{"duration":20,"transform":{},"curve":[0.25,0,0.75,1]},{"duration":20,"transform":{"skX":-28.23,"skY":-28.23},"curve":[0.25,0,0.75,1]},{"duration":0,"transform":{}}],"name":"bone8"},{"frame":[{"duration":14,"transform":{},"curve":[0.393,0.52,0.75,1]},{"duration":20,"transform":{"skX":-12.53,"skY":-12.53},"curve":[0.25,0,0.75,1]},{"duration":6,"transform":{"skX":10.62,"skY":10.62},"curve":[0.25,0,0.555,0.46]},{"duration":0,"transform":{}}],"name":"bone7"},{"frame":[{"duration":8,"transform":{},"curve":[0.393,0.52,0.75,1]},{"duration":20,"transform":{"skX":-7.86,"skY":-7.86},"curve":[0.25,0,0.75,1]},{"duration":12,"transform":{"skX":7.57,"skY":7.57},"curve":[0.25,0,0.555,0.46]},{"duration":0,"transform":{}}],"name":"bone6"},{"frame":[{"duration":19,"transform":{},"curve":[0.25,0,0.75,1]},{"duration":21,"transform":{"skX":-29.29,"skY":-29.29},"curve":[0.25,0,0.75,1]},{"duration":0,"transform":{}}],"name":"bone30"},{"frame":[{"duration":12,"transform":{},"curve":[0.25,0,0.75,1]},{"duration":28,"transform":{"skX":-15.4,"skY":-15.4},"curve":[0.25,0,0.75,1]},{"duration":0,"transform":{}}],"name":"bone29"},{"frame":[{"duration":6,"transform":{},"curve":[0.3085,0.265,0.75,1]},{"duration":14,"transform":{"y":-0.18,"x":1.99},"curve":[0.25,0,0.75,1]},{"duration":6,"transform":{"y":-0.18,"skX":1.91,"skY":1.91,"x":1.99},"curve":[0.25,0,0.75,1]},{"duration":14,"transform":{"y":0.28,"skX":1.91,"skY":1.91,"x":-2.98},"curve":[0.25,0,0.514,0.46]},{"duration":0,"transform":{}}],"name":"bone3"},{"frame":[{"duration":20,"transform":{},"curve":[0.25,0,0.75,1]},{"duration":20,"transform":{"y":3,"x":1.99},"curve":[0.25,0,0.75,1]},{"duration":0,"transform":{}}],"name":"bone"},{"frame":[{"duration":40,"transform":{}},{"duration":0,"transform":{}}],"name":"4"},{"frame":[{"duration":40,"transform":{}},{"duration":0,"transform":{}}],"name":"3"},{"frame":[{"duration":40,"transform":{}},{"duration":0,"transform":{}}],"name":"2"},{"frame":[{"duration":40,"transform":{}},{"duration":0,"transform":{}}],"name":"1"},{"frame":[{"duration":40,"transform":{}},{"duration":0,"transform":{}}],"name":"bone32"}],"slot":[{"frame":[{"tweenEasing":0,"duration":40,"displayIndex":-1},{"tweenEasing":null,"duration":0}],"name":"houbai"},{"frame":[{"tweenEasing":0,"duration":40,"displayIndex":-1},{"tweenEasing":null,"duration":0}],"name":"pifeng"},{"frame":[{"tweenEasing":0,"duration":40,"displayIndex":-1},{"tweenEasing":null,"duration":0}],"name":"shenti"},{"frame":[{"tweenEasing":0,"duration":40},{"tweenEasing":null,"duration":0,"displayIndex":-1}],"name":"shihua"},{"frame":[{"tweenEasing":0,"duration":40,"displayIndex":-1},{"tweenEasing":null,"duration":0}],"name":"tou"},{"frame":[{"tweenEasing":null,"duration":40,"displayIndex":-1}],"name":"ty"},{"frame":[{"tweenEasing":0,"duration":40,"displayIndex":-1},{"tweenEasing":null,"duration":0}],"name":"wuqi"},{"frame":[{"tweenEasing":0,"duration":40,"displayIndex":-1},{"tweenEasing":null,"duration":0}],"name":"youbi"},{"frame":[{"tweenEasing":0,"duration":40,"displayIndex":-1},{"tweenEasing":null,"duration":0}],"name":"youdatui"},{"frame":[{"tweenEasing":0,"duration":40,"displayIndex":-1},{"tweenEasing":null,"duration":0}],"name":"youjian"},{"frame":[{"tweenEasing":0,"duration":40,"displayIndex":-1},{"tweenEasing":null,"duration":0}],"name":"youjianhou"},{"frame":[{"tweenEasing":0,"duration":40,"displayIndex":-1},{"tweenEasing":null,"duration":0}],"name":"youjiao"},{"frame":[{"tweenEasing":0,"duration":40,"displayIndex":-1},{"tweenEasing":null,"duration":0}],"name":"youshou"},{"frame":[{"tweenEasing":0,"duration":40,"displayIndex":-1},{"tweenEasing":null,"duration":0}],"name":"youwan"},{"frame":[{"tweenEasing":0,"duration":40,"displayIndex":-1},{"tweenEasing":null,"duration":0}],"name":"youxiaotui"},{"frame":[{"tweenEasing":0,"duration":40,"displayIndex":-1},{"tweenEasing":null,"duration":0}],"name":"zuobi"},{"frame":[{"tweenEasing":0,"duration":40,"displayIndex":-1},{"tweenEasing":null,"duration":0}],"name":"zuodatui"},{"frame":[{"tweenEasing":0,"duration":40,"displayIndex":-1},{"tweenEasing":null,"duration":0}],"name":"zuojiao"},{"frame":[{"tweenEasing":0,"duration":40,"displayIndex":-1},{"tweenEasing":null,"duration":0}],"name":"zuowan"},{"frame":[{"tweenEasing":0,"duration":40,"displayIndex":-1},{"tweenEasing":null,"duration":0}],"name":"zuoxiaotui"}],"ffd":[{"frame":[{"duration":40,"offset":0,"vertices":[],"tweenEasing":null},{"duration":0,"offset":0,"vertices":[],"tweenEasing":null}],"scale":1,"slot":"houbai","offset":0,"name":"houbai","skin":""},{"frame":[{"duration":40,"offset":0,"vertices":[],"tweenEasing":null},{"duration":0,"offset":0,"vertices":[],"tweenEasing":null}],"scale":1,"slot":"pifeng","offset":0,"name":"pifeng","skin":""},{"frame":[{"duration":40,"offset":0,"vertices":[],"tweenEasing":null},{"duration":0,"offset":0,"vertices":[],"tweenEasing":null}],"scale":1,"slot":"shenti","offset":0,"name":"shenti","skin":""},{"frame":[{"duration":40,"offset":0,"vertices":[],"tweenEasing":null},{"duration":0,"offset":0,"vertices":[],"tweenEasing":null}],"scale":1,"slot":"tou","offset":0,"name":"tou","skin":""}],"name":"shihua"},{"duration":40,"frame":[],"ik":[],"bone":[{"frame":[{"duration":40,"transform":{}},{"duration":0,"transform":{}}],"name":"root"},{"frame":[{"duration":20,"transform":{},"curve":[0.25,0,0.75,1]},{"duration":20,"transform":{"y":1},"curve":[0.25,0,0.75,1]},{"duration":0,"transform":{}}],"name":"bone2"},{"frame":[{"duration":8,"transform":{},"curve":[0.316,0.51,0.75,1]},{"duration":20,"transform":{"skX":-2.62,"skY":-2.62},"curve":[0.25,0,0.75,1]},{"duration":12,"transform":{"skX":2.63,"skY":2.63},"curve":[0.25,0,0.591,0.51]},{"duration":0,"transform":{}}],"name":"bone4"},{"frame":[{"duration":20,"transform":{},"curve":[0.25,0,0.75,1]},{"duration":20,"transform":{"skX":-354.12,"skY":-354.12},"curve":[0.25,0,0.75,1]},{"duration":0,"transform":{}}],"name":"bone5"},{"frame":[{"duration":20,"transform":{},"curve":[0.25,0,0.75,1]},{"duration":20,"transform":{"skX":7.04,"skY":7.04},"curve":[0.25,0,0.75,1]},{"duration":0,"transform":{}}],"name":"bone13"},{"frame":[{"duration":20,"transform":{},"curve":[0.25,0,0.75,1]},{"duration":20,"transform":{"skX":5.82,"skY":5.82},"curve":[0.25,0,0.75,1]},{"duration":0,"transform":{}}],"name":"bone14"},{"frame":[{"duration":40,"transform":{}},{"duration":0,"transform":{}}],"name":"bone15"},{"frame":[{"duration":20,"transform":{},"curve":[0.25,0,0.75,1]},{"duration":20,"transform":{"skX":-4.46,"skY":-4.46},"curve":[0.25,0,0.75,1]},{"duration":0,"transform":{}}],"name":"bone16"},{"frame":[{"duration":8,"transform":{},"curve":[0.373,0.5,0.75,1]},{"duration":20,"transform":{"skX":2,"skY":2},"curve":[0.25,0,0.75,1]},{"duration":12,"transform":{"skX":-2.24,"skY":-2.24},"curve":[0.25,0,0.508,0.47]},{"duration":0,"transform":{}}],"name":"bone17"},{"frame":[{"duration":40,"transform":{}},{"duration":0,"transform":{}}],"name":"bone31"},{"frame":[{"duration":40,"transform":{}},{"duration":0,"transform":{}}],"name":"bone25"},{"frame":[{"duration":40,"transform":{}},{"duration":0,"transform":{}}],"name":"bone26"},{"frame":[{"duration":40,"transform":{}},{"duration":0,"transform":{}}],"name":"bone19"},{"frame":[{"duration":40,"transform":{}},{"duration":0,"transform":{}}],"name":"bone20"},{"frame":[{"duration":40,"transform":{}},{"duration":0,"transform":{}}],"name":"bone21"},{"frame":[{"duration":40,"transform":{}},{"duration":0,"transform":{}}],"name":"bone22"},{"frame":[{"duration":40,"transform":{}},{"duration":0,"transform":{}}],"name":"bone23"},{"frame":[{"duration":40,"transform":{}},{"duration":0,"transform":{}}],"name":"bone24"},{"frame":[{"duration":40,"transform":{}},{"duration":0,"transform":{}}],"name":"bone28"},{"frame":[{"duration":40,"transform":{}},{"duration":0,"transform":{}}],"name":"bone27"},{"frame":[{"duration":40,"transform":{}},{"duration":0,"transform":{}}],"name":"bone18"},{"frame":[{"duration":20,"transform":{},"curve":[0.25,0,0.75,1]},{"duration":20,"transform":{"skX":21.23,"skY":21.23},"curve":[0.25,0,0.75,1]},{"duration":0,"transform":{}}],"name":"bone12"},{"frame":[{"duration":14,"transform":{},"curve":[0.342,0.5,0.75,1]},{"duration":20,"transform":{"skX":8.82,"skY":8.82},"curve":[0.25,0,0.75,1]},{"duration":6,"transform":{"skX":-10.34,"skY":-10.34},"curve":[0.25,0,0.57,0.48]},{"duration":0,"transform":{}}],"name":"bone11"},{"frame":[{"duration":8,"transform":{},"curve":[0.342,0.5,0.75,1]},{"duration":20,"transform":{"skX":8.96,"skY":8.96},"curve":[0.25,0,0.75,1]},{"duration":12,"transform":{"skX":-5.56,"skY":-5.56},"curve":[0.25,0,0.57,0.48]},{"duration":0,"transform":{}}],"name":"bone10"},{"frame":[{"duration":20,"transform":{},"curve":[0.25,0,0.75,1]},{"duration":20,"transform":{"skX":-6.91,"skY":-6.91},"curve":[0.25,0,0.75,1]},{"duration":0,"transform":{}}],"name":"bone9"},{"frame":[{"duration":20,"transform":{},"curve":[0.25,0,0.75,1]},{"duration":20,"transform":{"skX":-28.23,"skY":-28.23},"curve":[0.25,0,0.75,1]},{"duration":0,"transform":{}}],"name":"bone8"},{"frame":[{"duration":14,"transform":{},"curve":[0.393,0.52,0.75,1]},{"duration":20,"transform":{"skX":-12.53,"skY":-12.53},"curve":[0.25,0,0.75,1]},{"duration":6,"transform":{"skX":10.62,"skY":10.62},"curve":[0.25,0,0.555,0.46]},{"duration":0,"transform":{}}],"name":"bone7"},{"frame":[{"duration":8,"transform":{},"curve":[0.393,0.52,0.75,1]},{"duration":20,"transform":{"skX":-7.86,"skY":-7.86},"curve":[0.25,0,0.75,1]},{"duration":12,"transform":{"skX":7.57,"skY":7.57},"curve":[0.25,0,0.555,0.46]},{"duration":0,"transform":{}}],"name":"bone6"},{"frame":[{"duration":19,"transform":{},"curve":[0.25,0,0.75,1]},{"duration":21,"transform":{"skX":-29.29,"skY":-29.29},"curve":[0.25,0,0.75,1]},{"duration":0,"transform":{}}],"name":"bone30"},{"frame":[{"duration":12,"transform":{},"curve":[0.25,0,0.75,1]},{"duration":28,"transform":{"skX":-15.4,"skY":-15.4},"curve":[0.25,0,0.75,1]},{"duration":0,"transform":{}}],"name":"bone29"},{"frame":[{"duration":6,"transform":{},"curve":[0.3085,0.265,0.75,1]},{"duration":14,"transform":{"y":-0.18,"x":1.99},"curve":[0.25,0,0.75,1]},{"duration":6,"transform":{"y":-0.18,"skX":1.91,"skY":1.91,"x":1.99},"curve":[0.25,0,0.75,1]},{"duration":14,"transform":{"y":0.28,"skX":1.91,"skY":1.91,"x":-2.98},"curve":[0.25,0,0.514,0.46]},{"duration":0,"transform":{}}],"name":"bone3"},{"frame":[{"duration":20,"transform":{},"curve":[0.25,0,0.75,1]},{"duration":20,"transform":{"y":3,"x":1.99},"curve":[0.25,0,0.75,1]},{"duration":0,"transform":{}}],"name":"bone"},{"frame":[{"duration":40,"transform":{}},{"duration":0,"transform":{}}],"name":"4"},{"frame":[{"duration":40,"transform":{}},{"duration":0,"transform":{}}],"name":"3"},{"frame":[{"duration":40,"transform":{}},{"duration":0,"transform":{}}],"name":"2"},{"frame":[{"duration":40,"transform":{}},{"duration":0,"transform":{}}],"name":"1"},{"frame":[{"duration":40,"transform":{}},{"duration":0,"transform":{}}],"name":"bone32"}],"slot":[{"frame":[{"tweenEasing":0,"duration":40},{"tweenEasing":null,"duration":0}],"name":"houbai"},{"frame":[{"tweenEasing":0,"duration":40},{"tweenEasing":null,"duration":0}],"name":"pifeng"},{"frame":[{"tweenEasing":0,"duration":40},{"tweenEasing":null,"duration":0}],"name":"shenti"},{"frame":[{"tweenEasing":0,"duration":40,"displayIndex":-1},{"tweenEasing":null,"duration":0,"displayIndex":-1}],"name":"shihua"},{"frame":[{"tweenEasing":0,"duration":40},{"tweenEasing":null,"duration":0}],"name":"tou"},{"frame":[{"tweenEasing":null,"duration":40}],"name":"ty"},{"frame":[{"tweenEasing":0,"duration":40},{"tweenEasing":null,"duration":0}],"name":"wuqi"},{"frame":[{"tweenEasing":0,"duration":40},{"tweenEasing":null,"duration":0}],"name":"youbi"},{"frame":[{"tweenEasing":0,"duration":40},{"tweenEasing":null,"duration":0}],"name":"youdatui"},{"frame":[{"tweenEasing":0,"duration":40},{"tweenEasing":null,"duration":0}],"name":"youjian"},{"frame":[{"tweenEasing":0,"duration":40},{"tweenEasing":null,"duration":0}],"name":"youjianhou"},{"frame":[{"tweenEasing":0,"duration":40},{"tweenEasing":null,"duration":0}],"name":"youjiao"},{"frame":[{"tweenEasing":0,"duration":40},{"tweenEasing":null,"duration":0}],"name":"youshou"},{"frame":[{"tweenEasing":0,"duration":40},{"tweenEasing":null,"duration":0}],"name":"youwan"},{"frame":[{"tweenEasing":0,"duration":40},{"tweenEasing":null,"duration":0}],"name":"youxiaotui"},{"frame":[{"tweenEasing":0,"duration":40},{"tweenEasing":null,"duration":0}],"name":"zuobi"},{"frame":[{"tweenEasing":0,"duration":40},{"tweenEasing":null,"duration":0}],"name":"zuodatui"},{"frame":[{"tweenEasing":0,"duration":40},{"tweenEasing":null,"duration":0}],"name":"zuojiao"},{"frame":[{"tweenEasing":0,"duration":40},{"tweenEasing":null,"duration":0}],"name":"zuowan"},{"frame":[{"tweenEasing":0,"duration":40},{"tweenEasing":null,"duration":0}],"name":"zuoxiaotui"}],"ffd":[{"frame":[{"duration":40,"offset":0,"vertices":[],"tweenEasing":null},{"duration":0,"offset":0,"vertices":[],"tweenEasing":null}],"scale":1,"slot":"houbai","offset":0,"name":"houbai","skin":""},{"frame":[{"duration":40,"offset":0,"vertices":[],"tweenEasing":null},{"duration":0,"offset":0,"vertices":[],"tweenEasing":null}],"scale":1,"slot":"pifeng","offset":0,"name":"pifeng","skin":""},{"frame":[{"duration":40,"offset":0,"vertices":[],"tweenEasing":null},{"duration":0,"offset":0,"vertices":[],"tweenEasing":null}],"scale":1,"slot":"shenti","offset":0,"name":"shenti","skin":""},{"frame":[{"duration":40,"offset":0,"vertices":[],"tweenEasing":null},{"duration":0,"offset":0,"vertices":[],"tweenEasing":null}],"scale":1,"slot":"tou","offset":0,"name":"tou","skin":""}],"name":"wait"}],"ik":[{"bendPositive":"false","chain":1,"name":"1","bone":"bone20","target":"1"},{"chain":1,"name":"3","bone":"bone23","target":"3"},{"bendPositive":"false","name":"2","bone":"bone21","target":"2"},{"bendPositive":"false","name":"4","bone":"bone24","target":"4"}],"frameRate":30,"name":"armatureName","skin":[{"name":"","slot":[{"display":[{"path":"zuojiao","type":"image","name":"zuojiao","transform":{"y":-0.19,"skX":-40.55,"skY":-40.55,"x":4.73}}],"name":"zuojiao"},{"display":[{"slotPose":[1,0,0,1,0,0],"userEdges":[17,29,29,30,1,20,27,21,20,31,31,0,26,22,16,32,13,33,33,30,32,33,30,34,34,35,35,5,36,37,37,38,38,39,39,36,40,41,41,42,42,43,43,40],"vertices":[29.25,-223.99,37.8,-216.68,54.1,-197.96,71.71,-168.21,71.71,-156.2,62.47,-144.25,71.71,-125.62,71.71,-94.94,1.26,-94.94,-25.04,-106.41,-27.98,-128.15,-47.68,-148.73,-58.27,-169.46,-58.27,-175.12,-58.27,-191.74,-44.47,-199.52,-39.69,-199.6,-31.96,-199.76,-16.26,-207.85,-0.41,-215.19,19.24,-218.26,8.49,-220.43,-2.18,-219.95,-8.44,-214.51,-14.01,-213.63,-9.4,-222.12,-0.97,-225.92,8.3,-225.92,18.52,-225.92,-34.55,-187.78,-38.86,-175.12,23.69,-221.4,-44.17,-187.74,-49,-175.11,-8.95,-160.19,22.82,-141.73,22.39,-158.69,5.47,-168.98,3.48,-162.51,10.86,-156.37,43.04,-158.56,54.66,-163.21,53.67,-156.07,46.7,-155.57],"path":"tou","edges":[12,11,11,10,10,9,9,8,8,7,7,6,6,5,5,4,4,3,3,2,2,1,1,0,0,28,28,27,27,26,26,25,25,24,24,23,23,22,22,21,21,20,20,19,19,18,18,17,17,16,16,15,15,14,14,13,13,12],"name":"tou","type":"mesh","triangles":[2,41,3,35,8,7,35,7,6,5,35,6,42,5,4,3,41,4,41,42,4,40,41,2,42,43,5,43,35,5,43,42,41,40,43,41,37,36,2,1,20,2,20,37,2,36,40,2,40,35,43,36,35,40,19,37,20,0,31,1,31,20,1,28,31,0,19,18,37,37,39,36,28,20,31,10,8,35,36,39,35,10,9,8,28,21,20,27,21,28,18,29,37,38,34,39,37,38,39,29,34,37,27,26,21,26,22,21,34,38,37,17,29,18,25,22,26,29,30,34,25,23,22,11,10,34,25,24,23,30,11,34,33,11,30,16,29,17,33,12,11,32,30,29,16,32,29,15,32,16,32,33,30,14,13,33,15,14,32,14,33,32,13,12,33,10,34,35,39,34,35],"bonePose":[19,0.13294835696180465,-0.991122966327164,0.991122966327164,0.13294835696180465,6.888195126346476,-111.59012810546584,26,-0.9998738758086452,-0.015881828465204362,0.015881828465204362,-0.9998738758086452,24.090152869901974,-221.17595314588303,27,-0.9811917252174278,-0.19303574374930604,0.19303574374930604,-0.9811917252174278,-35.84117840535654,-186.5059584591915],"width":130,"weights":[2,19,0.50186,26,0.49812,1,19,1,1,19,1,1,19,1,1,19,1,1,19,1,1,19,1,1,19,1,1,19,1,1,19,1,1,19,1,1,19,1,1,19,1,1,19,1,3,19,0.49985,27,0.49976,26,0.00037,3,19,0.29082,27,0.70861,26,0.00056,3,19,0.49426,27,0.50528,26,0.00043,1,19,1,1,19,1,1,19,1,1,19,1,2,19,0.35939,26,0.6406,2,19,0.09375,26,0.90625,2,19,0.02083,26,0.97916,1,26,1,1,26,1,2,19,0.03125,26,0.96873,2,19,0.11464,26,0.88535,2,19,0.18071,26,0.81928,2,19,0.47,27,0.52999,1,19,1,2,19,0.64133,26,0.35866,3,19,0.61381,27,0.38584,26,0.00034,1,19,1,1,19,1,1,19,1,1,19,1,1,19,1,1,19,1,1,19,1,1,19,1,1,19,1,1,19,1,1,19,1],"uvs":[0.67331,0.01472,0.73912,0.07057,0.86445,0.21349,1,0.44057,1,0.53226,0.9289,0.62352,1,0.76571,1,1,0.45804,1,0.25562,0.91252,0.23301,0.74643,0.08148,0.58932,0,0.4311,0,0.38793,0,0.26094,0.1061,0.20157,0.14287,0.20089,0.20234,0.19978,0.32318,0.13801,0.44506,0.08195,0.59624,0.05859,0.51358,0.04198,0.43146,0.04561,0.38334,0.08714,0.34044,0.09389,0.37601,0.029,0.44088,0,0.51218,0,0.5907,0,0.18251,0.29119,0.14927,0.38793,0.63055,0.03458,0.10848,0.29152,0.07125,0.38793,0.3794,0.50183,0.62389,0.64276,0.62056,0.51327,0.49031,0.4347,0.47498,0.48412,0.53181,0.53101,0.77946,0.51426,0.86885,0.47878,0.86118,0.53327,0.80755,0.53707],"height":131,"transform":{}}],"name":"tou"},{"display":[{"path":"wuqi","type":"image","name":"wuqi","transform":{"y":0.25,"skX":16.94,"skY":16.94,"x":9.28}}],"name":"wuqi"},{"display":[{"slotPose":[1,0,0,1,0,0],"userEdges":[26,51,25,0,26,52,52,48,50,52,27,53,53,47,52,53,28,54,54,46,53,54,29,55,55,45,54,55,30,56,56,44,55,56,31,57,57,43,56,57,32,58,58,42,57,58,33,59,59,41,58,59,34,60,60,40,59,60,35,61,61,39,60,61,61,37,3,62,62,25,1,62,4,63,63,24,62,63,5,64,64,23,63,64,6,65,65,22,64,65,7,66,66,21,65,66,8,67,67,20,66,67,9,68,68,19,67,68,10,69,69,18,68,69,11,70,70,17,69,70,12,71,71,16,70,71,71,14],"vertices":[34.2,-129.97,42.84,-129.21,50.56,-128.52,51.17,-103.58,51.17,-88.62,51.09,-74.78,51.68,-64.7,53.77,-52.87,56.49,-43,59.19,-35.17,61.97,-25.45,64.47,-17.66,67.13,-10.68,71.71,-1.96,71.71,2.03,67.35,2.03,58.07,-5.23,52.76,-11.67,47.97,-19.45,44.69,-29.03,42.12,-37.4,39.59,-48.52,37.26,-61.37,35.74,-71.98,34.7,-86.06,33.74,-101.74,-10.85,-110.38,-12,-87.24,-14.62,-69.58,-20.57,-50.8,-28.61,-33.23,-35.95,-24.19,-46.13,-15.39,-54.48,-9.58,-63.57,-5.45,-72.48,-2.7,-84.27,0.12,-84.27,-2.35,-84.28,-5.13,-76.98,-10.87,-71.55,-16.72,-67.58,-21.46,-64.71,-28.48,-62.36,-36.31,-60.62,-43.84,-58.05,-59.13,-59.1,-75.49,-58.73,-92.84,-56.66,-114.39,-48.57,-135.93,-34.41,-135.92,-21.71,-135.93,-34.37,-112.43,-36.31,-90.15,-38.18,-72.71,-41.81,-55.52,-46.47,-39.16,-49.43,-30.38,-55.73,-22.15,-61.2,-15.67,-67.61,-11.16,-74.82,-6.94,42.99,-102.72,42.97,-87.35,43.55,-73.4,44.87,-63.13,46.8,-50.74,49.73,-40.37,52.59,-32.37,55.72,-22.77,58.83,-14.77,62.92,-8.15],"path":"pifeng","edges":[36,35,35,34,34,33,33,32,32,31,31,30,30,29,29,28,28,27,27,26,26,25,25,24,24,23,23,22,22,21,21,20,20,19,19,18,18,17,17,16,16,15,15,14,14,13,13,12,12,11,11,10,10,9,9,8,8,7,7,6,6,5,5,4,4,3,3,2,2,1,1,0,0,51,51,50,50,49,49,48,48,47,47,46,46,45,45,44,44,43,43,42,42,41,41,40,40,39,39,38,38,37,37,36],"name":"pifeng","type":"mesh","triangles":[12,71,13,11,70,12,70,71,12,71,16,15,10,69,11,69,70,11,9,68,10,70,16,71,17,16,70,68,69,10,62,3,2,18,17,69,8,67,9,67,68,9,69,17,70,1,62,2,68,19,69,7,66,8,66,67,8,3,62,4,6,65,7,19,18,69,62,63,4,4,63,5,5,64,6,65,66,7,63,64,5,64,65,6,67,20,68,20,19,68,1,0,62,0,25,62,66,21,67,21,20,67,65,22,66,22,21,66,25,63,62,63,24,64,64,23,65,25,24,63,24,23,64,23,22,65,26,25,0,51,26,0,53,54,28,53,28,27,51,52,26,53,27,26,52,53,26,54,29,28,50,52,51,55,30,29,54,55,29,50,49,52,56,31,30,55,56,30,56,57,31,46,54,53,47,53,52,48,47,52,49,48,52,57,32,31,47,46,53,45,55,54,46,45,54,57,58,32,44,56,55,45,44,55,58,33,32,43,57,56,44,43,56,58,59,33,42,58,57,43,42,57,59,34,33,41,59,58,42,41,58,60,34,59,40,60,59,41,40,59,60,35,34,40,39,60,39,61,60,61,35,60,61,37,35,37,36,35,39,38,61,38,37,61,15,71,14,13,71,14],"bonePose":[20,-0.0312363117968642,0.9995120273540128,-0.9995120273540128,-0.0312363117968642,-35.35170000036141,-124.64852615747508,28,-0.28853050603075775,0.9574707029928564,-0.9574707029928564,-0.28853050603075775,-36.64802192497497,-73.56409066614597,21,0.05495017991244559,0.998489097450538,-0.998489097450538,0.05495017991244559,40.55818512538934,-119.33422091639945,25,0.2031290962381821,0.979151964845835,-0.979151964845835,0.2031290962381821,43.428395129518975,-72.82166353097722,29,0.3239174181981493,0.9460853588275454,-0.9460853588275454,0.3239174181981493,50.28519352330159,-40.704907533725255,34,0.5389178124813592,0.842358350935222,-0.842358350935222,0.5389178124813592,59.32434779815588,-14.859395544302728,33,-0.5386237411204703,0.8425464174165054,-0.8425464174165054,-0.5386237411204703,-47.04471113436816,-39.860460987975,36,-0.7905827096287528,0.6123552720733763,-0.6123552720733763,-0.7905827096287528,-62.09262552055119,-16.54443275360143],"width":156,"weights":[3,20,0.27952,21,0.7204,25,0.00006,2,20,0.0647,21,0.93529,3,20,0.00412,21,0.9957,25,0.00015,4,20,0.00121,21,0.97284,25,0.0259,29,0.00003,3,21,0.83295,25,0.16683,29,0.00021,3,21,0.52714,25,0.47186,29,0.00098,3,21,0.20782,25,0.76022,29,0.03193,3,21,0.04412,25,0.77237,29,0.1835,3,21,0.00375,25,0.49836,29,0.49788,4,21,0.00008,25,0.19037,29,0.78097,34,0.02856,4,21,0.00004,25,0.03505,29,0.79194,34,0.17294,3,25,0.00138,29,0.52169,34,0.4769,2,29,0.21396,34,0.78603,2,29,0.06227,34,0.93772,2,29,0.0497,34,0.95029,2,29,0.06409,34,0.9359,2,29,0.21275,34,0.78724,3,25,0.00293,29,0.51489,34,0.48216,3,25,0.03283,29,0.78533,34,0.18183,3,25,0.18083,29,0.78428,34,0.03486,4,21,0.00224,25,0.47996,29,0.51468,34,0.0031,3,21,0.03452,25,0.76249,29,0.20297,3,21,0.19017,25,0.76593,29,0.04388,4,20,0.00101,21,0.50322,25,0.4916,29,0.00414,3,20,0.04481,21,0.77341,25,0.18176,4,20,0.23135,28,0.00282,21,0.73976,25,0.02605,4,20,0.67195,28,0.03218,21,0.2958,25,0.00005,4,20,0.72316,28,0.19912,33,0.00078,21,0.07692,4,20,0.47877,28,0.4836,33,0.02518,21,0.01243,4,20,0.18639,28,0.65575,33,0.15738,21,0.00046,4,20,0.03551,28,0.51663,33,0.44446,36,0.00337,4,20,0.00266,28,0.24786,33,0.7183,36,0.03116,3,28,0.06516,33,0.75389,36,0.18093,3,28,0.01316,33,0.515,36,0.47183,3,28,0.00017,33,0.21208,36,0.78774,2,33,0.04665,36,0.95334,2,33,0.00571,36,0.99428,1,36,1,2,33,0.00736,36,0.99263,2,33,0.04277,36,0.95722,2,33,0.20061,36,0.79938,3,28,0.00716,33,0.49912,36,0.49371,3,28,0.04435,33,0.75531,36,0.20033,4,20,0.0025,28,0.21194,33,0.74273,36,0.0428,4,20,0.03461,28,0.47753,33,0.48182,36,0.00601,3,20,0.18544,28,0.63121,33,0.18333,4,20,0.48948,28,0.4747,33,0.03571,21,0.00009,4,20,0.79714,28,0.19988,33,0.00155,21,0.00141,3,20,0.94687,28,0.04125,21,0.01187,3,20,0.9829,28,0.00557,21,0.01152,2,20,0.90388,21,0.09611,3,20,0.65858,28,0.00353,21,0.33788,3,20,0.90245,28,0.03166,21,0.06587,3,20,0.79528,28,0.18624,21,0.01847,4,20,0.49012,28,0.48543,33,0.02336,21,0.00107,4,20,0.17354,28,0.66209,33,0.16433,21,0.00003,3,20,0.02744,28,0.507,33,0.46555,3,28,0.20805,33,0.75842,36,0.03351,3,28,0.04902,33,0.77797,36,0.173,3,28,0.00024,33,0.51088,36,0.48887,2,33,0.19465,36,0.80534,2,33,0.03413,36,0.96586,3,20,0.03809,21,0.94162,25,0.02026,4,20,0.00157,21,0.83441,25,0.16395,29,0.00005,3,21,0.51443,25,0.4853,29,0.00025,3,21,0.18472,25,0.78827,29,0.027,3,21,0.02847,25,0.78992,29,0.18159,3,21,0.00005,25,0.49479,29,0.50514,4,21,0.00005,25,0.17154,29,0.80393,34,0.02446,4,21,0.00001,25,0.02622,29,0.80687,34,0.16689,2,29,0.51965,34,0.48034,2,29,0.19416,34,0.80583],"uvs":[0.75966,0.0433,0.81506,0.04887,0.86452,0.05384,0.86843,0.23468,0.8684,0.34309,0.86785,0.44338,0.87163,0.51644,0.88497,0.60214,0.90239,0.67367,0.9197,0.73048,0.93754,0.80089,0.95354,0.85733,0.97064,0.90795,1,0.97112,1,1,0.97199,1,0.91247,0.94741,0.87843,0.90078,0.84776,0.84434,0.82672,0.77496,0.8102,0.71432,0.79405,0.63362,0.77907,0.54055,0.76938,0.46362,0.76275,0.36159,0.75663,0.24797,0.47086,0.1852,0.4635,0.35289,0.44675,0.48084,0.40856,0.6169,0.35701,0.74427,0.30996,0.8098,0.24466,0.8736,0.19114,0.91568,0.13279,0.94565,0.07569,0.96551,0,0.98581,0,0.96799,0,0.9478,0.04678,0.90627,0.08159,0.86385,0.10707,0.82955,0.12555,0.77868,0.14059,0.72189,0.15175,0.66733,0.16825,0.55654,0.16151,0.43796,0.1639,0.31228,0.17711,0.15616,0.22904,0,0.31984,0,0.40125,0,0.32007,0.17029,0.30768,0.33177,0.29566,0.45813,0.27238,0.5827,0.24249,0.70135,0.22351,0.76493,0.18314,0.82457,0.14806,0.87154,0.10687,0.90424,0.06064,0.93466,0.816,0.24091,0.81583,0.35229,0.81952,0.45331,0.82794,0.52782,0.8403,0.61761,0.85901,0.6928,0.87733,0.75075,0.8974,0.82032,0.91734,0.87827,0.94361,0.92629],"height":138,"transform":{}}],"name":"pifeng"},{"display":[{"path":"zuowan","type":"image","name":"zuowan","transform":{"y":7.26,"skX":-45.03,"skY":-45.03,"x":25.5}}],"name":"zuowan"},{"display":[{"path":"youbi","type":"image","name":"youbi","transform":{"y":-3.31,"skX":-128.41,"skY":-128.41,"x":30.24}}],"name":"youbi"},{"display":[{"triangles":[5,2,6,6,2,0,2,1,0,5,3,2,5,4,3],"width":50,"userEdges":[],"type":"mesh","vertices":[-10.19,-22.36,-0.47,-24.26,3.39,-18.61,25.13,-12.29,37.72,2.64,3.3,31.63,-28.9,-6.6],"transform":{},"path":"youdatui","edges":[4,3,3,2,2,1,1,0,0,6,6,5,5,4],"uvs":[1,0.54377,0.90377,0.73606,0.76751,0.72095,0.3907,1,0,1,0,0,1,0],"height":45,"name":"youdatui"}],"name":"youdatui"},{"display":[{"path":"youjianhou","type":"image","name":"youjianhou","transform":{"y":-9.83,"skX":154.34,"skY":154.34,"x":39.58}}],"name":"youjianhou"},{"display":[{"slotPose":[1,0,0,1,0,0],"userEdges":[4,17,6,17,3,18,17,18,2,19,18,19,19,0,9,20,20,17,7,20,10,21,21,18,21,20,11,22,22,19,21,22,22,14],"vertices":[27.29,-114.18,48.72,-99.3,48.71,-86.41,44.27,-73.63,31.7,-59.07,29.21,-46.88,12.94,-37.95,-6.37,-37.96,-29.76,-51.29,-27.84,-63.93,-41.09,-79.29,-45.27,-89.74,-45.27,-103.19,-32.01,-111.32,-17.59,-118.65,-11.98,-126.93,23.39,-126.93,17.68,-60.21,21.29,-75.15,23.68,-87.29,-7.97,-62.32,-9.37,-77.19,-10.55,-88.51],"path":"shenti","edges":[11,10,10,9,9,8,8,7,7,6,6,5,5,4,4,3,3,2,2,1,1,0,0,16,16,15,15,14,14,13,13,12,12,11],"name":"shenti","type":"mesh","triangles":[0,19,1,1,19,2,19,3,2,18,4,3,19,18,3,17,5,4,18,17,4,22,19,0,17,6,5,14,22,0,16,15,0,15,14,0,21,18,19,22,21,19,20,17,18,21,20,18,20,7,6,20,6,17,14,13,22,21,9,20,9,8,20,20,8,7,22,10,21,10,9,21,13,11,22,11,10,22,12,11,13],"bonePose":[8,0.0941083133185145,-0.99556196460308,0.99556196460308,0.0941083133185145,2.25,-52.37,10,0.0392598157590688,-0.9992290362407228,0.9992290362407228,0.0392598157590688,4.712615943888207,-77.35915009985149],"width":94,"weights":[2,8,0.06966,10,0.93033,2,8,0.09713,10,0.90286,2,8,0.20457,10,0.79542,2,8,0.45351,10,0.54648,2,8,0.75497,10,0.24502,2,8,0.9108,10,0.08919,2,8,0.97082,10,0.02917,2,8,0.97148,10,0.02851,2,8,0.89349,10,0.1065,2,8,0.74906,10,0.25093,2,8,0.49404,10,0.50594,2,8,0.24737,10,0.75262,2,8,0.17828,10,0.82171,2,8,0.1017,10,0.89829,2,8,0.08377,10,0.91622,2,8,0.00751,10,0.99248,2,8,0.0017,10,0.99829,2,8,0.83222,10,0.16777,2,8,0.51348,10,0.48651,2,8,0.21194,10,0.78805,2,8,0.852,10,0.14799,2,8,0.52568,10,0.47431,2,8,0.2531,10,0.74689],"uvs":[0.772,0.14334,1,0.31058,1,0.45548,0.95272,0.5991,0.81897,0.76257,0.79252,0.8997,0.61941,1,0.41383,1,0.16499,0.85018,0.18542,0.70797,0.04446,0.53535,0,0.41796,0,0.26684,0.14103,0.1755,0.29451,0.09316,0.3542,0,0.73059,0,0.66973,0.74971,0.70823,0.58194,0.73362,0.44548,0.39682,0.72619,0.38198,0.55904,0.36943,0.43182],"height":89,"transform":{}}],"name":"shenti"},{"display":[{"triangles":[1,0,3,2,1,3],"width":37,"userEdges":[],"type":"mesh","vertices":[32.82,-3.37,10.08,25.8,-15.94,5.52,6.8,-23.66],"transform":{},"path":"zuodatui","edges":[1,0,0,3,3,2,2,1],"uvs":[1,1,0,1,0,0,1,0],"height":33,"name":"zuodatui"}],"name":"zuodatui"},{"display":[{"path":"shihua","type":"image","name":"shihua","transform":{"y":-111.94,"x":9.72}}],"name":"shihua"},{"display":[{"path":"zuoxiaotui","type":"image","name":"zuoxiaotui","transform":{"y":0.51,"skX":-105.26,"skY":-105.26,"x":7.42}}],"name":"zuoxiaotui"},{"display":[{"path":"youjiao","type":"image","name":"youjiao","transform":{"y":0.13,"skX":-141.83,"skY":-141.83,"x":5.19}}],"name":"youjiao"},{"display":[{"path":"youxiaotui","type":"image","name":"youxiaotui","transform":{"y":0.08,"skX":-100.22,"skY":-100.22,"x":7.57}}],"name":"youxiaotui"},{"display":[{"slotPose":[1,0,0,1,0,0],"userEdges":[11,31,31,32,32,33,33,34,34,35,35,36,36,37,37,0,28,38,38,39,39,40,40,41,41,42,42,43,43,17,13,44,44,45,45,46,46,47,47,48,48,49,49,30,29,50,50,51,51,52,52,53,53,54,54,55,55,15],"vertices":[36.27,-122.92,47.3,-106.55,49.32,-90.36,48.95,-72.52,49.43,-58.25,53.12,-42.49,57.94,-28.86,62.62,-15.52,68.69,-2.88,68.69,1.05,64.37,1.05,49.97,-5.13,31.5,-3.62,15.6,-5.07,1.84,-1.59,-14.05,-0.84,-30.3,-1.1,-45.68,-4.88,-57.14,-6.96,-69.31,-5.62,-69.31,-10.86,-64.53,-23.39,-61.43,-35.81,-58.66,-49.61,-57.05,-66.06,-57.16,-80.65,-59.22,-95.21,-54.15,-111.08,-38.51,-124.85,-21.61,-131.93,18.42,-131.93,46.34,-13.31,42.45,-26.3,38.68,-39.98,35.73,-56.38,33.38,-71.48,31.37,-90.36,29.72,-108.94,-34.13,-105.83,-33.25,-85.6,-32.18,-67.88,-33.97,-49.81,-36.13,-33.16,-40.42,-18.13,15.16,-21.76,15.16,-36.68,13.98,-52,12.99,-69.91,11.2,-90,12.19,-113.49,-14.27,-109.11,-13.88,-87.02,-13.48,-69.11,-13.69,-49.81,-14.49,-33.1,-15.28,-16.78],"path":"houbai","edges":[19,18,18,17,17,16,16,15,15,14,14,13,13,12,12,11,11,10,10,9,9,8,8,7,7,6,6,5,5,4,4,3,3,2,2,1,1,0,0,30,30,29,29,28,28,27,27,26,26,25,25,24,24,23,23,22,22,21,21,20,20,19],"name":"houbai","type":"mesh","triangles":[7,10,8,8,10,9,7,11,10,6,31,7,31,11,7,5,32,6,32,31,6,34,33,4,4,33,5,33,32,5,35,34,4,35,4,3,1,36,2,35,3,2,36,35,2,31,12,11,0,37,1,37,36,1,32,12,31,44,12,32,33,45,32,45,44,32,34,46,33,46,45,33,44,13,12,35,47,34,47,46,34,30,37,0,30,49,37,36,47,35,37,48,36,48,47,36,49,48,37,44,14,13,29,49,30,50,48,49,29,50,49,48,51,47,47,52,46,52,53,46,55,14,44,46,53,45,53,54,45,54,44,45,51,52,47,54,55,44,50,51,48,55,15,14,38,39,51,51,39,52,39,40,52,29,28,50,28,38,50,38,51,50,55,16,15,42,55,54,41,42,54,52,40,53,40,41,53,41,54,53,43,16,55,42,43,55,26,39,38,24,41,40,39,25,40,43,17,16,23,42,41,28,27,38,25,24,40,24,23,41,26,25,39,27,26,38,22,43,42,23,22,42,22,21,43,18,17,43,21,18,43,21,20,18,20,19,18],"bonePose":[18,0.015881828465203758,0.9998738758086452,-0.9998738758086452,0.015881828465203758,-1.8755642955092415,-123.38328378135832,22,-0.015532805679965345,0.9998793586966922,-0.9998793586966922,-0.015532805679965345,-1.0463740313409535,-71.17986872538897,20,-0.0312363117968642,0.9995120273540128,-0.9995120273540128,-0.0312363117968642,-35.35170000036141,-124.64852615747508,28,-0.28853050603075775,0.9574707029928564,-0.9574707029928564,-0.28853050603075775,-36.64802192497497,-73.56409066614597,21,0.05495017991244559,0.998489097450538,-0.998489097450538,0.05495017991244559,40.55818512538934,-119.33422091639945,25,0.2031290962381821,0.979151964845835,-0.979151964845835,0.2031290962381821,43.428395129518975,-72.82166353097722,29,0.3239174181981493,0.9460853588275454,-0.9460853588275454,0.3239174181981493,50.28519352330159,-40.704907533725255,34,0.5389178124813592,0.842358350935222,-0.842358350935222,0.5389178124813592,59.32434779815588,-14.859395544302728,32,0.0001745329243129489,0.9999999847691292,-0.9999999847691292,0.0001745329243129489,-1.891933039292873,-28.337834110258108,33,-0.5386237411204703,0.8425464174165054,-0.8425464174165054,-0.5386237411204703,-47.04471113436816,-39.860460987975,36,-0.7905827096287528,0.6123552720733763,-0.6123552720733763,-0.7905827096287528,-62.09262552055119,-16.54443275360143],"width":138,"weights":[5,18,0.31316,22,0.00099,20,0.03736,21,0.64825,25,0.00021,5,18,0.14672,22,0.00007,20,0.00002,21,0.79144,25,0.06173,3,18,0.03294,21,0.73248,25,0.23455,3,21,0.48149,25,0.46738,29,0.05111,3,21,0.20988,25,0.57676,29,0.21334,4,21,0.04938,25,0.46392,29,0.42229,34,0.06439,3,25,0.23109,29,0.52901,34,0.23989,4,32,0.00001,25,0.05999,29,0.41876,34,0.52123,3,32,0.00016,29,0.21886,34,0.78096,4,22,0.00036,32,0.00875,29,0.1159,34,0.87497,5,22,0.0048,32,0.05713,25,0.00122,29,0.1943,34,0.74251,5,22,0.01601,32,0.17062,25,0.01216,29,0.37115,34,0.43004,5,22,0.03581,32,0.39372,25,0.01187,29,0.32869,34,0.22989,7,22,0.09321,32,0.5906,28,0.00013,33,0.01211,25,0.02747,29,0.21152,34,0.06492,7,22,0.03265,32,0.76863,28,0.00194,33,0.07269,25,0.00946,29,0.10127,34,0.01334,7,22,0.04603,32,0.71901,28,0.01408,33,0.19973,25,0.00093,29,0.01847,34,0.00172,7,22,0.00933,32,0.52433,28,0.00689,33,0.42681,29,0.00087,34,0.00007,36,0.03166,5,22,0.02067,32,0.25409,28,0.0366,33,0.57655,36,0.11208,5,22,0.00319,32,0.10736,28,0.00448,33,0.54217,36,0.34277,5,22,0.00022,32,0.02942,28,0.00029,33,0.46561,36,0.50444,4,32,0.00292,28,0.0194,33,0.47322,36,0.50444,4,32,0.00006,28,0.12412,33,0.52247,36,0.35333,4,20,0.02196,28,0.31798,33,0.50004,36,0.16,4,20,0.12004,28,0.50866,33,0.32906,36,0.04222,3,20,0.32505,28,0.53214,33,0.14278,3,20,0.59723,28,0.37735,33,0.02539,2,20,0.82832,28,0.17167,4,18,0.03424,20,0.92237,28,0.04335,21,0.00002,4,18,0.13734,20,0.84276,28,0.00313,21,0.01674,5,18,0.41069,22,0.00652,20,0.48925,28,0.00381,21,0.0897,5,18,0.5294,22,0.00316,20,0.15967,21,0.3061,25,0.00165,5,22,0.03333,32,0.12222,25,0.07772,29,0.50423,34,0.26248,7,18,0.00236,22,0.0668,32,0.09537,21,0.00273,25,0.22228,29,0.49177,34,0.11864,7,18,0.01596,22,0.10435,32,0.06261,21,0.04113,25,0.39173,29,0.35058,34,0.0336,7,18,0.04379,22,0.12163,32,0.02816,21,0.17502,25,0.45867,29,0.16765,34,0.00504,6,18,0.10424,22,0.10083,32,0.00662,21,0.37706,25,0.3615,29,0.04972,6,18,0.17519,22,0.05535,32,0.00077,21,0.58591,25,0.17977,29,0.00297,5,18,0.26113,22,0.01844,20,0.00002,21,0.67148,25,0.04889,5,18,0.04154,22,0.00862,20,0.89426,28,0.05554,21,0.00001,6,18,0.0129,22,0.03779,32,0.00182,20,0.74785,28,0.1944,33,0.0052,6,18,0.01757,22,0.08715,32,0.01828,20,0.457,28,0.37177,33,0.0482,6,18,0.01143,22,0.12237,32,0.053,20,0.19418,28,0.44315,33,0.17583,6,18,0.00581,22,0.11671,32,0.10772,20,0.04153,28,0.3479,33,0.3803,6,18,0.0002,22,0.07033,32,0.16926,28,0.17484,33,0.55368,36,0.03166,7,18,0.00486,22,0.26102,32,0.44415,21,0.00327,25,0.09252,29,0.17854,34,0.01558,7,18,0.03688,22,0.40033,32,0.25466,21,0.02466,25,0.16005,29,0.11885,34,0.00455,7,18,0.15602,22,0.41635,32,0.10083,21,0.06367,25,0.19826,29,0.06361,34,0.00122,7,18,0.35476,22,0.31426,32,0.02563,21,0.1179,25,0.16558,29,0.02182,34,0.00002,7,18,0.5806,22,0.15511,32,0.00168,20,0.00002,21,0.16564,25,0.09204,29,0.00486,6,18,0.64775,22,0.04931,20,0.0498,21,0.22388,25,0.02908,29,0.00015,5,18,0.49238,22,0.05767,20,0.39566,28,0.03193,21,0.02233,7,18,0.43947,22,0.17918,32,0.00148,20,0.28577,28,0.09129,33,0.00275,21,0.00002,6,18,0.29218,22,0.32843,32,0.03976,20,0.16444,28,0.1548,33,0.02033,6,18,0.12771,22,0.40387,32,0.17221,20,0.07323,28,0.17629,33,0.04665,6,18,0.03266,22,0.33424,32,0.39647,20,0.02005,28,0.13293,33,0.0836,8,18,0.00085,22,0.18178,32,0.62677,20,0.00097,28,0.06611,33,0.12254,29,0.00087,34,0.00007],"uvs":[0.76486,0.06776,0.84486,0.19089,0.85953,0.31264,0.85686,0.44683,0.86035,0.55406,0.8871,0.67257,0.92209,0.77506,0.95604,0.87542,1,0.97045,1,1,0.96872,1,0.86425,0.95356,0.73045,0.96492,0.61518,0.95403,0.51547,0.9802,0.40039,0.98586,0.28265,0.98389,0.17126,0.95545,0.08816,0.93986,0,0.94995,0,0.91052,0.0346,0.81627,0.0571,0.72289,0.0771,0.61913,0.08876,0.49548,0.08793,0.38567,0.07293,0.27629,0.1096,0.15696,0.22293,0.0532,0.34543,0,0.63553,0,0.83799,0.892,0.80977,0.79441,0.78241,0.69149,0.76103,0.56817,0.74393,0.4546,0.7294,0.31265,0.71742,0.17294,0.25476,0.19637,0.26124,0.34845,0.26903,0.48169,0.25606,0.61763,0.24049,0.74279,0.20936,0.85585,0.61205,0.82851,0.61205,0.71629,0.6034,0.60108,0.59619,0.46642,0.58321,0.3153,0.59042,0.13874,0.39863,0.17166,0.40151,0.33774,0.4044,0.47241,0.40296,0.61754,0.39719,0.74323,0.39142,0.86592],"height":133,"transform":{}}],"name":"houbai"},{"display":[{"path":"youwan","type":"image","name":"youwan","transform":{"y":-0.28,"skX":18.1,"skY":18.1,"x":18.04}}],"name":"youwan"},{"display":[{"path":"zuobi","type":"image","name":"zuobi","transform":{"y":0.25,"skX":-59.71,"skY":-59.71,"x":30.29}}],"name":"zuobi"},{"display":[{"path":"youshou","type":"image","name":"youshou","transform":{"y":2.67,"skX":20.98,"skY":20.98,"x":12.61}}],"name":"youshou"},{"display":[{"path":"ty","type":"image","name":"ty","transform":{}}],"name":"ty"},{"display":[{"path":"youjian","type":"image","name":"youjian","transform":{"y":-0.41,"skX":154.34,"skY":154.34,"x":22.65}}],"name":"youjian"}]}]}],"name":"heroDB42015","version":"5.0"}