{"frameRate":30,"isGlobal":0,"armature":[{"aabb":{"width":178.4829211451613,"y":-160.35304632916666,"height":212,"x":-92.18292114516129},"type":"Armature","bone":[{"name":"root","transform":{}},{"length":83,"transform":{"y":-138.28,"skX":-93.6,"skY":-93.6,"x":-9.09},"parent":"root","name":"bone"},{"transform":{"y":-7.55,"x":-0.7},"name":"bone29","parent":"root"},{"length":22,"transform":{"y":-35.45,"skX":157.73,"skY":157.73,"x":-41.77},"parent":"bone","name":"bone12"},{"length":19,"transform":{"y":-4.96,"skX":175.49,"skY":175.49,"x":-68.27},"parent":"bone","name":"bone17"},{"length":30,"transform":{"y":18.09,"skX":144.97,"skY":144.97,"x":-62.21},"parent":"bone","name":"bone2"},{"length":14,"transform":{"y":-0.21,"skX":146.62,"skY":146.62,"x":-62.33},"parent":"bone","name":"bone20"},{"length":17,"transform":{"y":40.78,"skX":163.34,"skY":163.34,"x":-43.25},"parent":"bone","name":"bone22"},{"length":18,"transform":{"y":25.84,"skX":-138.08,"skY":-138.08,"x":-86.34},"parent":"bone","name":"bone25"},{"length":11,"transform":{"y":34.32,"skX":92.25,"skY":92.25,"x":-4.68},"parent":"bone","name":"bone27"},{"length":38,"transform":{"y":5.11,"skX":-55.58,"skY":-55.58,"x":-27.02},"parent":"bone","name":"bone28"},{"length":27,"transform":{"y":33.57,"skX":89.54,"skY":89.54,"x":7.41},"parent":"bone","name":"bone7"},{"length":21,"transform":{"y":-48.03,"skX":-134.77,"skY":-134.77,"x":-31.11},"parent":"bone","name":"bone8"},{"length":20,"transform":{"y":-0.14,"skX":45.45,"skY":45.45,"x":22.46},"parent":"bone12","name":"bone13"},{"length":15,"transform":{"y":-0.04,"skX":21.09,"skY":21.09,"x":19.28},"parent":"bone17","name":"bone18"},{"length":12,"transform":{"skX":-47.1,"skY":-47.1,"x":14.66},"parent":"bone20","name":"bone21"},{"length":12,"transform":{"skX":-12.43,"skY":-12.43,"x":17.77},"parent":"bone22","name":"bone23"},{"length":13,"transform":{"y":0.05,"skX":22.26,"skY":22.26,"x":18.27},"parent":"bone25","name":"bone26"},{"length":26,"transform":{"y":-0.01,"skX":48.36,"skY":48.36,"x":30.35},"parent":"bone2","name":"bone3"},{"length":17,"transform":{"y":-0.03,"skX":8.94,"skY":8.94,"x":21.32},"parent":"bone8","name":"bone9"},{"length":11,"transform":{"y":0.45,"skX":21.48,"skY":21.48,"x":15.44},"parent":"bone18","name":"bone19"},{"length":18,"transform":{"y":-0.05,"skX":66.96,"skY":66.96,"x":20.33},"parent":"bone13","name":"bone14"},{"length":15,"transform":{"y":0.01,"skX":-49.92,"skY":-49.92,"x":17.2},"parent":"bone9","name":"bone10"},{"length":10,"transform":{"y":-0.01,"skX":37.59,"skY":37.59,"x":12.68},"parent":"bone23","name":"bone24"},{"length":25,"transform":{"y":0.07,"skX":70.08,"skY":70.08,"x":26.22},"parent":"bone3","name":"bone4"},{"length":9,"transform":{"y":-0.03,"skX":-40.11,"skY":-40.11,"x":15.82},"parent":"bone10","name":"bone11"},{"length":13,"transform":{"y":-0.09,"skX":-43.36,"skY":-43.36,"x":18.8},"parent":"bone14","name":"bone15"},{"length":16,"transform":{"y":-0.08,"skX":-51,"skY":-51,"x":25.67},"parent":"bone4","name":"bone5"},{"length":12,"transform":{"y":0.02,"skX":-42.4,"skY":-42.4,"x":13.08},"parent":"bone15","name":"bone16"},{"length":16,"transform":{"y":-0.05,"skX":-54.97,"skY":-54.97,"x":16.28},"parent":"bone5","name":"bone6"}],"defaultActions":[{"gotoAndPlay":"atk"}],"slot":[{"color":{},"name":"ty","parent":"bone29"},{"z":1,"color":{},"name":"chuxu6","parent":"bone17"},{"z":2,"color":{},"name":"chuxu5","parent":"bone25"},{"z":3,"color":{},"name":"chixu4","parent":"bone22"},{"z":4,"color":{},"name":"shenti","parent":"bone"},{"z":5,"color":{},"name":"biyan","parent":"bone7","displayIndex":-1},{"z":6,"color":{},"name":"chuxu3","parent":"bone20"},{"z":7,"color":{},"name":"chuxu2","parent":"bone12"},{"z":8,"color":{},"name":"chuxu1","parent":"bone8"},{"z":9,"color":{},"name":"shihua","parent":"root","displayIndex":-1}],"animation":[{"duration":40,"frame":[{"duration":15,"tweenEasing":null},{"duration":0,"tweenEasing":null,"events":[{"name":"hit"}]}],"ik":[],"bone":[{"frame":[{"duration":3,"transform":{},"tweenEasing":0},{"duration":3,"transform":{"y":31.69,"x":-14.09},"tweenEasing":0},{"duration":2,"transform":{"y":31.69,"skX":-9.52,"skY":-9.52,"x":-14.09}},{"duration":5,"transform":{"y":-15.63,"skX":-9.52,"skY":-9.52,"x":-63.92},"tweenEasing":0},{"duration":2,"transform":{"y":-18.27,"skX":-9.52,"skY":-9.52,"x":-67.92},"tweenEasing":0},{"duration":3,"transform":{"scX":1.176,"y":-5.96,"scY":1.176,"skX":10.16,"skY":10.16,"x":83.3},"tweenEasing":0},{"duration":3,"transform":{"scX":1.176,"y":-1.96,"scY":1.176,"skX":10.16,"skY":10.16,"x":83.3},"tweenEasing":0},{"duration":3,"transform":{"scX":1.176,"y":-5.96,"scY":1.176,"skX":10.16,"skY":10.16,"x":83.3},"tweenEasing":0},{"duration":3,"transform":{"scX":1.176,"y":-1.96,"scY":1.176,"skX":10.16,"skY":10.16,"x":83.3},"tweenEasing":0},{"duration":3,"transform":{"scX":1.176,"y":-5.96,"scY":1.176,"skX":10.16,"skY":10.16,"x":83.3},"tweenEasing":0},{"duration":10,"transform":{"scX":1.176,"y":-1.96,"scY":1.176,"skX":10.16,"skY":10.16,"x":83.3},"tweenEasing":0},{"duration":0,"transform":{}}],"name":"bone"},{"frame":[{"duration":6,"transform":{}},{"duration":7,"transform":{}},{"duration":2,"transform":{}},{"duration":15,"transform":{}},{"duration":10,"transform":{}},{"duration":0,"transform":{}}],"name":"bone7"},{"frame":[{"duration":5,"transform":{},"curve":[0.25,0,0.75,1]},{"duration":6,"transform":{"skX":19.53,"skY":19.53},"curve":[0.25,0,0.75,1]},{"duration":6,"transform":{"skX":-36.61,"skY":-36.61},"curve":[0.25,0,0.75,1]},{"duration":6,"transform":{"skX":19.53,"skY":19.53},"curve":[0.25,0,0.75,1]},{"duration":6,"transform":{"skX":-36.61,"skY":-36.61},"curve":[0.25,0,0.75,1]},{"duration":6,"transform":{"skX":19.53,"skY":19.53},"curve":[0.25,0,0.75,1]},{"duration":5,"transform":{"skX":-36.61,"skY":-36.61},"curve":[0.25,0,0.75,1]},{"duration":0,"transform":{}}],"name":"bone8"},{"frame":[{"duration":6,"transform":{"skX":3.46,"skY":3.46},"curve":[0.25,0,0.75,1]},{"duration":7,"transform":{"skX":-320.99,"skY":-320.99},"curve":[0.25,0,0.75,1]},{"duration":7,"transform":{"skX":1.09,"skY":1.09},"curve":[0.25,0,0.75,1]},{"duration":7,"transform":{"skX":-320.99,"skY":-320.99},"curve":[0.25,0,0.75,1]},{"duration":7,"transform":{"skX":1.09,"skY":1.09},"curve":[0.25,0,0.75,1]},{"duration":6,"transform":{"skX":-320.99,"skY":-320.99},"curve":[0.25,0,0.75,1]},{"duration":0,"transform":{"skX":3.46,"skY":3.46}}],"name":"bone12"},{"frame":[{"duration":5,"transform":{"skX":33.61,"skY":33.61},"curve":[0.25,0,0.75,1]},{"duration":6,"transform":{"skX":-353.1,"skY":-353.1},"curve":[0.25,0,0.75,1]},{"duration":6,"transform":{"skX":-315.02,"skY":-315.02},"curve":[0.25,0,0.75,1]},{"duration":6,"transform":{"skX":-308.04,"skY":-308.04},"curve":[0.25,0,0.75,1]},{"duration":6,"transform":{"skX":-275.19,"skY":-275.19},"curve":[0.25,0,0.75,1]},{"duration":6,"transform":{"skX":-308.04,"skY":-308.04},"curve":[0.25,0,0.75,1]},{"duration":5,"transform":{"skX":-275.19,"skY":-275.19},"curve":[0.25,0,0.75,1]},{"duration":0,"transform":{"skX":-326.38,"skY":-326.38}}],"name":"bone17"},{"frame":[{"duration":6,"transform":{},"tweenEasing":0},{"duration":7,"transform":{"skX":-307.59,"skY":-307.59},"tweenEasing":0},{"duration":2,"transform":{"skX":-259.11,"skY":-259.11},"tweenEasing":0},{"duration":15,"transform":{"y":-9.04,"skX":-284.46,"skY":-284.46,"x":5.93}},{"duration":10,"transform":{"y":-9.04,"skX":-284.46,"skY":-284.46,"x":5.93},"tweenEasing":0},{"duration":0,"transform":{}}],"name":"bone20"},{"frame":[{"duration":6,"transform":{},"tweenEasing":0},{"duration":7,"transform":{"skX":-20.94,"skY":-20.94},"tweenEasing":0},{"duration":2,"transform":{"skX":-82.57,"skY":-82.57},"tweenEasing":0},{"duration":15,"transform":{"skX":-332.11,"skY":-332.11}},{"duration":10,"transform":{"skX":-332.11,"skY":-332.11},"tweenEasing":0},{"duration":0,"transform":{}}],"name":"bone22"},{"frame":[{"duration":6,"transform":{},"tweenEasing":0},{"duration":7,"transform":{"y":0.67,"skX":284.49,"skY":284.49,"x":9.32},"tweenEasing":0},{"duration":2,"transform":{"y":0.67,"x":9.32},"tweenEasing":0},{"duration":5,"transform":{"y":-24.96,"skX":16.6,"skY":16.6,"x":1.97},"tweenEasing":0},{"duration":5,"transform":{"y":-24.96,"skX":-27.89,"skY":-27.89,"x":1.97},"curve":[0.25,0,0.75,1]},{"duration":5,"transform":{"y":-24.96,"skX":15.82,"skY":15.82,"x":1.97},"curve":[0.25,0,0.75,1]},{"duration":1,"transform":{"y":-24.96,"skX":15.82,"skY":15.82,"x":1.97},"tweenEasing":0},{"duration":5,"transform":{"y":-24.96,"skX":-27.89,"skY":-27.89,"x":1.97},"curve":[0.25,0,0.75,1]},{"duration":4,"transform":{"y":-24.96,"skX":15.82,"skY":15.82,"x":1.97},"curve":[0.25,0,0.75,1]},{"duration":0,"transform":{}}],"name":"bone25"},{"frame":[{"duration":15,"transform":{}},{"duration":15,"transform":{}},{"duration":10,"transform":{}},{"duration":0,"transform":{}}],"name":"root"},{"frame":[{"duration":6,"transform":{},"tweenEasing":0},{"duration":7,"transform":{"y":-1.89,"x":-10.17},"tweenEasing":0},{"duration":2,"transform":{"y":7.1,"x":11.85},"tweenEasing":0},{"duration":4,"transform":{},"tweenEasing":0},{"duration":4,"transform":{"y":1.59,"x":-13.88},"tweenEasing":0},{"duration":4,"transform":{"y":7.56,"x":4.57},"tweenEasing":0},{"duration":3,"transform":{"y":-2.77,"x":-10.14},"tweenEasing":0},{"duration":1,"transform":{"y":-2.77,"x":-10.14}},{"duration":9,"transform":{}},{"duration":0,"transform":{}}],"name":"bone28"},{"frame":[{"duration":6,"transform":{},"tweenEasing":0},{"duration":7,"transform":{"y":-3.47,"x":2.18},"tweenEasing":0},{"duration":2,"transform":{"scX":0.447,"y":-1.86,"scY":0.447,"x":1.55},"tweenEasing":0},{"duration":15,"transform":{"scX":1.351,"y":4.21,"scY":1.351,"skX":-8.57,"skY":-8.57,"x":1.39}},{"duration":10,"transform":{"scX":1.351,"y":4.21,"scY":1.351,"skX":-8.57,"skY":-8.57,"x":1.39},"tweenEasing":0},{"duration":0,"transform":{}}],"name":"bone27"},{"frame":[{"duration":6,"transform":{},"tweenEasing":0},{"duration":7,"transform":{"skX":-49.87,"skY":-49.87},"tweenEasing":0},{"duration":2,"transform":{},"tweenEasing":0},{"duration":3,"transform":{"skX":-75.24,"skY":-75.24},"tweenEasing":0},{"duration":5,"transform":{"skX":22.25,"skY":22.25},"curve":[0.25,0,0.75,1]},{"duration":6,"transform":{"skX":-75.31,"skY":-75.31},"curve":[0.25,0,0.75,1]},{"duration":5,"transform":{"skX":22.25,"skY":22.25},"curve":[0.25,0,0.75,1]},{"duration":6,"transform":{"skX":-75.31,"skY":-75.31},"curve":[0.25,0,0.75,1]},{"duration":0,"transform":{}}],"name":"bone26"},{"frame":[{"duration":6,"transform":{}},{"duration":7,"transform":{}},{"duration":2,"transform":{}},{"duration":15,"transform":{}},{"duration":10,"transform":{}},{"duration":0,"transform":{}}],"name":"bone24"},{"frame":[{"duration":6,"transform":{},"tweenEasing":0},{"duration":7,"transform":{"skX":19.63,"skY":19.63}},{"duration":2,"transform":{"skX":19.63,"skY":19.63},"tweenEasing":0},{"duration":15,"transform":{"skX":34.05,"skY":34.05}},{"duration":10,"transform":{"skX":34.05,"skY":34.05},"tweenEasing":0},{"duration":0,"transform":{}}],"name":"bone23"},{"frame":[{"duration":6,"transform":{}},{"duration":7,"transform":{}},{"duration":2,"transform":{}},{"duration":15,"transform":{}},{"duration":10,"transform":{}},{"duration":0,"transform":{}}],"name":"bone21"},{"frame":[{"duration":5,"transform":{"skX":-52.65,"skY":-52.65},"curve":[0.25,0,0.75,1]},{"duration":6,"transform":{"skX":1.65,"skY":1.65},"curve":[0.25,0,0.75,1]},{"duration":6,"transform":{"skX":-68.3,"skY":-68.3},"curve":[0.25,0,0.75,1]},{"duration":6,"transform":{"skX":1.65,"skY":1.65},"curve":[0.25,0,0.75,1]},{"duration":6,"transform":{"skX":-68.3,"skY":-68.3},"curve":[0.25,0,0.75,1]},{"duration":6,"transform":{"skX":1.65,"skY":1.65},"curve":[0.25,0,0.75,1]},{"duration":5,"transform":{"skX":-68.3,"skY":-68.3},"curve":[0.25,0,0.75,1]},{"duration":0,"transform":{"skX":-52.65,"skY":-52.65}}],"name":"bone19"},{"frame":[{"duration":3,"transform":{"skX":-41.52,"skY":-41.52},"curve":[0.25,0,0.75,1]},{"duration":6,"transform":{"skX":9.78,"skY":9.78},"curve":[0.25,0,0.75,1]},{"duration":6,"transform":{"skX":-63.56,"skY":-63.56},"curve":[0.25,0,0.75,1]},{"duration":6,"transform":{"skX":9.78,"skY":9.78},"curve":[0.25,0,0.75,1]},{"duration":6,"transform":{"skX":-63.56,"skY":-63.56},"curve":[0.25,0,0.75,1]},{"duration":6,"transform":{"skX":9.78,"skY":9.78},"curve":[0.25,0,0.75,1]},{"duration":7,"transform":{"skX":-63.56,"skY":-63.56},"curve":[0.25,0,0.75,1]},{"duration":0,"transform":{"skX":-41.52,"skY":-41.52}}],"name":"bone18"},{"frame":[{"duration":8,"transform":{"skX":-12.19,"skY":-12.19},"curve":[0.25,0,0.75,1]},{"duration":7,"transform":{"skX":12.29,"skY":12.29},"curve":[0.25,0,0.75,1]},{"duration":7,"transform":{"skX":62.36,"skY":62.36},"curve":[0.25,0,0.75,1]},{"duration":7,"transform":{"skX":12.29,"skY":12.29},"curve":[0.25,0,0.75,1]},{"duration":7,"transform":{"skX":62.36,"skY":62.36},"curve":[0.25,0,0.75,1]},{"duration":4,"transform":{"skX":12.29,"skY":12.29},"curve":[0.25,0,0.75,1]},{"duration":0,"transform":{"skX":-12.19,"skY":-12.19}}],"name":"bone16"},{"frame":[{"duration":7,"transform":{"skX":-10.37,"skY":-10.37},"curve":[0.25,0,0.75,1]},{"duration":7,"transform":{"skX":-34.8,"skY":-34.8},"curve":[0.25,0,0.75,1]},{"duration":7,"transform":{"skX":27.48,"skY":27.48},"curve":[0.25,0,0.75,1]},{"duration":7,"transform":{"skX":-34.8,"skY":-34.8},"curve":[0.25,0,0.75,1]},{"duration":7,"transform":{"skX":27.48,"skY":27.48},"curve":[0.25,0,0.75,1]},{"duration":5,"transform":{"skX":-34.8,"skY":-34.8},"curve":[0.25,0,0.75,1]},{"duration":0,"transform":{"skX":-10.37,"skY":-10.37}}],"name":"bone15"},{"frame":[{"duration":6,"transform":{"skX":11.02,"skY":11.02},"curve":[0.25,0,0.75,1]},{"duration":7,"transform":{"skX":-78.01,"skY":-78.01},"curve":[0.25,0,0.75,1]},{"duration":7,"transform":{"skX":-11.77,"skY":-11.77},"curve":[0.25,0,0.75,1]},{"duration":7,"transform":{"skX":-78.01,"skY":-78.01},"curve":[0.25,0,0.75,1]},{"duration":7,"transform":{"skX":-11.77,"skY":-11.77},"curve":[0.25,0,0.75,1]},{"duration":6,"transform":{"skX":-78.01,"skY":-78.01},"curve":[0.25,0,0.75,1]},{"duration":0,"transform":{"skX":11.02,"skY":11.02}}],"name":"bone14"},{"frame":[{"duration":4,"transform":{"skX":8.41,"skY":8.41},"curve":[0.25,0,0.75,1]},{"duration":7,"transform":{"skX":-30.2,"skY":-30.2},"curve":[0.25,0,0.75,1]},{"duration":7,"transform":{"skX":13.38,"skY":13.38},"curve":[0.25,0,0.75,1]},{"duration":7,"transform":{"skX":-30.2,"skY":-30.2},"curve":[0.25,0,0.75,1]},{"duration":7,"transform":{"skX":13.38,"skY":13.38},"curve":[0.25,0,0.75,1]},{"duration":8,"transform":{"skX":-30.2,"skY":-30.2},"curve":[0.25,0,0.75,1]},{"duration":0,"transform":{"skX":8.41,"skY":8.41}}],"name":"bone13"},{"frame":[{"duration":6,"transform":{},"curve":[0.25,0,0.75,1]},{"duration":6,"transform":{"skX":-29.58,"skY":-29.58},"curve":[0.25,0,0.75,1]},{"duration":6,"transform":{"skX":60.12,"skY":60.12},"curve":[0.25,0,0.75,1]},{"duration":6,"transform":{"skX":-29.58,"skY":-29.58},"curve":[0.25,0,0.75,1]},{"duration":6,"transform":{"skX":60.12,"skY":60.12},"curve":[0.25,0,0.75,1]},{"duration":6,"transform":{"skX":-29.58,"skY":-29.58},"curve":[0.25,0,0.75,1]},{"duration":4,"transform":{"skX":60.12,"skY":60.12},"curve":[0.25,0,0.75,1]},{"duration":0,"transform":{}}],"name":"bone11"},{"frame":[{"duration":5,"transform":{},"curve":[0.25,0,0.75,1]},{"duration":6,"transform":{"skX":-23.71,"skY":-23.71},"curve":[0.25,0,0.75,1]},{"duration":6,"transform":{"skX":75.22,"skY":75.22},"curve":[0.25,0,0.75,1]},{"duration":6,"transform":{"skX":-23.71,"skY":-23.71},"curve":[0.25,0,0.75,1]},{"duration":6,"transform":{"skX":75.22,"skY":75.22},"curve":[0.25,0,0.75,1]},{"duration":6,"transform":{"skX":-23.71,"skY":-23.71},"curve":[0.25,0,0.75,1]},{"duration":5,"transform":{"skX":75.22,"skY":75.22},"curve":[0.25,0,0.75,1]},{"duration":0,"transform":{}}],"name":"bone10"},{"frame":[{"duration":3,"transform":{},"curve":[0.25,0,0.75,1]},{"duration":6,"transform":{"skX":-45.48,"skY":-45.48},"curve":[0.25,0,0.75,1]},{"duration":6,"transform":{"skX":37.25,"skY":37.25},"curve":[0.25,0,0.75,1]},{"duration":6,"transform":{"skX":-45.48,"skY":-45.48},"curve":[0.25,0,0.75,1]},{"duration":6,"transform":{"skX":37.25,"skY":37.25},"curve":[0.25,0,0.75,1]},{"duration":6,"transform":{"skX":-45.48,"skY":-45.48},"curve":[0.25,0,0.75,1]},{"duration":7,"transform":{"skX":37.25,"skY":37.25},"curve":[0.25,0,0.75,1]},{"duration":0,"transform":{}}],"name":"bone9"},{"frame":[{"duration":3,"transform":{},"tweenEasing":0},{"duration":3,"transform":{"skX":-18.09,"skY":-18.09},"tweenEasing":0},{"duration":7,"transform":{"skX":6.32,"skY":6.32},"tweenEasing":0},{"duration":2,"transform":{"skX":-34.02,"skY":-34.02},"tweenEasing":0},{"duration":7,"transform":{"skX":-39.82,"skY":-39.82},"tweenEasing":0},{"duration":7,"transform":{"skX":52.42,"skY":52.42},"curve":[0.25,0,0.75,1]},{"duration":7,"transform":{"skX":-5.8,"skY":-5.8},"curve":[0.25,0,0.75,1]},{"duration":4,"transform":{"skX":52.42,"skY":52.42},"curve":[0.25,0,0.75,1]},{"duration":0,"transform":{}}],"name":"bone6"},{"frame":[{"duration":3,"transform":{},"tweenEasing":0},{"duration":3,"transform":{"skX":-57.84,"skY":-57.84},"tweenEasing":0},{"duration":7,"transform":{"skX":35.14,"skY":35.14},"tweenEasing":0},{"duration":2,"transform":{"skX":-42.73,"skY":-42.73},"tweenEasing":0},{"duration":6,"transform":{"skX":-33.39,"skY":-33.39},"tweenEasing":0},{"duration":7,"transform":{"skX":39.08,"skY":39.08},"curve":[0.25,0,0.75,1]},{"duration":7,"transform":{"skX":-10.55,"skY":-10.55},"curve":[0.25,0,0.75,1]},{"duration":5,"transform":{"skX":39.08,"skY":39.08},"curve":[0.25,0,0.75,1]},{"duration":0,"transform":{}}],"name":"bone5"},{"frame":[{"duration":3,"transform":{},"tweenEasing":0},{"duration":3,"transform":{"skX":-44.11,"skY":-44.11},"tweenEasing":0},{"duration":7,"transform":{"skX":-44.67,"skY":-44.67},"tweenEasing":0},{"duration":2,"transform":{"skX":9.76,"skY":9.76},"tweenEasing":0},{"duration":5,"transform":{"skX":-83.74,"skY":-83.74},"tweenEasing":0},{"duration":7,"transform":{"skX":-34.54,"skY":-34.54},"curve":[0.25,0,0.75,1]},{"duration":7,"transform":{"skX":-89.17,"skY":-89.17},"curve":[0.25,0,0.75,1]},{"duration":6,"transform":{"skX":-34.54,"skY":-34.54},"curve":[0.25,0,0.75,1]},{"duration":0,"transform":{}}],"name":"bone4"},{"frame":[{"duration":3,"transform":{},"tweenEasing":0},{"duration":3,"transform":{"skX":29.76,"skY":29.76},"tweenEasing":0},{"duration":7,"transform":{"skX":-9,"skY":-9},"tweenEasing":0},{"duration":2,"transform":{"skX":31.92,"skY":31.92},"tweenEasing":0},{"duration":3,"transform":{"skX":-57.03,"skY":-57.03},"tweenEasing":0},{"duration":7,"transform":{"skX":12.43,"skY":12.43},"curve":[0.25,0,0.75,1]},{"duration":7,"transform":{"skX":-65,"skY":-65},"curve":[0.25,0,0.75,1]},{"duration":8,"transform":{"skX":12.43,"skY":12.43},"curve":[0.25,0,0.75,1]},{"duration":0,"transform":{}}],"name":"bone3"},{"frame":[{"duration":3,"transform":{},"tweenEasing":0},{"duration":3,"transform":{"skX":-21.42,"skY":-21.42},"tweenEasing":0},{"duration":7,"transform":{"skX":-14.91,"skY":-14.91},"tweenEasing":0},{"duration":2,"transform":{"skX":-23.54,"skY":-23.54},"tweenEasing":0},{"duration":5,"transform":{"y":-23.91,"skX":-273.69,"skY":-273.69,"x":-8.16},"tweenEasing":0},{"duration":7,"transform":{"y":-23.91,"skX":-321.26,"skY":-321.26,"x":-8.16},"curve":[0.25,0,0.75,1]},{"duration":3,"transform":{"y":-23.91,"skX":-263.5,"skY":-263.5,"x":-8.16},"curve":[0.25,0,0.75,1]},{"duration":4,"transform":{"y":-23.91,"skX":-263.5,"skY":-263.5,"x":-8.16},"tweenEasing":0},{"duration":6,"transform":{"y":-23.91,"skX":-321.26,"skY":-321.26,"x":-8.16},"curve":[0.25,0,0.75,1]},{"duration":0,"transform":{}}],"name":"bone2"},{"frame":[{"duration":6,"transform":{},"tweenEasing":0},{"duration":7,"transform":{"scX":1.055,"scY":1.055,"x":-29.24},"tweenEasing":0},{"duration":2,"transform":{"scX":1.055,"y":-0.91,"scY":1.055,"x":-43.87},"tweenEasing":0},{"duration":5,"transform":{"scX":0.997,"y":-1.82,"scY":0.997,"x":27.41},"tweenEasing":0},{"duration":10,"transform":{"scX":1.115,"y":-1.82,"scY":1.115,"x":27.41},"tweenEasing":0},{"duration":10,"transform":{"scX":0.997,"y":-1.82,"scY":0.997,"x":27.41},"tweenEasing":0},{"duration":0,"transform":{}}],"name":"bone29"}],"slot":[{"frame":[{"tweenEasing":0,"duration":40,"displayIndex":-1},{"tweenEasing":null,"duration":0,"displayIndex":-1}],"name":"biyan"},{"frame":[{"tweenEasing":0,"duration":40},{"tweenEasing":null,"duration":0}],"name":"chixu4"},{"frame":[{"tweenEasing":0,"duration":40},{"tweenEasing":null,"duration":0}],"name":"chuxu1"},{"frame":[{"tweenEasing":null,"duration":40}],"name":"chuxu2"},{"frame":[{"tweenEasing":0,"duration":40},{"tweenEasing":null,"duration":0}],"name":"chuxu3"},{"frame":[{"tweenEasing":0,"duration":40},{"tweenEasing":null,"duration":0}],"name":"chuxu5"},{"frame":[{"tweenEasing":0,"duration":40},{"tweenEasing":null,"duration":0}],"name":"chuxu6"},{"frame":[{"tweenEasing":0,"duration":40},{"tweenEasing":null,"duration":0}],"name":"shenti"},{"frame":[{"tweenEasing":null,"duration":40,"displayIndex":-1}],"name":"shihua"},{"frame":[{"tweenEasing":0,"duration":40},{"tweenEasing":null,"duration":0}],"name":"ty"}],"ffd":[{"frame":[{"duration":40,"offset":0,"vertices":[],"tweenEasing":null},{"duration":0,"offset":0,"vertices":[],"tweenEasing":null}],"scale":1,"slot":"chixu4","offset":0,"name":"chixu4","skin":""},{"frame":[{"duration":40,"offset":0,"vertices":[],"tweenEasing":null},{"duration":0,"offset":0,"vertices":[],"tweenEasing":null}],"scale":1,"slot":"chuxu1","offset":0,"name":"chuxu1","skin":""},{"frame":[{"duration":40,"offset":0,"vertices":[],"tweenEasing":null}],"scale":1,"slot":"chuxu2","offset":0,"name":"chuxu2","skin":""},{"frame":[{"duration":40,"offset":0,"vertices":[],"tweenEasing":null},{"duration":0,"offset":0,"vertices":[],"tweenEasing":null}],"scale":1,"slot":"chuxu3","offset":0,"name":"chuxu3","skin":""},{"frame":[{"duration":40,"offset":0,"vertices":[],"tweenEasing":null},{"duration":0,"offset":0,"vertices":[],"tweenEasing":null}],"scale":1,"slot":"chuxu5","offset":0,"name":"chuxu5","skin":""},{"frame":[{"duration":40,"offset":0,"vertices":[],"tweenEasing":null},{"duration":0,"offset":0,"vertices":[],"tweenEasing":null}],"scale":1,"slot":"chuxu6","offset":0,"name":"chuxu6","skin":""},{"frame":[{"duration":13,"offset":0,"vertices":[],"tweenEasing":null},{"duration":2,"offset":0,"vertices":[],"tweenEasing":0},{"duration":15,"offset":82,"vertices":[0.98,3.83,-5.45,4.97,0,0,0,0,0,0,0,0,0,0,0,0,0,0,0,0,-4.58,-3.44,-4.8,0.51,-2.67,3.2,0.06,4.13,2.88,3.39,4.94,0.77,4.35,-3.02,0,0,0,0,0,0,0,0,0,0,0,0,0,0,0,0,0,0,0,0,0,0,0,0,0,0,0,0,0,0,0,0,0,0,0,0,0,0,0,0,0,0,0,0,0,0,0,0,0,0,0,0,0,0,0,0,0,0,0,0,0,0,0,0,0,0,0,0,0,0,0,0,0,0],"tweenEasing":0},{"duration":10,"offset":82,"vertices":[-1.93,5.39,-8.31,4.31,0,0,0,0,0,0,0,0,0,0,0,0,0,0,0,0,-4.58,-3.44,-4.8,0.51,-2.67,3.2,0.06,4.13,2.88,3.39,4.94,0.77,4.35,-3.02,0,0,0,0,0,0,0,0,0,0,0,0,0,0,0,0,0,0,0,0,0,0,0,0,0,0,0,0,0,0,0,0,0,0,0,0,0,0,0,0,0,0,0,0,0,0,0,0,0,0,0,0,0,0,0,0,0,0,0,0,0,0,0,0,0,0,0,0,0,0,0,0,0,0],"tweenEasing":0},{"duration":0,"offset":0,"vertices":[],"tweenEasing":null}],"scale":1,"slot":"shenti","offset":0,"name":"shenti","skin":""}],"name":"atk"},{"duration":20,"frame":[],"ik":[],"bone":[{"frame":[{"duration":2,"transform":{},"tweenEasing":0},{"duration":3,"transform":{"y":20.02,"skX":-5.12,"skY":-5.12,"x":-32.23},"tweenEasing":0},{"duration":3,"transform":{"y":33.69,"skX":-16.83,"skY":-16.83,"x":-44.33},"tweenEasing":0},{"duration":6,"transform":{"y":20.48,"skX":-16.83,"skY":-16.83,"x":-50.18},"tweenEasing":0},{"duration":6,"transform":{"y":20.02,"skX":-5.12,"skY":-5.12,"x":-32.23},"tweenEasing":0},{"duration":0,"transform":{}}],"name":"bone"},{"frame":[{"duration":2,"transform":{}},{"duration":12,"transform":{}},{"duration":3,"transform":{},"tweenEasing":0},{"duration":3,"transform":{"y":0.3,"scY":0.053,"skX":4.46,"skY":4.46,"x":2.83},"tweenEasing":0},{"duration":0,"transform":{}}],"name":"bone7"},{"frame":[{"duration":2,"transform":{},"tweenEasing":0},{"duration":7,"transform":{"skX":-74.48,"skY":-74.48},"tweenEasing":0},{"duration":5,"transform":{"skX":-31.25,"skY":-31.25},"tweenEasing":0},{"duration":6,"transform":{"skX":-35.94,"skY":-35.94},"tweenEasing":0},{"duration":0,"transform":{}}],"name":"bone8"},{"frame":[{"duration":2,"transform":{"skX":3.46,"skY":3.46},"tweenEasing":0},{"duration":12,"transform":{"skX":-46.64,"skY":-46.64},"tweenEasing":0},{"duration":6,"transform":{"skX":11.94,"skY":11.94},"tweenEasing":0},{"duration":0,"transform":{"skX":3.46,"skY":3.46}}],"name":"bone12"},{"frame":[{"duration":2,"transform":{"skX":33.61,"skY":33.61},"tweenEasing":0},{"duration":3,"transform":{"skX":-300.07,"skY":-300.07},"tweenEasing":0},{"duration":9,"transform":{"skX":-260.05,"skY":-260.05},"tweenEasing":0},{"duration":6,"transform":{"skX":-316.53,"skY":-316.53},"tweenEasing":0},{"duration":0,"transform":{"skX":-326.38,"skY":-326.38}}],"name":"bone17"},{"frame":[{"duration":2,"transform":{},"tweenEasing":0},{"duration":5,"transform":{"skX":-23.15,"skY":-23.15},"tweenEasing":0},{"duration":7,"transform":{"skX":-310.03,"skY":-310.03},"tweenEasing":0},{"duration":6,"transform":{"skX":-310.16,"skY":-310.16},"tweenEasing":0},{"duration":0,"transform":{}}],"name":"bone20"},{"frame":[{"duration":2,"transform":{},"tweenEasing":0},{"duration":12,"transform":{"skX":-36.85,"skY":-36.85},"tweenEasing":0},{"duration":6,"transform":{"skX":12.83,"skY":12.83},"tweenEasing":0},{"duration":0,"transform":{}}],"name":"bone22"},{"frame":[{"duration":2,"transform":{},"tweenEasing":0},{"duration":3,"transform":{"y":3.72,"skX":-6.58,"skY":-6.58,"x":9.44},"tweenEasing":0},{"duration":9,"transform":{"y":3.72,"skX":39.17,"skY":39.17,"x":9.44},"tweenEasing":0},{"duration":6,"transform":{"y":3.72,"skX":17.19,"skY":17.19,"x":9.44},"tweenEasing":0},{"duration":0,"transform":{}}],"name":"bone25"},{"frame":[{"duration":2,"transform":{}},{"duration":12,"transform":{}},{"duration":6,"transform":{}},{"duration":0,"transform":{}}],"name":"root"},{"frame":[{"duration":2,"transform":{},"tweenEasing":0},{"duration":5,"transform":{"y":0.96,"x":6.27},"tweenEasing":0},{"duration":7,"transform":{"y":-8.09,"x":-8.98},"tweenEasing":0},{"duration":6,"transform":{}},{"duration":0,"transform":{}}],"name":"bone28"},{"frame":[{"duration":2,"transform":{}},{"duration":12,"transform":{}},{"duration":6,"transform":{}},{"duration":0,"transform":{}}],"name":"bone27"},{"frame":[{"duration":2,"transform":{},"tweenEasing":0},{"duration":12,"transform":{"skX":-79.7,"skY":-79.7},"tweenEasing":0},{"duration":6,"transform":{"skX":41.03,"skY":41.03},"tweenEasing":0},{"duration":0,"transform":{}}],"name":"bone26"},{"frame":[{"duration":2,"transform":{},"tweenEasing":0},{"duration":12,"transform":{"skX":-41.61,"skY":-41.61},"tweenEasing":0},{"duration":6,"transform":{"skX":51.09,"skY":51.09},"tweenEasing":0},{"duration":0,"transform":{}}],"name":"bone24"},{"frame":[{"duration":2,"transform":{},"tweenEasing":0},{"duration":12,"transform":{"skX":-12.35,"skY":-12.35},"tweenEasing":0},{"duration":6,"transform":{"skX":105.31,"skY":105.31},"tweenEasing":0},{"duration":0,"transform":{}}],"name":"bone23"},{"frame":[{"duration":2,"transform":{}},{"duration":5,"transform":{},"tweenEasing":0},{"duration":7,"transform":{"skX":-47.8,"skY":-47.8},"tweenEasing":0},{"duration":6,"transform":{}},{"duration":0,"transform":{}}],"name":"bone21"},{"frame":[{"duration":2,"transform":{"skX":-52.65,"skY":-52.65},"tweenEasing":0},{"duration":12,"transform":{"skX":-101.96,"skY":-101.96},"tweenEasing":0},{"duration":6,"transform":{"skX":36.65,"skY":36.65},"tweenEasing":0},{"duration":0,"transform":{"skX":-52.65,"skY":-52.65}}],"name":"bone19"},{"frame":[{"duration":2,"transform":{"skX":-41.52,"skY":-41.52},"tweenEasing":0},{"duration":12,"transform":{"skX":-86.18,"skY":-86.18},"tweenEasing":0},{"duration":6,"transform":{"skX":49.85,"skY":49.85},"tweenEasing":0},{"duration":0,"transform":{"skX":-41.52,"skY":-41.52}}],"name":"bone18"},{"frame":[{"duration":2,"transform":{"skX":-12.19,"skY":-12.19},"tweenEasing":0},{"duration":6,"transform":{"skX":27.14,"skY":27.14},"tweenEasing":0},{"duration":6,"transform":{"skX":12.06,"skY":12.06},"tweenEasing":0},{"duration":6,"transform":{"skX":-101.27,"skY":-101.27},"tweenEasing":0},{"duration":0,"transform":{"skX":-12.19,"skY":-12.19}}],"name":"bone16"},{"frame":[{"duration":2,"transform":{"skX":-10.37,"skY":-10.37},"tweenEasing":0},{"duration":6,"transform":{"skX":15.74,"skY":15.74},"tweenEasing":0},{"duration":6,"transform":{"skX":-77.6,"skY":-77.6},"tweenEasing":0},{"duration":6,"transform":{"skX":-47.53,"skY":-47.53},"tweenEasing":0},{"duration":0,"transform":{"skX":-10.37,"skY":-10.37}}],"name":"bone15"},{"frame":[{"duration":2,"transform":{"skX":11.02,"skY":11.02},"tweenEasing":0},{"duration":6,"transform":{"skX":-3.05,"skY":-3.05},"tweenEasing":0},{"duration":6,"transform":{"skX":-81.82,"skY":-81.82},"tweenEasing":0},{"duration":6,"transform":{"skX":-7.93,"skY":-7.93},"tweenEasing":0},{"duration":0,"transform":{"skX":11.02,"skY":11.02}}],"name":"bone14"},{"frame":[{"duration":2,"transform":{"skX":8.41,"skY":8.41},"tweenEasing":0},{"duration":12,"transform":{"skX":43.97,"skY":43.97},"tweenEasing":0},{"duration":6,"transform":{"skX":59.95,"skY":59.95},"tweenEasing":0},{"duration":0,"transform":{"skX":8.41,"skY":8.41}}],"name":"bone13"},{"frame":[{"duration":2,"transform":{},"tweenEasing":0},{"duration":7,"transform":{"skX":-44.03,"skY":-44.03},"tweenEasing":0},{"duration":5,"transform":{"skX":-58.8,"skY":-58.8},"tweenEasing":0},{"duration":6,"transform":{"skX":-44.03,"skY":-44.03},"tweenEasing":0},{"duration":0,"transform":{}}],"name":"bone11"},{"frame":[{"duration":2,"transform":{},"tweenEasing":0},{"duration":7,"transform":{"skX":-54.9,"skY":-54.9},"tweenEasing":0},{"duration":5,"transform":{"skX":-33.38,"skY":-33.38},"tweenEasing":0},{"duration":6,"transform":{"skX":-11.01,"skY":-11.01},"tweenEasing":0},{"duration":0,"transform":{}}],"name":"bone10"},{"frame":[{"duration":2,"transform":{},"tweenEasing":0},{"duration":7,"transform":{"skX":79.86,"skY":79.86},"tweenEasing":0},{"duration":5,"transform":{"skX":21.51,"skY":21.51},"tweenEasing":0},{"duration":6,"transform":{"skX":77.71,"skY":77.71},"tweenEasing":0},{"duration":0,"transform":{}}],"name":"bone9"},{"frame":[{"duration":2,"transform":{},"tweenEasing":0},{"duration":6,"transform":{"skX":11.33,"skY":11.33},"tweenEasing":0},{"duration":6,"transform":{"skX":-59.35,"skY":-59.35},"tweenEasing":0},{"duration":6,"transform":{"skX":-24.63,"skY":-24.63},"tweenEasing":0},{"duration":0,"transform":{}}],"name":"bone6"},{"frame":[{"duration":2,"transform":{},"tweenEasing":0},{"duration":6,"transform":{"skX":-62.38,"skY":-62.38},"tweenEasing":0},{"duration":6,"transform":{"skX":-30.32,"skY":-30.32},"tweenEasing":0},{"duration":6,"transform":{"skX":-16.08,"skY":-16.08},"tweenEasing":0},{"duration":0,"transform":{}}],"name":"bone5"},{"frame":[{"duration":2,"transform":{},"tweenEasing":0},{"duration":6,"transform":{"skX":-4.21,"skY":-4.21},"tweenEasing":0},{"duration":6,"transform":{"skX":-12.55,"skY":-12.55},"tweenEasing":0},{"duration":6,"transform":{"skX":31.83,"skY":31.83},"tweenEasing":0},{"duration":0,"transform":{}}],"name":"bone4"},{"frame":[{"duration":2,"transform":{},"tweenEasing":0},{"duration":6,"transform":{"skX":30.29,"skY":30.29},"tweenEasing":0},{"duration":6,"transform":{"skX":68.22,"skY":68.22},"tweenEasing":0},{"duration":6,"transform":{"skX":38.82,"skY":38.82},"tweenEasing":0},{"duration":0,"transform":{}}],"name":"bone3"},{"frame":[{"duration":2,"transform":{},"tweenEasing":0},{"duration":6,"transform":{"skX":-21.89,"skY":-21.89},"tweenEasing":0},{"duration":6,"transform":{"skX":17.34,"skY":17.34},"tweenEasing":0},{"duration":6,"transform":{"skX":15.09,"skY":15.09},"tweenEasing":0},{"duration":0,"transform":{}}],"name":"bone2"},{"frame":[{"duration":5,"transform":{},"tweenEasing":0},{"duration":15,"transform":{"scX":0.879,"y":-4.14,"scY":0.879,"x":-15.52},"tweenEasing":0},{"duration":0,"transform":{}}],"name":"bone29"}],"slot":[{"frame":[{"tweenEasing":0,"duration":2,"displayIndex":-1},{"tweenEasing":0,"duration":12},{"tweenEasing":0,"duration":3},{"tweenEasing":0,"duration":3,"displayIndex":-1},{"tweenEasing":null,"duration":0,"displayIndex":-1}],"name":"biyan"},{"frame":[{"tweenEasing":0,"duration":20},{"tweenEasing":null,"duration":0}],"name":"chixu4"},{"frame":[{"tweenEasing":0,"duration":20},{"tweenEasing":null,"duration":0}],"name":"chuxu1"},{"frame":[{"tweenEasing":null,"duration":20}],"name":"chuxu2"},{"frame":[{"tweenEasing":0,"duration":20},{"tweenEasing":null,"duration":0}],"name":"chuxu3"},{"frame":[{"tweenEasing":0,"duration":20},{"tweenEasing":null,"duration":0}],"name":"chuxu5"},{"frame":[{"tweenEasing":0,"duration":20},{"tweenEasing":null,"duration":0}],"name":"chuxu6"},{"frame":[{"tweenEasing":0,"duration":20},{"tweenEasing":null,"duration":0}],"name":"shenti"},{"frame":[{"tweenEasing":null,"duration":20,"displayIndex":-1}],"name":"shihua"},{"frame":[{"tweenEasing":0,"duration":20},{"tweenEasing":null,"duration":0}],"name":"ty"}],"ffd":[{"frame":[{"duration":20,"offset":0,"vertices":[],"tweenEasing":null},{"duration":0,"offset":0,"vertices":[],"tweenEasing":null}],"scale":1,"slot":"chixu4","offset":0,"name":"chixu4","skin":""},{"frame":[{"duration":20,"offset":0,"vertices":[],"tweenEasing":null},{"duration":0,"offset":0,"vertices":[],"tweenEasing":null}],"scale":1,"slot":"chuxu1","offset":0,"name":"chuxu1","skin":""},{"frame":[{"duration":20,"offset":0,"vertices":[],"tweenEasing":null}],"scale":1,"slot":"chuxu2","offset":0,"name":"chuxu2","skin":""},{"frame":[{"duration":20,"offset":0,"vertices":[],"tweenEasing":null},{"duration":0,"offset":0,"vertices":[],"tweenEasing":null}],"scale":1,"slot":"chuxu3","offset":0,"name":"chuxu3","skin":""},{"frame":[{"duration":20,"offset":0,"vertices":[],"tweenEasing":null},{"duration":0,"offset":0,"vertices":[],"tweenEasing":null}],"scale":1,"slot":"chuxu5","offset":0,"name":"chuxu5","skin":""},{"frame":[{"duration":20,"offset":0,"vertices":[],"tweenEasing":null},{"duration":0,"offset":0,"vertices":[],"tweenEasing":null}],"scale":1,"slot":"chuxu6","offset":0,"name":"chuxu6","skin":""},{"frame":[{"duration":20,"offset":0,"vertices":[],"tweenEasing":null},{"duration":0,"offset":0,"vertices":[],"tweenEasing":null}],"scale":1,"slot":"shenti","offset":0,"name":"shenti","skin":""}],"name":"byatk"},{"duration":33,"frame":[],"ik":[],"bone":[{"frame":[{"duration":2,"transform":{},"tweenEasing":0},{"duration":6,"transform":{"y":-6.6,"skX":27.16,"skY":27.16,"x":-11},"tweenEasing":0},{"duration":9,"transform":{"y":-10.14,"skX":-12.19,"skY":-12.19,"x":-31.62},"tweenEasing":0},{"duration":4,"transform":{"y":90.31,"skX":85.22,"skY":85.22,"x":43.77},"tweenEasing":0},{"duration":4,"transform":{"y":72.94,"skX":85.22,"skY":85.22,"x":49.76},"tweenEasing":0},{"duration":8,"transform":{"y":87.55,"skX":85.22,"skY":85.22,"x":54.76}}],"name":"bone"},{"frame":[{"duration":33,"transform":{}}],"name":"bone7"},{"frame":[{"duration":5,"transform":{},"tweenEasing":0},{"duration":6,"transform":{"skX":19.53,"skY":19.53},"curve":[0.25,0,0.75,1]},{"duration":7,"transform":{"skX":-36.61,"skY":-36.61},"curve":[0.25,0,0.75,1]},{"duration":6,"transform":{"skX":19.53,"skY":19.53},"curve":[0.25,0,0.75,1]},{"duration":9,"transform":{"skX":-36.61,"skY":-36.61},"curve":[0.25,0,0.75,1]},{"duration":0,"transform":{"skX":301.24,"skY":301.24}}],"name":"bone8"},{"frame":[{"duration":2,"transform":{"skX":3.46,"skY":3.46},"tweenEasing":0},{"duration":2,"transform":{"skX":-18.19,"skY":-18.19},"tweenEasing":0},{"duration":4,"transform":{"skX":15.82,"skY":15.82},"curve":[0.246,0,0.633,0.53]},{"duration":3,"transform":{"skX":-319.15,"skY":-319.15},"curve":[0.38,0.53,0.744,1]},{"duration":6,"transform":{"skX":1.09,"skY":1.09},"curve":[0.25,0,0.75,1]},{"duration":7,"transform":{"skX":-320.99,"skY":-320.99},"curve":[0.25,0,0.75,1]},{"duration":4,"transform":{"skX":1.09,"skY":1.09},"curve":[0.25,0,0.625,0.5]},{"duration":3,"transform":{"skX":-31.32,"skY":-31.32},"curve":[0.375,0.5,0.75,1]},{"duration":2,"transform":{"skX":-35.49,"skY":-35.49}}],"name":"bone12"},{"frame":[{"duration":2,"transform":{"skX":33.61,"skY":33.61},"tweenEasing":0},{"duration":6,"transform":{"skX":-16.02,"skY":-16.02},"tweenEasing":0},{"duration":15,"transform":{"skX":-303.66,"skY":-303.66},"tweenEasing":0},{"duration":6,"transform":{"y":2.32,"skX":-303.66,"skY":-303.66,"x":1.72},"tweenEasing":0},{"duration":4,"transform":{"y":2.32,"skX":-25.25,"skY":-25.25,"x":1.72}}],"name":"bone17"},{"frame":[{"duration":2,"transform":{},"tweenEasing":0},{"duration":6,"transform":{"skX":-27.26,"skY":-27.26},"tweenEasing":0},{"duration":8,"transform":{"skX":-288.05,"skY":-288.05},"tweenEasing":0},{"duration":7,"transform":{"y":-5.59,"skX":33.2,"skY":33.2,"x":4.94},"tweenEasing":0},{"duration":7,"transform":{"y":-5.59,"skX":-313.55,"skY":-313.55,"x":4.94},"tweenEasing":0},{"duration":3,"transform":{"y":-5.59,"skX":10.84,"skY":10.84,"x":4.94}}],"name":"bone20"},{"frame":[{"duration":2,"transform":{},"tweenEasing":0},{"duration":6,"transform":{"skX":-59.94,"skY":-59.94},"tweenEasing":0},{"duration":10,"transform":{"skX":-9.62,"skY":-9.62},"tweenEasing":0},{"duration":8,"transform":{"skX":12.58,"skY":12.58},"tweenEasing":0},{"duration":7,"transform":{"skX":9.87,"skY":9.87}}],"name":"bone22"},{"frame":[{"duration":33,"transform":{}}],"name":"bone25"},{"frame":[{"duration":33,"transform":{}}],"name":"root"},{"frame":[{"duration":33,"transform":{}}],"name":"bone28"},{"frame":[{"duration":33,"transform":{}}],"name":"bone27"},{"frame":[{"duration":33,"transform":{}}],"name":"bone26"},{"frame":[{"duration":2,"transform":{},"tweenEasing":0},{"duration":6,"transform":{"skX":48.21,"skY":48.21},"tweenEasing":0},{"duration":5,"transform":{"skX":-40.32,"skY":-40.32},"tweenEasing":0},{"duration":5,"transform":{"skX":-82.38,"skY":-82.38},"tweenEasing":0},{"duration":8,"transform":{"skX":-25.68,"skY":-25.68},"tweenEasing":0},{"duration":7,"transform":{"skX":-56.38,"skY":-56.38}}],"name":"bone24"},{"frame":[{"duration":2,"transform":{},"tweenEasing":0},{"duration":6,"transform":{"skX":33.9,"skY":33.9},"tweenEasing":0},{"duration":5,"transform":{"skX":-25.08,"skY":-25.08},"tweenEasing":0},{"duration":5,"transform":{"skX":-7.57,"skY":-7.57},"tweenEasing":0},{"duration":8,"transform":{"skX":43.65,"skY":43.65},"tweenEasing":0},{"duration":7,"transform":{"skX":19.88,"skY":19.88}}],"name":"bone23"},{"frame":[{"duration":2,"transform":{},"tweenEasing":0},{"duration":6,"transform":{"skX":-13.85,"skY":-13.85},"tweenEasing":0},{"duration":8,"transform":{"skX":19.86,"skY":19.86},"tweenEasing":0},{"duration":7,"transform":{"skX":-35.89,"skY":-35.89},"tweenEasing":0},{"duration":7,"transform":{"skX":42.45,"skY":42.45},"tweenEasing":0},{"duration":3,"transform":{"skX":2.99,"skY":2.99}}],"name":"bone21"},{"frame":[{"duration":2,"transform":{"skX":-52.65,"skY":-52.65},"tweenEasing":0},{"duration":6,"transform":{"skX":-76.82,"skY":-76.82},"tweenEasing":0},{"duration":21,"transform":{"skX":42.26,"skY":42.26},"tweenEasing":0},{"duration":4,"transform":{"skX":-14.61,"skY":-14.61}}],"name":"bone19"},{"frame":[{"duration":2,"transform":{"skX":-41.52,"skY":-41.52},"tweenEasing":0},{"duration":6,"transform":{"skX":-66.86,"skY":-66.86},"tweenEasing":0},{"duration":21,"transform":{"skX":38.13,"skY":38.13},"tweenEasing":0},{"duration":4,"transform":{"skX":-20.21,"skY":-20.21}}],"name":"bone18"},{"frame":[{"duration":6,"transform":{"skX":-12.19,"skY":-12.19},"tweenEasing":0},{"duration":7,"transform":{"skX":12.29,"skY":12.29},"curve":[0.25,0,0.75,1]},{"duration":6,"transform":{"skX":62.36,"skY":62.36},"curve":[0.25,0,0.75,1]},{"duration":7,"transform":{"skX":12.29,"skY":12.29},"curve":[0.25,0,0.75,1]},{"duration":2,"transform":{"skX":62.36,"skY":62.36},"curve":[0.275,0,0.62,0.4]},{"duration":3,"transform":{"skX":85.01,"skY":85.01},"curve":[0.333,0.33,0.757,1]},{"duration":2,"transform":{"skX":-13.98,"skY":-13.98}}],"name":"bone16"},{"frame":[{"duration":5,"transform":{"skX":-10.37,"skY":-10.37},"tweenEasing":0},{"duration":7,"transform":{"skX":-34.8,"skY":-34.8},"curve":[0.25,0,0.75,1]},{"duration":6,"transform":{"skX":27.48,"skY":27.48},"curve":[0.25,0,0.75,1]},{"duration":7,"transform":{"skX":-34.8,"skY":-34.8},"curve":[0.25,0,0.75,1]},{"duration":3,"transform":{"skX":27.48,"skY":27.48},"curve":[0.257,0,0.618,0.45]},{"duration":3,"transform":{"skX":82.63,"skY":82.63},"curve":[0.362,0.44,0.754,1]},{"duration":2,"transform":{"skX":-5.57,"skY":-5.57}}],"name":"bone15"},{"frame":[{"duration":4,"transform":{"skX":11.02,"skY":11.02},"tweenEasing":0},{"duration":7,"transform":{"skX":-78.01,"skY":-78.01},"curve":[0.25,0,0.75,1]},{"duration":6,"transform":{"skX":-11.77,"skY":-11.77},"curve":[0.25,0,0.75,1]},{"duration":7,"transform":{"skX":-78.01,"skY":-78.01},"curve":[0.25,0,0.75,1]},{"duration":4,"transform":{"skX":-11.77,"skY":-11.77},"curve":[0.25,0,0.625,0.5]},{"duration":3,"transform":{"skX":-30.46,"skY":-30.46},"curve":[0.375,0.5,0.75,1]},{"duration":2,"transform":{"skX":-66.83,"skY":-66.83}}],"name":"bone14"},{"frame":[{"duration":2,"transform":{"skX":8.41,"skY":8.41},"tweenEasing":0},{"duration":7,"transform":{"skX":-30.2,"skY":-30.2},"curve":[0.25,0,0.75,1]},{"duration":6,"transform":{"skX":13.38,"skY":13.38},"curve":[0.25,0,0.75,1]},{"duration":7,"transform":{"skX":-30.2,"skY":-30.2},"curve":[0.25,0,0.75,1]},{"duration":6,"transform":{"skX":13.38,"skY":13.38},"curve":[0.244,0,0.641,0.57]},{"duration":3,"transform":{"skX":-37.65,"skY":-37.65},"curve":[0.382,0.55,0.739,1]},{"duration":2,"transform":{"skX":-7.66,"skY":-7.66}}],"name":"bone13"},{"frame":[{"duration":6,"transform":{},"tweenEasing":0},{"duration":6,"transform":{"skX":-29.58,"skY":-29.58},"curve":[0.25,0,0.75,1]},{"duration":7,"transform":{"skX":60.12,"skY":60.12},"curve":[0.25,0,0.75,1]},{"duration":6,"transform":{"skX":-29.58,"skY":-29.58},"curve":[0.25,0,0.75,1]},{"duration":8,"transform":{"skX":60.12,"skY":60.12},"curve":[0.25,0,0.75,1]},{"duration":0,"transform":{"skX":-2.88,"skY":-2.88}}],"name":"bone11"},{"frame":[{"duration":5,"transform":{},"tweenEasing":0},{"duration":6,"transform":{"skX":-23.71,"skY":-23.71},"curve":[0.25,0,0.75,1]},{"duration":7,"transform":{"skX":75.22,"skY":75.22},"curve":[0.25,0,0.75,1]},{"duration":6,"transform":{"skX":-23.71,"skY":-23.71},"curve":[0.25,0,0.75,1]},{"duration":9,"transform":{"skX":75.22,"skY":75.22},"curve":[0.25,0,0.75,1]},{"duration":0,"transform":{"skX":13.31,"skY":13.31}}],"name":"bone10"},{"frame":[{"duration":3,"transform":{},"tweenEasing":0},{"duration":6,"transform":{"skX":-45.48,"skY":-45.48},"curve":[0.25,0,0.75,1]},{"duration":7,"transform":{"skX":37.25,"skY":37.25},"curve":[0.25,0,0.75,1]},{"duration":6,"transform":{"skX":-45.48,"skY":-45.48},"curve":[0.25,0,0.75,1]},{"duration":11,"transform":{"skX":37.25,"skY":37.25},"curve":[0.25,0,0.75,1]},{"duration":0,"transform":{"skX":-12.02,"skY":-12.02}}],"name":"bone9"},{"frame":[{"duration":2,"transform":{},"tweenEasing":0},{"duration":6,"transform":{"skX":-31.03,"skY":-31.03},"tweenEasing":0},{"duration":9,"transform":{"skX":-37.05,"skY":-37.05},"tweenEasing":0},{"duration":9,"transform":{"skX":0.4,"skY":0.4},"tweenEasing":0},{"duration":7,"transform":{"skX":-50.52,"skY":-50.52}}],"name":"bone6"},{"frame":[{"duration":2,"transform":{},"tweenEasing":0},{"duration":6,"transform":{"skX":-43.33,"skY":-43.33},"tweenEasing":0},{"duration":9,"transform":{"skX":-29.84,"skY":-29.84},"tweenEasing":0},{"duration":9,"transform":{"skX":33.31,"skY":33.31},"tweenEasing":0},{"duration":7,"transform":{"skX":-40.65,"skY":-40.65}}],"name":"bone5"},{"frame":[{"duration":2,"transform":{},"tweenEasing":0},{"duration":6,"transform":{"skX":7.88,"skY":7.88},"tweenEasing":0},{"duration":9,"transform":{"skX":-72.27,"skY":-72.27},"tweenEasing":0},{"duration":9,"transform":{"skX":-13.22,"skY":-13.22},"tweenEasing":0},{"duration":7,"transform":{"skX":50.95,"skY":50.95}}],"name":"bone4"},{"frame":[{"duration":2,"transform":{},"tweenEasing":0},{"duration":6,"transform":{"skX":-36.72,"skY":-36.72},"tweenEasing":0},{"duration":9,"transform":{"skX":-16.25,"skY":-16.25},"tweenEasing":0},{"duration":9,"transform":{"skX":-7.93,"skY":-7.93},"tweenEasing":0},{"duration":7,"transform":{"skX":-0.35,"skY":-0.35}}],"name":"bone3"},{"frame":[{"duration":2,"transform":{},"tweenEasing":0},{"duration":6,"transform":{"skX":-42.33,"skY":-42.33},"tweenEasing":0},{"duration":9,"transform":{"skX":-302.19,"skY":-302.19},"tweenEasing":0},{"duration":9,"transform":{"skX":-311.35,"skY":-311.35},"tweenEasing":0},{"duration":7,"transform":{"skX":7.96,"skY":7.96}}],"name":"bone2"},{"frame":[{"duration":5,"transform":{},"tweenEasing":0},{"duration":12,"transform":{"scX":0.927,"scY":0.927},"tweenEasing":0},{"duration":16,"transform":{"scX":1.109,"scY":1.109}}],"name":"bone29"}],"slot":[{"frame":[{"tweenEasing":0,"duration":2,"displayIndex":-1},{"tweenEasing":null,"duration":31}],"name":"biyan"},{"frame":[{"tweenEasing":null,"duration":33}],"name":"chixu4"},{"frame":[{"tweenEasing":null,"duration":33}],"name":"chuxu1"},{"frame":[{"tweenEasing":null,"duration":33}],"name":"chuxu2"},{"frame":[{"tweenEasing":null,"duration":33}],"name":"chuxu3"},{"frame":[{"tweenEasing":null,"duration":33}],"name":"chuxu5"},{"frame":[{"tweenEasing":null,"duration":33}],"name":"chuxu6"},{"frame":[{"tweenEasing":null,"duration":33}],"name":"shenti"},{"frame":[{"tweenEasing":null,"duration":33,"displayIndex":-1}],"name":"shihua"},{"frame":[{"tweenEasing":null,"duration":33}],"name":"ty"}],"ffd":[{"frame":[{"duration":33,"offset":0,"vertices":[],"tweenEasing":null}],"scale":1,"slot":"chixu4","offset":0,"name":"chixu4","skin":""},{"frame":[{"duration":33,"offset":0,"vertices":[],"tweenEasing":null}],"scale":1,"slot":"chuxu1","offset":0,"name":"chuxu1","skin":""},{"frame":[{"duration":33,"offset":0,"vertices":[],"tweenEasing":null}],"scale":1,"slot":"chuxu2","offset":0,"name":"chuxu2","skin":""},{"frame":[{"duration":33,"offset":0,"vertices":[],"tweenEasing":null}],"scale":1,"slot":"chuxu3","offset":0,"name":"chuxu3","skin":""},{"frame":[{"duration":33,"offset":0,"vertices":[],"tweenEasing":null}],"scale":1,"slot":"chuxu5","offset":0,"name":"chuxu5","skin":""},{"frame":[{"duration":33,"offset":0,"vertices":[],"tweenEasing":null}],"scale":1,"slot":"chuxu6","offset":0,"name":"chuxu6","skin":""},{"frame":[{"duration":33,"offset":0,"vertices":[],"tweenEasing":null}],"scale":1,"slot":"shenti","offset":0,"name":"shenti","skin":""}],"name":"die"},{"duration":0,"frame":[],"ik":[],"bone":[{"frame":[{"duration":0,"transform":{}}],"name":"bone"},{"frame":[{"duration":0,"transform":{}}],"name":"bone7"},{"frame":[{"duration":0,"transform":{}}],"name":"bone8"},{"frame":[{"duration":0,"transform":{"skX":3.46,"skY":3.46}}],"name":"bone12"},{"frame":[{"duration":0,"transform":{"skX":33.61,"skY":33.61}}],"name":"bone17"},{"frame":[{"duration":0,"transform":{}}],"name":"bone20"},{"frame":[{"duration":0,"transform":{}}],"name":"bone22"},{"frame":[{"duration":0,"transform":{}}],"name":"bone25"},{"frame":[{"duration":0,"transform":{}}],"name":"root"},{"frame":[{"duration":0,"transform":{}}],"name":"bone28"},{"frame":[{"duration":0,"transform":{}}],"name":"bone27"},{"frame":[{"duration":0,"transform":{}}],"name":"bone26"},{"frame":[{"duration":0,"transform":{}}],"name":"bone24"},{"frame":[{"duration":0,"transform":{}}],"name":"bone23"},{"frame":[{"duration":0,"transform":{}}],"name":"bone21"},{"frame":[{"duration":0,"transform":{"skX":-52.65,"skY":-52.65}}],"name":"bone19"},{"frame":[{"duration":0,"transform":{"skX":-41.52,"skY":-41.52}}],"name":"bone18"},{"frame":[{"duration":0,"transform":{"skX":-12.19,"skY":-12.19}}],"name":"bone16"},{"frame":[{"duration":0,"transform":{"skX":-10.37,"skY":-10.37}}],"name":"bone15"},{"frame":[{"duration":0,"transform":{"skX":11.02,"skY":11.02}}],"name":"bone14"},{"frame":[{"duration":0,"transform":{"skX":8.41,"skY":8.41}}],"name":"bone13"},{"frame":[{"duration":0,"transform":{}}],"name":"bone11"},{"frame":[{"duration":0,"transform":{}}],"name":"bone10"},{"frame":[{"duration":0,"transform":{}}],"name":"bone9"},{"frame":[{"duration":0,"transform":{}}],"name":"bone6"},{"frame":[{"duration":0,"transform":{}}],"name":"bone5"},{"frame":[{"duration":0,"transform":{}}],"name":"bone4"},{"frame":[{"duration":0,"transform":{}}],"name":"bone3"},{"frame":[{"duration":0,"transform":{}}],"name":"bone2"},{"frame":[{"duration":0,"transform":{}}],"name":"bone29"}],"slot":[{"frame":[{"tweenEasing":null,"duration":0,"displayIndex":-1}],"name":"biyan"},{"frame":[{"tweenEasing":null,"duration":0,"displayIndex":-1}],"name":"chixu4"},{"frame":[{"tweenEasing":null,"duration":0,"displayIndex":-1}],"name":"chuxu1"},{"frame":[{"tweenEasing":null,"duration":0,"displayIndex":-1}],"name":"chuxu2"},{"frame":[{"tweenEasing":null,"duration":0,"displayIndex":-1}],"name":"chuxu3"},{"frame":[{"tweenEasing":null,"duration":0,"displayIndex":-1}],"name":"chuxu5"},{"frame":[{"tweenEasing":null,"duration":0,"displayIndex":-1}],"name":"chuxu6"},{"frame":[{"tweenEasing":null,"duration":0,"displayIndex":-1}],"name":"shenti"},{"frame":[{"tweenEasing":null,"duration":0}],"name":"shihua"},{"frame":[{"tweenEasing":null,"duration":0}],"name":"ty"}],"ffd":[{"frame":[{"duration":0,"offset":0,"vertices":[],"tweenEasing":null}],"scale":1,"slot":"chixu4","offset":0,"name":"chixu4","skin":""},{"frame":[{"duration":0,"offset":0,"vertices":[],"tweenEasing":null}],"scale":1,"slot":"chuxu1","offset":0,"name":"chuxu1","skin":""},{"frame":[{"duration":0,"offset":0,"vertices":[],"tweenEasing":null}],"scale":1,"slot":"chuxu2","offset":0,"name":"chuxu2","skin":""},{"frame":[{"duration":0,"offset":0,"vertices":[],"tweenEasing":null}],"scale":1,"slot":"chuxu3","offset":0,"name":"chuxu3","skin":""},{"frame":[{"duration":0,"offset":0,"vertices":[],"tweenEasing":null}],"scale":1,"slot":"chuxu5","offset":0,"name":"chuxu5","skin":""},{"frame":[{"duration":0,"offset":0,"vertices":[],"tweenEasing":null}],"scale":1,"slot":"chuxu6","offset":0,"name":"chuxu6","skin":""},{"frame":[{"duration":0,"offset":0,"vertices":[],"tweenEasing":null}],"scale":1,"slot":"shenti","offset":0,"name":"shenti","skin":""}],"name":"shihua"},{"duration":40,"frame":[],"ik":[],"bone":[{"frame":[{"duration":20,"transform":{},"curve":[0.25,0,0.75,1]},{"duration":20,"transform":{"y":-15.89},"curve":[0.25,0,0.75,1]},{"duration":0,"transform":{}}],"name":"bone"},{"frame":[{"duration":40,"transform":{}},{"duration":0,"transform":{}}],"name":"bone7"},{"frame":[{"duration":20,"transform":{},"curve":[0.25,0,0.75,1]},{"duration":20,"transform":{"skX":-40.42,"skY":-40.42},"curve":[0.25,0,0.75,1]},{"duration":0,"transform":{}}],"name":"bone8"},{"frame":[{"duration":6,"transform":{"skX":3.46,"skY":3.46},"curve":[0.381,0.58,0.731,1]},{"duration":20,"transform":{},"curve":[0.25,0,0.75,1]},{"duration":14,"transform":{"skX":14.3,"skY":14.3},"curve":[0.242,0,0.655,0.62]},{"duration":0,"transform":{"skX":3.46,"skY":3.46}}],"name":"bone12"},{"frame":[{"duration":20,"transform":{"skX":33.61,"skY":33.61},"curve":[0.25,0,0.75,1]},{"duration":20,"transform":{"skX":-352.95,"skY":-352.95},"curve":[0.25,0,0.75,1]},{"duration":0,"transform":{"skX":-326.38,"skY":-326.38}}],"name":"bone17"},{"frame":[{"duration":20,"transform":{},"curve":[0.25,0,0.75,1]},{"duration":20,"transform":{"skX":-14.82,"skY":-14.82},"curve":[0.25,0,0.75,1]},{"duration":0,"transform":{}}],"name":"bone20"},{"frame":[{"duration":20,"transform":{},"curve":[0.25,0,0.75,1]},{"duration":20,"transform":{"skX":-340.61,"skY":-340.61},"curve":[0.25,0,0.75,1]},{"duration":0,"transform":{}}],"name":"bone22"},{"frame":[{"duration":20,"transform":{},"curve":[0.25,0,0.75,1]},{"duration":20,"transform":{"skX":31.21,"skY":31.21},"curve":[0.25,0,0.75,1]},{"duration":0,"transform":{}}],"name":"bone25"},{"frame":[{"duration":40,"transform":{}},{"duration":0,"transform":{}}],"name":"root"},{"frame":[{"duration":8,"transform":{},"curve":[0.405,0.53,0.75,1]},{"duration":20,"transform":{"y":-2.59,"x":-4.12},"curve":[0.25,0,0.75,1]},{"duration":12,"transform":{"y":3.64,"x":2.93},"curve":[0.25,0,0.558,0.49]},{"duration":0,"transform":{}}],"name":"bone28"},{"frame":[{"duration":8,"transform":{},"tweenEasing":0},{"duration":8,"transform":{"y":5.61,"x":1.99}},{"duration":2,"transform":{"y":5.61,"x":1.99},"tweenEasing":0},{"duration":2,"transform":{"y":5.61,"x":1.99},"tweenEasing":0},{"duration":2,"transform":{"scX":0.151,"y":5.61,"x":1.99},"tweenEasing":0},{"duration":3,"transform":{"y":5.61,"x":1.99}},{"duration":8,"transform":{"y":-2.62,"x":1.79}},{"duration":7,"transform":{"y":-2.62,"x":1.79},"tweenEasing":0},{"duration":0,"transform":{}}],"name":"bone27"},{"frame":[{"duration":8,"transform":{},"curve":[0.369,0.51,0.75,1]},{"duration":20,"transform":{"skX":-23.96,"skY":-23.96},"curve":[0.25,0,0.75,1]},{"duration":12,"transform":{"skX":32.56,"skY":32.56},"curve":[0.25,0,0.573,0.47]},{"duration":0,"transform":{}}],"name":"bone26"},{"frame":[{"duration":13,"transform":{},"curve":[0.358,0.5,0.75,1]},{"duration":20,"transform":{"skX":-48,"skY":-48},"curve":[0.25,0,0.75,1]},{"duration":7,"transform":{"skX":17.98,"skY":17.98},"curve":[0.25,0,0.542,0.46]},{"duration":0,"transform":{}}],"name":"bone24"},{"frame":[{"duration":8,"transform":{},"curve":[0.358,0.5,0.75,1]},{"duration":20,"transform":{"skX":-26.33,"skY":-26.33},"curve":[0.25,0,0.75,1]},{"duration":12,"transform":{"skX":15.18,"skY":15.18},"curve":[0.25,0,0.542,0.46]},{"duration":0,"transform":{}}],"name":"bone23"},{"frame":[{"duration":8,"transform":{},"curve":[0.358,0.49,0.75,1]},{"duration":20,"transform":{"skX":21.98,"skY":21.98},"curve":[0.25,0,0.75,1]},{"duration":12,"transform":{"skX":-16.54,"skY":-16.54},"curve":[0.25,0,0.641,0.46]},{"duration":0,"transform":{}}],"name":"bone21"},{"frame":[{"duration":20,"transform":{"skX":-52.65,"skY":-52.65},"curve":[0.25,0,0.75,1]},{"duration":20,"transform":{"skX":13.77,"skY":13.77},"curve":[0.25,0,0.75,1]},{"duration":0,"transform":{"skX":-52.65,"skY":-52.65}}],"name":"bone19"},{"frame":[{"duration":10,"transform":{"skX":-41.52,"skY":-41.52},"curve":[0.322,0.42,0.75,1]},{"duration":20,"transform":{"skX":3.75,"skY":3.75},"curve":[0.25,0,0.75,1]},{"duration":10,"transform":{"skX":-60,"skY":-60},"curve":[0.25,0,0.563,0.49]},{"duration":0,"transform":{"skX":-41.52,"skY":-41.52}}],"name":"bone18"},{"frame":[{"duration":6,"transform":{"skX":-12.19,"skY":-12.19},"curve":[0.381,0.58,0.731,1]},{"duration":20,"transform":{},"curve":[0.25,0,0.75,1]},{"duration":14,"transform":{"skX":-50.33,"skY":-50.33},"curve":[0.242,0,0.655,0.62]},{"duration":0,"transform":{"skX":-12.19,"skY":-12.19}}],"name":"bone16"},{"frame":[{"duration":6,"transform":{"skX":-10.37,"skY":-10.37},"curve":[0.381,0.58,0.731,1]},{"duration":20,"transform":{},"curve":[0.25,0,0.75,1]},{"duration":14,"transform":{"skX":-42.84,"skY":-42.84},"curve":[0.242,0,0.655,0.62]},{"duration":0,"transform":{"skX":-10.37,"skY":-10.37}}],"name":"bone15"},{"frame":[{"duration":6,"transform":{"skX":11.02,"skY":11.02},"curve":[0.25,0,0.604,0.46]},{"duration":13,"transform":{},"curve":[0.332,0.46,0.75,1]},{"duration":21,"transform":{"skX":-22.22,"skY":-22.22},"curve":[0.25,0,0.75,1]},{"duration":0,"transform":{"skX":11.02,"skY":11.02}}],"name":"bone14"},{"frame":[{"duration":6,"transform":{"skX":8.41,"skY":8.41},"curve":[0.295,0.27,0.627,0.62]},{"duration":7,"transform":{},"curve":[0.322,0.43,0.75,1]},{"duration":20,"transform":{"skX":-12.73,"skY":-12.73},"curve":[0.25,0,0.75,1]},{"duration":7,"transform":{"skX":14.6,"skY":14.6},"curve":[0.284,0,0.615,0.39]},{"duration":0,"transform":{"skX":8.41,"skY":8.41}}],"name":"bone13"},{"frame":[{"duration":20,"transform":{},"curve":[0.25,0,0.75,1]},{"duration":20,"transform":{"skX":74.98,"skY":74.98},"curve":[0.25,0,0.75,1]},{"duration":0,"transform":{}}],"name":"bone11"},{"frame":[{"duration":20,"transform":{},"curve":[0.25,0,0.75,1]},{"duration":20,"transform":{"skX":69.33,"skY":69.33},"curve":[0.25,0,0.75,1]},{"duration":0,"transform":{}}],"name":"bone10"},{"frame":[{"duration":10,"transform":{},"curve":[0.348,0.46,0.75,1]},{"duration":20,"transform":{"skX":25.8,"skY":25.8},"curve":[0.25,0,0.75,1]},{"duration":10,"transform":{"skX":-23.24,"skY":-23.24},"curve":[0.25,0,0.656,0.55]},{"duration":0,"transform":{}}],"name":"bone9"},{"frame":[{"duration":5,"transform":{},"curve":[0.348,0.48,0.75,1]},{"duration":20,"transform":{"skX":25.29,"skY":25.29},"curve":[0.25,0,0.75,1]},{"duration":15,"transform":{"skX":-44.73,"skY":-44.73},"curve":[0.25,0,0.589,0.55]},{"duration":0,"transform":{}}],"name":"bone6"},{"frame":[{"duration":20,"transform":{},"curve":[0.25,0,0.75,1]},{"duration":20,"transform":{"skX":-34.93,"skY":-34.93},"curve":[0.25,0,0.75,1]},{"duration":0,"transform":{}}],"name":"bone5"},{"frame":[{"duration":14,"transform":{},"curve":[0.312,0.45,0.75,1]},{"duration":20,"transform":{"skX":-19.73,"skY":-19.73},"curve":[0.25,0,0.75,1]},{"duration":6,"transform":{"skX":9.16,"skY":9.16},"curve":[0.25,0,0.615,0.49]},{"duration":0,"transform":{}}],"name":"bone4"},{"frame":[{"duration":8,"transform":{},"curve":[0.312,0.45,0.75,1]},{"duration":20,"transform":{"skX":-10.99,"skY":-10.99},"curve":[0.25,0,0.75,1]},{"duration":12,"transform":{"skX":10.21,"skY":10.21},"curve":[0.25,0,0.615,0.49]},{"duration":0,"transform":{}}],"name":"bone3"},{"frame":[{"duration":20,"transform":{},"curve":[0.25,0,0.75,1]},{"duration":20,"transform":{"skX":13.38,"skY":13.38},"curve":[0.25,0,0.75,1]},{"duration":0,"transform":{}}],"name":"bone2"},{"frame":[{"duration":40,"transform":{}}],"name":"bone29"}],"slot":[{"frame":[{"tweenEasing":0,"duration":40,"displayIndex":-1},{"tweenEasing":null,"duration":0,"displayIndex":-1}],"name":"biyan"},{"frame":[{"tweenEasing":0,"duration":40},{"tweenEasing":null,"duration":0}],"name":"chixu4"},{"frame":[{"tweenEasing":0,"duration":40},{"tweenEasing":null,"duration":0}],"name":"chuxu1"},{"frame":[{"tweenEasing":0,"duration":6},{"tweenEasing":null,"duration":34}],"name":"chuxu2"},{"frame":[{"tweenEasing":0,"duration":40},{"tweenEasing":null,"duration":0}],"name":"chuxu3"},{"frame":[{"tweenEasing":0,"duration":40},{"tweenEasing":null,"duration":0}],"name":"chuxu5"},{"frame":[{"tweenEasing":0,"duration":40},{"tweenEasing":null,"duration":0}],"name":"chuxu6"},{"frame":[{"tweenEasing":0,"duration":40},{"tweenEasing":null,"duration":0}],"name":"shenti"},{"frame":[{"tweenEasing":null,"duration":40,"displayIndex":-1}],"name":"shihua"},{"frame":[{"tweenEasing":null,"duration":40}],"name":"ty"}],"ffd":[{"frame":[{"duration":40,"offset":0,"vertices":[],"tweenEasing":null},{"duration":0,"offset":0,"vertices":[],"tweenEasing":null}],"scale":1,"slot":"chixu4","offset":0,"name":"chixu4","skin":""},{"frame":[{"duration":40,"offset":0,"vertices":[],"tweenEasing":null},{"duration":0,"offset":0,"vertices":[],"tweenEasing":null}],"scale":1,"slot":"chuxu1","offset":0,"name":"chuxu1","skin":""},{"frame":[{"duration":6,"offset":0,"vertices":[],"tweenEasing":null},{"duration":34,"offset":0,"vertices":[],"tweenEasing":null}],"scale":1,"slot":"chuxu2","offset":0,"name":"chuxu2","skin":""},{"frame":[{"duration":40,"offset":0,"vertices":[],"tweenEasing":null},{"duration":0,"offset":0,"vertices":[],"tweenEasing":null}],"scale":1,"slot":"chuxu3","offset":0,"name":"chuxu3","skin":""},{"frame":[{"duration":40,"offset":0,"vertices":[],"tweenEasing":null},{"duration":0,"offset":0,"vertices":[],"tweenEasing":null}],"scale":1,"slot":"chuxu5","offset":0,"name":"chuxu5","skin":""},{"frame":[{"duration":40,"offset":0,"vertices":[],"tweenEasing":null},{"duration":0,"offset":0,"vertices":[],"tweenEasing":null}],"scale":1,"slot":"chuxu6","offset":0,"name":"chuxu6","skin":""},{"frame":[{"duration":40,"offset":0,"vertices":[],"tweenEasing":null},{"duration":0,"offset":0,"vertices":[],"tweenEasing":null}],"scale":1,"slot":"shenti","offset":0,"name":"shenti","skin":""}],"name":"wait"}],"ik":[],"frameRate":30,"name":"armatureName","skin":[{"name":"","slot":[{"display":[{"slotPose":[1,0,0,1,0,0],"userEdges":[33,34,34,31,32,34,0,35,35,30,34,35,29,36,36,1,35,36,2,37,37,28,36,37,3,38,38,27,37,38,26,39,39,4,38,39,5,40,40,25,39,40,24,41,41,6,40,41,7,42,42,23,41,42,8,43,43,22,42,43,21,44,44,9,43,44,10,45,45,20,44,45,19,46,46,11,45,46,47,12,46,47,13,48,48,17,48,15,18,49,49,47,48,49],"vertices":[-26.86,-91.79,-24.26,-82.97,-22.12,-75.54,-22.12,-65.84,-24.8,-55.49,-33.06,-48.33,-40.98,-46.44,-47.91,-47.05,-53.73,-47.02,-57.2,-46.14,-60.31,-44.66,-62.51,-42.34,-64.35,-39.26,-63.94,-35.61,-63.48,-31.43,-65.57,-31.43,-67.3,-31.43,-69.26,-34.95,-70.09,-39.34,-70.09,-46.09,-68.94,-52.3,-65.75,-56.02,-59.92,-59,-54.17,-60.17,-48.67,-60.52,-44,-62.71,-42.95,-65.72,-43.18,-69.75,-44.72,-73.3,-47.15,-78.36,-50.28,-84.16,-54.18,-92.09,-49.51,-101.39,-34.6,-101.38,-44.3,-96.77,-39.45,-87.69,-35,-80.8,-33.78,-74.38,-33.64,-67.98,-35.15,-61.32,-39.26,-56.48,-45.12,-54.01,-50.74,-52.99,-56.64,-52.66,-60.79,-50.28,-63.93,-47.86,-66.07,-44.11,-67.31,-39.3,-66.73,-35.26,-67.79,-39.31],"path":"chuxu2","edges":[18,17,17,16,16,15,15,14,14,13,13,12,12,11,11,10,10,9,9,8,8,7,7,6,6,5,5,4,4,3,3,2,2,1,1,0,0,33,33,32,32,31,31,30,30,29,29,28,28,27,27,26,26,25,25,24,24,23,23,22,22,21,21,20,20,19,19,18],"name":"chuxu2","type":"mesh","triangles":[39,4,3,38,39,3,1,37,2,38,3,2,37,38,2,0,36,1,36,37,1,39,5,4,39,40,5,33,35,0,35,36,0,26,39,38,27,38,37,34,35,33,40,6,5,27,26,38,28,27,37,28,37,36,29,28,36,32,34,33,35,29,36,25,40,39,26,25,39,34,30,35,30,29,35,41,6,40,25,41,40,31,30,34,24,41,25,41,7,6,32,31,34,42,7,41,24,42,41,23,42,24,42,8,7,23,43,42,43,8,42,43,9,8,22,43,23,22,44,43,43,44,9,44,10,9,45,10,44,21,44,22,45,11,10,21,45,44,21,20,45,45,46,11,47,13,12,11,46,12,46,47,12,13,15,14,19,46,45,20,19,45,47,48,13,48,15,13,49,47,46,47,49,48,48,16,15,18,49,46,19,18,46,17,16,48,49,17,48,18,17,49],"bonePose":[3,0.43633072116173927,0.8997863645168649,-0.8997863645168649,0.43633072116173927,-41.84728752204282,-94.36649963623694,13,-0.33512270923417303,0.9421744900789596,-0.9421744900789596,-0.33512270923417303,-31.9213294337178,-74.2183841901508,21,-0.9981771750997538,0.06035169516985556,-0.06035169516985556,-0.9981771750997538,-38.687265387944585,-55.04722067138385,26,-0.6842926061750167,0.72920753502292,-0.72920753502292,-0.6842926061750167,-57.44756462725467,-53.822772856431584,28,-0.013613147670749226,0.999907336812014,-0.999907336812014,-0.013613147670749226,-66.41269606672435,-44.29842415045529],"width":48,"weights":[2,3,0.93299,13,0.067,3,3,0.77965,13,0.22014,21,0.0002,3,3,0.52323,13,0.46974,21,0.00702,3,3,0.24926,13,0.6935,21,0.05723,4,3,0.07991,13,0.71563,21,0.20396,26,0.00048,4,3,0.01241,13,0.51838,21,0.46146,26,0.00773,5,3,0.00095,13,0.25587,21,0.68138,26,0.06171,28,0.00006,4,13,0.08109,21,0.7032,26,0.21415,28,0.00154,4,13,0.01516,21,0.50458,26,0.46827,28,0.01197,4,13,0.00184,21,0.25345,26,0.67546,28,0.06923,3,21,0.08775,26,0.68589,28,0.22635,3,21,0.0198,26,0.48176,28,0.49842,3,21,0.00336,26,0.23001,28,0.76661,3,21,0.00005,26,0.0583,28,0.94163,2,26,0.01322,28,0.98677,2,26,0.00164,28,0.99835,2,26,0.01434,28,0.98565,2,26,0.05435,28,0.94564,3,21,0.00061,26,0.20389,28,0.79548,3,21,0.00844,26,0.49957,28,0.49197,3,21,0.06077,26,0.72763,28,0.21159,4,13,0.00112,21,0.21227,26,0.72734,28,0.05925,5,3,0.00015,13,0.01201,21,0.46131,26,0.51915,28,0.00735,5,3,0.0015,13,0.071,21,0.67538,26,0.25172,28,0.00038,4,3,0.00913,13,0.23215,21,0.67686,26,0.08183,4,3,0.03406,13,0.47537,21,0.47573,26,0.01483,4,3,0.11866,13,0.65612,21,0.22344,26,0.00175,3,3,0.29639,13,0.63109,21,0.0725,3,3,0.56466,13,0.42092,21,0.0144,3,3,0.80446,13,0.19293,21,0.0026,3,3,0.94268,13,0.0571,21,0.00021,2,3,0.98982,13,0.01016,2,3,0.99714,13,0.00285,2,3,0.98806,13,0.01193,2,3,0.99153,13,0.00846,2,3,0.94555,13,0.05443,3,3,0.8021,13,0.19748,21,0.00041,3,3,0.5414,13,0.44957,21,0.00901,3,3,0.26936,13,0.67577,21,0.05485,4,3,0.08634,13,0.70379,21,0.20977,26,0.00008,4,3,0.0206,13,0.50227,21,0.46765,26,0.00946,4,3,0.00265,13,0.23579,21,0.69981,26,0.06174,5,3,0.00029,13,0.06727,21,0.70281,26,0.2295,28,0.00011,4,13,0.00978,21,0.48712,26,0.49543,28,0.00764,3,21,0.22399,26,0.72247,28,0.05352,3,21,0.0644,26,0.72271,28,0.21288,3,21,0.01083,26,0.50405,28,0.4851,3,21,0.00014,26,0.24535,28,0.7545,2,26,0.03216,28,0.96783,2,26,0.11387,28,0.88612],"uvs":[0.90114,0.13719,0.95537,0.26315,1,0.36933,1,0.50797,0.94424,0.6559,0.77206,0.75823,0.60687,0.78527,0.46263,0.77681,0.34136,0.77725,0.26885,0.78982,0.20402,0.81099,0.15818,0.84413,0.11984,0.88814,0.12841,0.94022,0.13824,1,0.09455,1,0.05823,1,0.0174,0.94975,0,0.88699,0,0.7904,0.02401,0.70182,0.0905,0.64865,0.21219,0.60579,0.33198,0.58914,0.44663,0.58408,0.54402,0.5528,0.56579,0.50964,0.56087,0.45215,0.52882,0.40143,0.47828,0.32906,0.41295,0.24622,0.3316,0.13294,0.429,0,0.73966,0,0.53745,0.06588,0.63845,0.19586,0.7315,0.29408,0.7567,0.38591,0.75987,0.47745,0.72846,0.5725,0.64276,0.64175,0.52073,0.67712,0.40348,0.69185,0.28059,0.69658,0.19413,0.73067,0.12855,0.76521,0.08417,0.81899,0.05795,0.88754,0.07026,0.94521,0.04804,0.88745],"height":70,"transform":{}}],"name":"chuxu2"},{"display":[{"path":"shihua","type":"image","name":"shihua","transform":{"y":-103.47,"x":-9.8}}],"name":"shihua"},{"display":[{"slotPose":[1,0,0,1,0,0],"userEdges":[4,16,16,8,6,16,3,17,17,9,16,17,2,18,18,10,17,18,1,19,19,11,18,19,0,20,20,12,19,20,20,14],"vertices":[4.42,-79.16,6.58,-74.68,8.91,-71.4,11.12,-69,13.93,-67.75,17.89,-67.51,17.89,-63.66,17.88,-61.56,14.41,-58.39,7.28,-58.4,-0.05,-58.4,-5.01,-61.88,-8.61,-64.97,-10.1,-67.76,-10.11,-81.38,0.99,-81.37,14.17,-63.15,9.22,-63.74,4.69,-65.28,0.62,-68.1,-2.31,-71.83],"path":"chuxu3","edges":[13,12,12,11,11,10,10,9,9,8,8,7,7,6,6,5,5,4,4,3,3,2,2,1,1,0,0,15,15,14,14,13],"name":"chuxu3","type":"mesh","triangles":[4,16,6,4,6,5,6,16,7,16,8,7,17,16,4,3,17,4,16,17,8,17,9,8,18,17,3,2,18,3,19,18,2,18,9,17,1,19,2,18,10,9,0,20,1,20,19,1,15,20,0,19,10,18,19,11,10,14,20,15,20,12,19,12,11,19,13,12,20,14,13,20],"bonePose":[15,0.994666875152874,0.10313974730246778,-0.10313974730246778,0.994666875152874,3.4326683094984256,-64.34873247277801,6,0.6015362101095684,0.7988455344602091,-0.7988455344602091,0.6015362101095684,-5.385852530707846,-76.05980800796468],"width":28,"weights":[2,15,0.05496,6,0.94503,2,15,0.24158,6,0.75841,2,15,0.53241,6,0.46757,2,15,0.82784,6,0.17215,2,15,0.9543,6,0.04569,2,15,0.98863,6,0.01136,2,15,0.99875,6,0.00124,2,15,0.99843,6,0.00156,2,15,0.95945,6,0.04053,2,15,0.82235,6,0.17764,2,15,0.50381,6,0.49618,2,15,0.2074,6,0.79259,2,15,0.0297,6,0.97029,2,15,0.00291,6,0.99708,2,15,0.00149,6,0.9985,2,15,0.01452,6,0.98547,2,15,0.97588,6,0.02411,2,15,0.8286,6,0.17139,2,15,0.54649,6,0.4535,2,15,0.19894,6,0.80105,2,15,0.04622,6,0.95377],"uvs":[0.51934,0.09676,0.59647,0.2916,0.67933,0.43424,0.75853,0.53872,0.85855,0.59266,1,0.60312,1,0.77062,1,0.8623,0.87565,1,0.62131,1,0.35921,1,0.18205,0.84815,0.05347,0.71419,0,0.59242,0,0,0.39647,0,0.86697,0.79327,0.69036,0.7679,0.52889,0.70011,0.38341,0.57773,0.2786,0.41582],"height":23,"transform":{}}],"name":"chuxu3"},{"display":[{"slotPose":[1,0,0,1,0,0],"userEdges":[0,31,31,29,30,31,2,32,32,28,31,32,3,33,33,27,32,33,4,34,34,26,33,34,5,35,35,25,34,35,6,36,36,24,35,36,7,37,37,23,36,37,8,38,38,22,37,38,9,39,39,21,38,39,10,40,40,20,39,40,11,41,41,19,40,41,12,42,42,18,41,42,13,43,43,17,42,43,43,15],"vertices":[-48.11,-98.9,-48.1,-94.53,-50.6,-89.81,-56.12,-85.38,-62.38,-81.21,-67.86,-79.24,-72.4,-77.22,-75.11,-74.44,-77.08,-71.58,-78.35,-68.15,-78.58,-65.4,-79.04,-62.16,-77.36,-59.58,-74.49,-58.59,-72.08,-57.78,-72.84,-55.04,-73.29,-53.4,-79.96,-53.42,-83.48,-55.83,-85.96,-59.87,-87.09,-64.09,-87.09,-68.83,-87.1,-73.9,-87.1,-79.15,-84.91,-85.58,-81.9,-90.98,-76.77,-96.11,-71.87,-100.14,-66.36,-104.87,-61.73,-111.39,-48.11,-111.4,-54.16,-104.44,-58.94,-97.78,-63.18,-91.99,-69.14,-88.21,-74.48,-84.78,-78.13,-81.04,-80.79,-76.67,-82.26,-72.78,-82.58,-68.48,-82.65,-64.78,-82.37,-61.06,-80.6,-57.59,-77.16,-56.08],"path":"chuxu1","edges":[20,19,19,18,18,17,17,16,16,15,15,14,14,13,13,12,12,11,11,10,10,9,9,8,8,7,7,6,6,5,5,4,4,3,3,2,2,1,1,0,0,30,30,29,29,28,28,27,27,26,26,25,25,24,24,23,23,22,22,21,21,20],"name":"chuxu1","type":"mesh","triangles":[31,32,0,0,32,1,32,2,1,29,31,30,31,0,30,32,33,3,32,3,2,28,32,31,29,28,31,33,4,3,33,34,4,27,33,32,28,27,32,34,5,4,27,34,33,27,26,34,34,35,5,35,6,5,26,35,34,26,25,35,35,36,6,13,15,14,36,7,6,43,16,15,13,43,15,43,17,16,12,43,13,36,37,7,24,36,35,25,24,35,37,8,7,42,43,12,38,9,8,37,38,8,42,17,43,11,42,12,38,39,9,23,37,36,24,23,36,9,39,10,39,40,10,41,42,11,10,40,11,40,41,11,18,17,42,41,18,42,19,18,41,22,38,37,23,22,37,20,41,40,21,39,38,20,19,41,39,21,40,21,20,40,22,21,38],"bonePose":[12,-0.6643176677893622,0.7474503570558398,-0.7474503570558398,-0.6643176677893622,-55.07181070385295,-104.21555982560356,19,-0.7724011234683431,0.6351350285292421,-0.6351350285292421,-0.7724011234683431,-69.21263987041047,-88.25998868313937,22,-0.011344396795372136,0.99993565026023,-0.99993565026023,-0.011344396795372136,-82.50429054435125,-77.34339020367109,25,0.6355393697303464,0.7720684616811865,-0.7720684616811865,0.6355393697303464,-82.65376083214622,-61.5240678846504],"width":39,"weights":[3,12,0.97627,19,0.0237,22,0.00001,3,12,0.94649,19,0.05326,22,0.00023,3,12,0.87139,19,0.12676,22,0.00184,3,12,0.72121,19,0.26809,22,0.01067,4,12,0.51538,19,0.44033,22,0.04423,25,0.00004,4,12,0.30574,19,0.56546,22,0.12849,25,0.00028,4,12,0.14555,19,0.56901,22,0.28314,25,0.00227,4,12,0.05422,19,0.45133,22,0.48194,25,0.01249,4,12,0.01526,19,0.2798,22,0.65632,25,0.04859,4,12,0.00326,19,0.13551,22,0.72293,25,0.13828,4,12,0.00048,19,0.0502,22,0.64959,25,0.29971,4,12,0.00006,19,0.01422,22,0.47194,25,0.51375,3,19,0.00298,22,0.27372,25,0.72328,3,19,0.00045,22,0.12705,25,0.87248,3,19,0.00006,22,0.06256,25,0.93736,2,22,0.05554,25,0.94444,3,19,0.00001,22,0.06159,25,0.93838,3,19,0.0002,22,0.12601,25,0.87377,3,19,0.0021,22,0.27309,25,0.72478,4,12,0.00002,19,0.01207,22,0.47262,25,0.51527,4,12,0.00026,19,0.04637,22,0.65236,25,0.30098,4,12,0.00239,19,0.13054,22,0.72788,25,0.13917,4,12,0.01284,19,0.27557,22,0.6625,25,0.04908,4,12,0.0491,19,0.45042,22,0.48776,25,0.01269,4,12,0.13702,19,0.57327,22,0.28736,25,0.00232,4,12,0.29425,19,0.5747,22,0.13075,25,0.00028,4,12,0.50277,19,0.45215,22,0.04504,25,0.00003,3,12,0.71014,19,0.27905,22,0.01078,3,12,0.865,19,0.13322,22,0.00177,3,12,0.95014,19,0.04972,22,0.00012,2,12,0.9764,19,0.02359,3,12,0.95984,19,0.04007,22,0.00008,3,12,0.8747,19,0.12411,22,0.00118,3,12,0.7202,19,0.27061,22,0.00916,4,12,0.50923,19,0.45052,22,0.04021,25,0.00001,4,12,0.29587,19,0.57904,22,0.12488,25,0.00017,4,12,0.13598,19,0.58146,22,0.28086,25,0.00167,4,12,0.04742,19,0.45411,22,0.4878,25,0.01064,4,12,0.01218,19,0.2759,22,0.66724,25,0.04465,4,12,0.00209,19,0.12771,22,0.73717,25,0.13301,4,12,0.00026,19,0.04462,22,0.65888,25,0.29622,4,12,0.00001,19,0.01116,22,0.4741,25,0.51471,3,19,0.00192,22,0.26913,25,0.72893,3,19,0.0002,22,0.12026,25,0.87953],"uvs":[1,0.21557,1,0.29095,0.93609,0.37235,0.79463,0.44861,0.63418,0.52048,0.49342,0.55461,0.37688,0.58953,0.30749,0.63749,0.2571,0.68674,0.22457,0.74585,0.21855,0.79327,0.20701,0.84913,0.25003,0.8936,0.32375,0.9105,0.38542,0.92464,0.36617,0.97177,0.35465,1,0.18336,1,0.09311,0.95843,0.02932,0.8887,0,0.81577,0,0.73404,0,0.64663,0,0.55602,0.05612,0.44522,0.13342,0.35212,0.26496,0.26367,0.39052,0.19412,0.5318,0.11271,0.65043,0,1,0,0.84497,0.11997,0.7222,0.23498,0.61367,0.33465,0.46073,0.39984,0.32344,0.459,0.22998,0.52344,0.16181,0.59889,0.12419,0.66601,0.11603,0.74015,0.11409,0.80402,0.12138,0.8682,0.16675,0.92801,0.25544,0.95405],"height":58,"transform":{}}],"name":"chuxu1"},{"display":[{"slotPose":[1,0,0,1,0,0],"userEdges":[5,48,48,49,49,43,50,51,51,52,52,53,53,54,54,55,55,56,1,57,57,50,56,57,51,58,58,45,59,60,60,61,61,62,62,63,63,64,64,65,65,66,66,59,3,67,67,68,68,69,69,70,6,71,71,72,72,42,7,73,71,73,8,74,73,74,9,75,74,75,10,76,75,76,11,77,76,77,12,78,77,78,13,79,79,35,78,79,14,80,80,34,79,80,15,81,81,33,80,81,16,82,82,32,81,82,17,83,83,31,82,83,18,84,84,30,83,84,19,85,85,29,84,85,20,86,86,28,85,86,21,87,87,27,86,87,22,88,88,26,87,88,88,24,36,89,89,78,79,89,37,90,90,77,89,90,38,91,91,76,90,91,39,92,92,75,91,92,40,93,93,74,92,93,41,94,94,73,93,94,94,72],"vertices":[56.06,-170.21,49.93,-157.86,58.88,-142.44,58.88,-122.22,58.89,-105.23,37.86,-89.17,40.74,-79.63,43.09,-70.65,44.5,-63.83,45.34,-56.25,45.47,-45.37,42.81,-33.14,34.77,-23.13,29.03,-20.33,22.15,-18.11,13.57,-18.35,6.07,-18.77,3.24,-17.05,1.82,-14.7,0.79,-12.17,0.35,-8.65,0.25,-4.84,1.89,-0.25,5.33,4.6,0.76,4.6,-2.22,4.6,-6.02,1.31,-9.02,-3.73,-10.36,-8.59,-11.24,-14.42,-9.54,-20.3,-6.34,-24.54,-0.47,-28.36,6.72,-29.8,11.41,-31.06,14.58,-32.11,17.14,-33.81,18.46,-38.73,17.16,-44.17,10.27,-49.5,-0.78,-53.72,-12.42,-59.54,-23.22,-69.34,-56.99,-93.56,-73.11,-115.88,-73.12,-165.81,-73.11,-207.37,33.8,-207.38,9.77,-82,-22.51,-86.7,24.54,-146.95,-3.21,-156.23,-4.28,-136.59,6.3,-123.2,19.91,-118.55,33.94,-122.23,44.2,-135.3,41.27,-154.14,-30.27,-168.64,26.03,-146.25,28.45,-137.42,28.68,-128.4,25.09,-121.61,22.62,-121.72,20.9,-128.74,20.9,-137.83,23.24,-146.17,37.5,-107.63,7.34,-102.07,-23.22,-119.17,-38.37,-142.11,24.3,-74.75,4.03,-70.69,29.62,-67.95,32.46,-61.14,34.91,-54.25,35.99,-44.97,34.69,-35.01,29.41,-26.38,22.9,-25.34,16.64,-24.75,10.28,-23.85,3.11,-23.11,-1.04,-20.39,-3.54,-17.35,-4.88,-13.23,-4.65,-8.63,-4.14,-4.32,-2.11,0.54,23.61,-29.89,25.75,-37.06,25.91,-44.54,23.93,-52.13,19.23,-58.19,11.11,-64.25],"path":"shenti","edges":[44,43,43,42,42,41,41,40,40,39,39,38,38,37,37,36,36,35,35,34,34,33,33,32,32,31,31,30,30,29,29,28,28,27,27,26,26,25,25,24,24,23,23,22,22,21,21,20,20,19,19,18,18,17,17,16,16,15,15,14,14,13,13,12,12,11,11,10,10,9,9,8,8,7,7,6,6,5,5,4,4,3,3,2,2,1,1,0,0,47,47,46,46,45,45,44],"name":"shenti","type":"mesh","triangles":[67,5,4,56,55,3,67,4,3,55,67,3,1,57,2,57,56,2,56,3,2,57,1,0,47,57,0,51,50,47,47,50,57,59,60,57,76,77,11,61,55,56,57,60,56,76,11,10,75,76,10,74,75,8,8,75,9,75,10,9,7,74,8,60,61,56,77,12,11,6,73,7,73,74,7,71,73,6,50,59,57,5,71,6,77,78,12,48,71,5,68,48,5,68,5,67,54,68,67,58,51,47,46,58,47,92,91,75,90,77,76,91,90,76,75,91,76,90,78,77,74,92,75,90,89,78,78,13,12,61,62,55,50,51,66,73,93,74,93,92,74,66,65,59,89,79,78,78,79,13,79,14,13,64,62,61,59,65,60,64,61,60,65,64,60,50,66,59,63,54,62,64,63,62,36,89,90,37,36,90,92,38,91,37,90,91,38,37,91,36,79,89,51,65,66,51,52,65,64,54,63,80,14,79,64,53,54,80,15,14,52,53,65,65,53,64,53,68,54,81,15,80,35,34,80,34,81,80,33,81,34,81,16,15,68,49,48,53,69,68,33,82,81,82,16,81,49,72,48,32,82,33,69,49,68,52,69,53,82,17,16,22,24,23,83,17,82,42,41,72,49,42,72,83,18,17,32,83,82,32,31,83,21,88,22,88,24,22,84,19,18,83,84,18,88,25,24,87,88,21,86,87,21,86,21,20,86,20,19,85,86,19,84,85,19,31,84,83,31,30,84,70,52,51,26,25,88,87,26,88,58,70,51,30,29,84,84,29,85,85,28,86,28,27,86,86,27,87,27,26,87,29,28,85,70,69,52,69,43,49,49,43,42,70,44,69,44,43,69,45,70,58,46,45,58,45,44,70,67,54,55,62,54,55,48,71,72,72,94,71,36,79,35,35,80,79,38,39,92,93,39,92,39,40,93,94,40,93,40,41,94,72,41,94,93,94,73,71,94,73],"bonePose":[1,-0.06279051952931318,-0.9980267284282716,0.9980267284282716,-0.06279051952931318,-9.09,-138.28,5,0.6242887143330872,0.781193702711652,-0.781193702711652,0.6242887143330872,12.870501737186004,-77.3286377227625,18,-0.16900546957477836,0.9856151131419448,-0.9856151131419448,-0.16900546957477836,31.82547615422232,-53.62565173260718,24,-0.9842265000966648,0.1769129630848733,-0.1769129630848733,-0.9842265000966648,27.325159684051695,-27.794653848895624,27,-0.4819066111316505,0.87622258481941,-0.87622258481941,-0.4819066111316505,2.0742184636170977,-23.174559966499192,29,0.4408793407386586,0.8975663802247975,-0.8975663802247975,0.4408793407386586,-5.727410036365202,-8.885560955082614,9,0.9997224302180006,-0.023559764833610015,0.023559764833610015,0.9997224302180006,25.45613695105547,-135.7642055412017,10,-0.8587811079253983,-0.5123426672359286,0.5123426672359286,-0.8587811079253983,-2.2934835800494904,-111.6341773526629],"width":132,"weights":[1,1,1,1,1,1,1,1,1,1,1,1,1,1,1,1,1,1,3,5,0.47556,18,0.00812,1,0.5163,3,5,0.7175,18,0.05982,1,0.22267,3,5,0.71435,18,0.22412,1,0.06152,4,5,0.48508,18,0.49835,24,0.00812,1,0.00843,3,5,0.21462,18,0.72555,24,0.05982,3,5,0.05642,18,0.71945,24,0.22412,3,5,0.0075,18,0.49322,24,0.49927,3,18,0.23595,24,0.75622,27,0.00781,3,18,0.06362,24,0.87825,27,0.05812,3,18,0.0075,24,0.77187,27,0.22062,2,24,0.5,27,0.5,3,24,0.22062,27,0.77171,29,0.00765,3,24,0.05812,27,0.8846,29,0.05727,3,24,0.00781,27,0.77396,29,0.21822,2,27,0.50318,29,0.49681,2,27,0.22302,29,0.77697,2,27,0.05897,29,0.94102,2,27,0.01062,29,0.98937,2,27,0.00509,29,0.9949,2,27,0.01062,29,0.98937,2,27,0.05897,29,0.94102,2,27,0.22302,29,0.77697,2,27,0.50318,29,0.49681,3,24,0.00781,27,0.77396,29,0.21822,3,24,0.05812,27,0.8846,29,0.05727,3,24,0.22062,27,0.77171,29,0.00765,2,24,0.5,27,0.5,3,18,0.0075,24,0.77187,27,0.22062,3,18,0.06362,24,0.87825,27,0.05812,3,18,0.23595,24,0.75622,27,0.00781,3,5,0.0075,18,0.49322,24,0.49927,3,5,0.05642,18,0.71945,24,0.22412,3,5,0.21462,18,0.72554,24,0.05982,4,5,0.48508,18,0.49835,24,0.00812,1,0.00843,3,5,0.71435,18,0.22412,1,0.06152,3,5,0.7175,18,0.05982,1,0.22267,3,5,0.47556,18,0.00812,1,0.5163,1,1,1,1,1,1,1,1,1,1,1,1,1,1,1,1,1,1,1,1,1,1,1,1,1,1,1,1,1,1,1,1,1,1,1,1,1,1,1,1,1,1,1,1,1,1,1,1,1,9,1,1,9,1,1,9,1,1,9,1,1,9,1,1,9,1,1,9,1,1,9,1,2,1,0.45,10,0.55,2,1,0.45,10,0.55,2,1,0.45,10,0.55,2,1,0.45,10,0.55,3,5,0.6485,18,0.00519,1,0.3463,3,5,0.64849,18,0.00519,1,0.3463,3,5,0.77633,18,0.04881,1,0.17485,3,5,0.74333,18,0.21103,1,0.04563,4,5,0.48872,18,0.5028,24,0.00415,1,0.00431,3,5,0.20146,18,0.74972,24,0.04881,3,5,0.04568,18,0.74583,24,0.20847,3,5,0.00384,18,0.50818,24,0.48797,3,18,0.27585,24,0.72081,27,0.00333,3,18,0.06426,24,0.88523,27,0.0505,3,18,0.0064,24,0.78309,27,0.2105,2,24,0.5,27,0.5,3,24,0.2105,27,0.78558,29,0.00392,3,24,0.0505,27,0.89985,29,0.04965,3,24,0.00399,27,0.78785,29,0.20814,2,27,0.50344,29,0.49656,2,27,0.21285,29,0.78715,2,27,0.05134,29,0.94865,3,5,0.00384,18,0.50818,24,0.48797,3,5,0.04568,18,0.74583,24,0.20847,3,5,0.20146,18,0.74972,24,0.04881,4,5,0.48872,18,0.5028,24,0.00415,1,0.00431,3,5,0.74333,18,0.21103,1,0.04563,3,5,0.77633,18,0.04881,1,0.17485],"uvs":[0.97865,0.17531,0.93216,0.2336,1,0.30639,1,0.40179,1,0.48188,0.84064,0.55763,0.86248,0.60265,0.88029,0.64504,0.891,0.67719,0.89729,0.71292,0.89829,0.76429,0.87811,0.82194,0.81717,0.86918,0.77374,0.88239,0.72146,0.89285,0.65646,0.8917,0.59964,0.88971,0.57817,0.89784,0.56744,0.90892,0.55971,0.92085,0.55637,0.93746,0.55557,0.95542,0.56798,0.97712,0.59403,1,0.55938,1,0.53676,1,0.50798,0.98446,0.48526,0.96068,0.47512,0.9377,0.46847,0.9102,0.4814,0.88244,0.50558,0.86247,0.55012,0.84441,0.60467,0.83763,0.64013,0.8317,0.66419,0.82677,0.68357,0.81878,0.69358,0.79557,0.68374,0.7699,0.6316,0.74478,0.54794,0.72481,0.45971,0.69732,0.37791,0.6511,0.12211,0.53686,0,0.4316,0,0.19601,0,0,0.80999,0,0.62789,0.59143,0.38327,0.5693,0.73988,0.28505,0.52961,0.24124,0.52143,0.33396,0.60161,0.39713,0.7047,0.41904,0.81107,0.40172,0.88879,0.34007,0.86661,0.25114,0.32457,0.1827,0.75119,0.28836,0.76946,0.33006,0.77122,0.37264,0.74394,0.40464,0.72517,0.40408,0.71223,0.37095,0.71225,0.3281,0.73001,0.28871,0.83805,0.4706,0.60953,0.49677,0.37791,0.41607,0.2632,0.30786,0.73798,0.62568,0.58434,0.64477,0.77826,0.65772,0.79974,0.68986,0.81834,0.72238,0.82649,0.76617,0.81665,0.81315,0.77656,0.85386,0.72718,0.85875,0.67978,0.86151,0.63163,0.86578,0.57724,0.86922,0.54578,0.88206,0.52677,0.89641,0.51662,0.91582,0.51849,0.93757,0.52225,0.95791,0.53759,0.98084,0.7326,0.83727,0.74886,0.80347,0.75006,0.76817,0.73507,0.73237,0.69944,0.70378,0.63798,0.67516],"height":212,"transform":{}}],"name":"shenti"},{"display":[{"slotPose":[1,0,0,1,0,0],"userEdges":[5,18,18,9,7,18,4,19,19,10,18,19,3,20,20,11,19,20,2,21,21,12,20,21,1,22,22,13,21,22,0,23,23,14,22,23,23,16],"vertices":[44.7,-97.1,45.18,-89.92,47.63,-85.66,50.87,-80.4,50.87,-72.26,50.86,-67.15,48.89,-60.38,46.63,-60.38,42.84,-60.39,42.89,-64.92,41.6,-67.93,36.15,-72.07,33.44,-77.62,31.17,-82.92,26.89,-88.08,26.9,-102.37,33.01,-102.37,41.88,-102.37,46.93,-66.06,46.46,-70.21,43.83,-76.42,41.01,-81.91,38.37,-86.51,36.25,-92.82],"path":"chixu4","edges":[14,13,13,12,12,11,11,10,10,9,9,8,8,7,7,6,6,5,5,4,4,3,3,2,2,1,1,0,0,17,17,16,16,15,15,14],"name":"chixu4","type":"mesh","triangles":[20,19,4,18,6,5,4,19,5,19,18,5,2,21,3,21,20,3,20,4,3,18,7,6,18,9,7,9,8,7,1,21,2,22,21,1,20,10,19,19,10,18,10,9,18,11,10,20,0,23,1,23,22,1,17,23,0,21,12,20,12,11,20,16,23,17,22,13,21,13,12,21,23,13,22,14,13,23,16,15,23,15,14,23],"bonePose":[7,0.3462807970832524,0.9381309128108868,-0.9381309128108868,0.3462807970832524,34.32521995494771,-97.67594138188264,16,0.54009344091171,0.8416050588513292,-0.8416050588513292,0.54009344091171,40.47862971911711,-81.00535506123319,23,-0.08541692313736787,0.9963452961909064,-0.9963452961909064,-0.08541692313736787,47.335430600466104,-70.33920384940745],"width":24,"weights":[2,7,0.94204,16,0.05795,3,7,0.79401,16,0.20184,23,0.00412,3,7,0.54122,16,0.41121,23,0.04755,3,7,0.25549,16,0.55395,23,0.19054,3,7,0.08147,16,0.45692,23,0.46159,3,7,0.01245,16,0.24808,23,0.73946,3,7,0.00183,16,0.10605,23,0.8921,2,16,0.09037,23,0.90962,3,7,0.00147,16,0.09818,23,0.90033,3,7,0.01144,16,0.23294,23,0.7556,3,7,0.07965,16,0.43681,23,0.48352,3,7,0.25358,16,0.53385,23,0.21254,3,7,0.54057,16,0.3995,23,0.05991,3,7,0.79477,16,0.19628,23,0.00894,3,7,0.94367,16,0.05599,23,0.00032,2,7,0.98648,16,0.01351,2,7,0.99194,16,0.00805,2,7,0.985,16,0.01499,3,7,0.01078,16,0.22695,23,0.76225,3,7,0.06757,16,0.46276,23,0.46966,3,7,0.25476,16,0.54937,23,0.19585,3,7,0.53692,16,0.41818,23,0.04489,3,7,0.81065,16,0.1847,23,0.00464,2,7,0.94916,16,0.05083],"uvs":[0.74267,0.12553,0.76237,0.29653,0.86449,0.3979,1,0.52308,1,0.71683,1,0.83868,0.91825,1,0.82417,1,0.66559,1,0.6674,0.89191,0.61365,0.82023,0.38609,0.72171,0.27316,0.58936,0.17821,0.46341,0,0.34054,0,0,0.25512,0,0.62442,0,0.836,0.86492,0.81613,0.76604,0.70663,0.618,0.5886,0.48723,0.4784,0.37765,0.39035,0.22753],"height":42,"transform":{}}],"name":"chixu4"},{"display":[{"slotPose":[1,0,0,1,0,0],"userEdges":[0,21,21,18,19,21,1,22,22,17,21,22,2,23,23,16,22,23,3,24,24,15,23,24,4,25,25,14,24,25,5,26,26,13,25,26,6,27,27,12,26,27,7,28,28,11,27,28,28,9],"vertices":[24.87,-52.71,24.87,-44.88,22.36,-40.16,18.8,-37.12,14.56,-34.64,10.58,-33.4,4.7,-33.4,0.62,-33.39,-3.12,-33.39,-3.12,-35.08,-3.11,-36.33,-0.09,-37.41,2.67,-38.97,4.9,-40.93,7.25,-43.68,8.85,-46.51,10.37,-50.51,11.22,-54.36,13.85,-58.38,21.76,-58.38,24.87,-58.38,20.68,-54.87,18.31,-49.43,16.34,-45.36,13.86,-41.79,10.92,-39.14,7.69,-37.24,3.68,-36.19,0.25,-35.49],"path":"chuxu5","edges":[8,7,7,6,6,5,5,4,4,3,3,2,2,1,1,0,0,20,20,19,19,18,18,17,17,16,16,15,15,14,14,13,13,12,12,11,11,10,10,9,9,8],"name":"chuxu5","type":"mesh","triangles":[19,21,20,23,2,1,22,23,1,22,1,0,21,22,0,20,21,0,23,24,3,23,3,2,18,21,19,17,22,21,18,17,21,24,4,3,16,23,22,17,16,22,25,4,24,15,24,23,16,15,23,25,5,4,14,25,24,15,14,24,14,13,25,13,26,25,26,5,25,26,6,5,12,27,13,13,27,26,27,6,26,27,7,6,28,7,27,12,11,27,11,28,27,8,7,28,9,8,28,11,10,28,10,9,28],"bonePose":[8,-0.6200529326616326,0.7845599790313733,-0.7845599790313733,-0.6200529326616326,22.12034411874744,-53.732879292140495,17,-0.8710424003100696,0.49120783469125623,-0.49120783469125623,-0.8710424003100696,10.752749040067842,-39.42997112187039],"width":28,"weights":[2,8,0.99905,17,0.00094,2,8,0.99042,17,0.00957,2,8,0.93707,17,0.06291,2,8,0.7864,17,0.21359,2,8,0.52199,17,0.478,2,8,0.25037,17,0.74962,2,8,0.07881,17,0.92118,2,8,0.01435,17,0.98564,2,8,0.00243,17,0.99756,1,17,1,2,8,0.00201,17,0.99798,2,8,0.0139,17,0.98609,2,8,0.07842,17,0.92157,2,8,0.25119,17,0.7488,2,8,0.52367,17,0.47631,2,8,0.78857,17,0.21142,2,8,0.93838,17,0.06161,2,8,0.99099,17,0.00899,2,8,0.99908,17,0.00091,1,8,1,1,8,1,1,8,1,2,8,0.99235,17,0.00764,2,8,0.94736,17,0.05263,2,8,0.79299,17,0.207,2,8,0.52455,17,0.47544,2,8,0.24094,17,0.75905,2,8,0.06866,17,0.93133,2,8,0.0105,17,0.98949],"uvs":[1,0.22687,1,0.54048,0.91041,0.72928,0.78326,0.85088,0.63184,0.95008,0.48938,1,0.27938,1,0.13367,1,0,1,0,0.93254,0,0.88235,0.10796,0.83915,0.20653,0.77675,0.28653,0.69835,0.37041,0.58848,0.42755,0.47488,0.48184,0.31488,0.51184,0.16128,0.60587,0,0.8889,0,1,0,0.84975,0.14038,0.76534,0.3582,0.69527,0.52125,0.60658,0.66413,0.50166,0.77003,0.38596,0.84621,0.24279,0.88787,0.12022,0.91587],"height":25,"transform":{}}],"name":"chuxu5"},{"display":[{"path":"ty","type":"image","name":"ty","transform":{}}],"name":"ty"},{"display":[{"path":"biyan","type":"image","name":"biyan","transform":{"y":9.52,"skX":4.05,"skY":4.05,"x":-5.73}}],"name":"biyan"},{"display":[{"slotPose":[1,0,0,1,0,0],"userEdges":[0,22,22,18,20,22,1,23,23,17,22,23,2,24,24,16,23,24,3,25,25,15,24,25,4,26,26,14,25,26,5,27,27,13,26,27,6,28,28,12,27,28,7,29,29,11,28,29,29,8],"vertices":[0.89,-63.77,0.89,-57.4,0.89,-50.79,0.89,-44.77,-1.56,-38.15,-4.63,-32.85,-8.45,-29.84,-13.81,-26.41,-17.47,-26.41,-19.1,-26.41,-19.1,-27.38,-17.62,-29.66,-16.62,-32.58,-15.74,-36.47,-15.62,-41.83,-15.81,-45.92,-16.61,-50.4,-17.91,-56.03,-19.1,-62.06,-19.11,-73.38,-11.5,-73.38,-4.3,-73.38,-9.4,-62.88,-8.1,-56.74,-7.33,-50.61,-8.17,-45.39,-8.97,-40.08,-10.3,-34.7,-12.37,-31.16,-15.64,-27.98],"path":"chuxu6","edges":[9,8,8,7,7,6,6,5,5,4,4,3,3,2,2,1,1,0,0,21,21,20,20,19,19,18,18,17,17,16,16,15,15,14,14,13,13,12,12,11,11,10,10,9],"name":"chuxu6","type":"mesh","triangles":[25,4,3,24,25,3,21,22,0,22,23,0,0,23,1,23,24,1,1,24,2,24,3,2,26,5,4,25,26,4,20,22,21,27,6,5,26,27,5,27,28,6,15,25,24,16,15,24,23,16,24,20,18,22,15,14,25,22,17,23,17,16,23,13,27,26,25,14,26,28,7,6,14,13,26,19,18,20,18,17,22,13,28,27,29,7,28,12,29,28,13,12,28,11,29,12,29,8,7,11,8,29,10,9,8,10,8,11],"bonePose":[4,0.14107402151565474,0.9899990507335856,-0.9899990507335856,0.14107402151565474,-9.753503804738015,-69.83327427333653,14,-0.2246109213307029,0.9744485281527048,-0.9744485281527048,-0.2246109213307029,-6.99399670788685,-50.75173553605362,20,-0.565830750324075,0.824521413904875,-0.824521413904875,-0.565830750324075,-10.90049117090162,-35.80732517597468],"width":20,"weights":[2,4,0.93141,14,0.06858,3,4,0.76914,14,0.2303,20,0.00053,3,4,0.5004,14,0.49178,20,0.00781,3,4,0.23053,14,0.70241,20,0.06703,3,4,0.07007,14,0.6983,20,0.23162,3,4,0.01116,14,0.47444,20,0.51439,3,4,0.00109,14,0.22562,20,0.77328,2,14,0.06876,20,0.93123,2,14,0.02046,20,0.97953,2,14,0.00259,20,0.9974,2,14,0.00778,20,0.99221,3,4,0.00014,14,0.04603,20,0.95382,3,4,0.0023,14,0.18842,20,0.80925,3,4,0.0146,14,0.43239,20,0.55299,3,4,0.07588,14,0.66289,20,0.26121,3,4,0.23644,14,0.6819,20,0.08164,3,4,0.50355,14,0.48409,20,0.01234,3,4,0.76881,14,0.23034,20,0.00084,2,4,0.9291,14,0.07089,2,4,0.98292,14,0.01706,2,4,0.98845,14,0.01154,2,4,0.98529,14,0.0147,2,4,0.93974,14,0.06025,2,4,0.77753,14,0.22246,3,4,0.50076,14,0.49057,20,0.00866,3,4,0.22668,14,0.71078,20,0.06251,3,4,0.06259,14,0.69153,20,0.24587,3,4,0.01037,14,0.45922,20,0.53039,3,4,0.00026,14,0.19184,20,0.80788,2,14,0.05282,20,0.94717],"uvs":[1,0.20473,1,0.34026,1,0.4808,1,0.60904,0.87785,0.75017,0.72375,0.86279,0.53279,0.92694,0.26477,1,0.08095,1,0,1,0,0.97928,0.07409,0.93077,0.12407,0.86849,0.16762,0.78581,0.17432,0.67176,0.16428,0.5848,0.12433,0.48935,0.05956,0.36945,0,0.24121,0,0,0.38011,0,0.7407,0,0.48516,0.22351,0.55009,0.35423,0.58828,0.48482,0.54692,0.5959,0.50692,0.70883,0.44021,0.82354,0.33663,0.89889,0.17319,0.96675],"height":47,"transform":{}}],"name":"chuxu6"}]}]}],"name":"heroDB35013","version":"5.0"}