{"width":1024,"imagePath":"heroDB250610_tex.png","height":2048,"name":"heroDB250610","SubTexture":[{"width":56,"y":686,"height":173,"name":"zuodabi3a","x":940},{"width":172,"y":1181,"height":56,"name":"yun_xiaoyun0031","x":304},{"width":171,"y":686,"height":117,"name":"yun_xiaoyun0011","x":752},{"width":189,"y":1173,"height":69,"name":"yun_xiaoyun0029","x":479},{"width":179,"y":826,"height":112,"name":"yun_xiaoyun0009","x":161},{"width":202,"y":902,"height":79,"name":"yun_xiaoyun0027","x":740},{"width":186,"y":713,"height":111,"name":"yun_xiaoyun0007","x":161},{"width":199,"y":940,"height":93,"name":"yun_xiaoyun0025","x":148},{"width":176,"y":712,"height":110,"name":"yun_xiaoyun0005","x":566},{"width":196,"y":694,"height":108,"name":"yun_xiaoyun0023","x":368},{"width":178,"y":907,"height":107,"name":"yun_xiaoyun0003","x":349},{"width":194,"y":805,"height":95,"name":"yun_xiaoyun0039","x":744},{"width":191,"y":804,"height":101,"name":"yun_xiaoyun0001","x":349},{"width":196,"y":824,"height":84,"name":"yun_xiaoyun0037","x":542},{"width":204,"y":441,"height":120,"name":"yun_xiaoyun0021","x":801},{"width":194,"y":1103,"height":68,"name":"yun_xiaoyun0035","x":479},{"width":211,"y":563,"height":129,"name":"yun_xiaoyun0019","x":1},{"width":212,"y":562,"height":130,"name":"yun_xiaoyun0017","x":377},{"width":184,"y":1244,"height":52,"name":"yun_xiaoyun0033","x":304},{"width":208,"y":441,"height":126,"name":"yun_xiaoyun0015","x":591},{"width":195,"y":563,"height":121,"name":"yun_xiaoyun0013","x":801},{"width":174,"y":983,"height":90,"name":"ty","x":740},{"width":191,"y":1173,"height":63,"name":"yun2_z2","x":670},{"width":208,"y":1035,"height":71,"name":"yun2_z4","x":1},{"width":243,"y":1075,"height":58,"name":"yun2_z1","x":740},{"width":210,"y":1238,"height":54,"name":"yun2_z3","x":675},{"width":236,"y":1016,"height":66,"name":"yun2_z5","x":349},{"width":339,"y":1,"height":213,"name":"pifeng","x":456},{"width":51,"y":1135,"height":36,"name":"xiong2a","x":755},{"frameY":0,"y":1168,"frameWidth":150,"frameX":0,"frameHeight":95,"width":148,"height":95,"name":"yun_z3","x":154},{"width":151,"y":1084,"height":95,"name":"yun_z5","x":326},{"width":151,"y":1006,"height":95,"name":"yun_z2","x":587},{"width":151,"y":1108,"height":95,"name":"yun_z1","x":1},{"frameY":0,"y":1205,"frameWidth":150,"frameX":0,"frameHeight":95,"width":148,"height":95,"name":"yun_z4","x":1},{"width":33,"y":958,"height":62,"name":"zuodabi2","x":983},{"width":87,"y":1265,"height":110,"name":"zuoxiaobi","x":151},{"width":159,"y":569,"height":141,"name":"xiong","x":591},{"width":226,"y":1,"height":244,"name":"tou","x":797},{"width":171,"y":910,"height":94,"name":"xiong2","x":542},{"width":65,"y":983,"height":72,"name":"youdabi2","x":916},{"width":113,"y":1035,"height":131,"name":"zuoxiaobi2","x":211},{"width":145,"y":838,"height":136,"name":"zuodabi","x":1},{"width":194,"y":415,"height":145,"name":"youdabi","x":377},{"width":152,"y":556,"height":155,"name":"guang13","x":214},{"width":189,"y":404,"height":150,"name":"guang12","x":186},{"width":153,"y":247,"height":155,"name":"guang11","x":842},{"width":202,"y":216,"height":197,"name":"guang10","x":456},{"width":180,"y":247,"height":192,"name":"guang9","x":660},{"width":453,"y":1,"height":401,"name":"shihua","x":1},{"width":57,"y":1103,"height":18,"name":"yun2","x":675},{"width":78,"y":1135,"height":36,"name":"yun3","x":675},{"width":45,"y":1135,"height":36,"name":"yun4","x":808},{"width":21,"y":1035,"height":42,"name":"zuoxiaobi2a","x":326},{"frameY":0,"y":1186,"frameWidth":128,"frameX":-33,"frameHeight":48,"width":95,"height":48,"name":"y3","x":863},{"width":130,"y":976,"height":50,"name":"y2","x":1},{"frameY":0,"y":909,"frameWidth":73,"frameX":0,"frameHeight":47,"width":72,"height":47,"name":"y6","x":944},{"width":110,"y":1302,"height":41,"name":"y5","x":1},{"width":74,"y":861,"height":46,"name":"y4","x":944},{"width":110,"y":1135,"height":49,"name":"y1","x":863},{"width":43,"y":1108,"height":51,"name":"g1","x":154},{"width":158,"y":694,"height":142,"name":"g2","x":1},{"width":183,"y":404,"height":157,"name":"g4","x":1}]}