{"width":512,"SubTexture":[{"width":174,"y":219,"height":90,"name":"ty","x":1},{"width":70,"y":58,"height":53,"name":"yumao","x":386},{"width":22,"y":98,"height":28,"name":"zuoshoubi","x":361},{"width":179,"y":1,"height":58,"name":"wuqi","x":205},{"width":24,"y":113,"height":21,"name":"xiaotui1","x":385},{"width":23,"y":107,"height":23,"name":"datui1","x":239},{"width":32,"y":132,"height":19,"name":"jiaozhang1","x":274},{"width":33,"y":132,"height":21,"name":"jiaozhang","x":239},{"width":21,"y":136,"height":21,"name":"xiaotui","x":308},{"width":18,"y":128,"height":25,"name":"datui","x":361},{"width":49,"y":61,"height":42,"name":"dangbu","x":271},{"width":45,"y":58,"height":54,"name":"xiongqiang","x":458},{"width":22,"y":143,"height":29,"name":"shougu","x":205},{"width":24,"y":1,"height":46,"name":"gulian","x":480},{"width":43,"y":61,"height":35,"name":"shangshoubi","x":322},{"width":37,"y":98,"height":36,"name":"xiashoubi","x":322},{"width":32,"y":107,"height":34,"name":"shouzhang","x":205},{"width":92,"y":1,"height":55,"name":"toufa6","x":386},{"width":46,"y":105,"height":25,"name":"liaoya2","x":271},{"width":118,"y":219,"height":109,"name":"lian","x":347},{"width":64,"y":61,"height":44,"name":"liaoya1","x":205},{"width":168,"y":219,"height":85,"name":"toufaa","x":177},{"width":202,"y":1,"height":216,"name":"shihua","x":1}],"height":512,"name":"heroDB52034","imagePath":"heroDB52034_tex.png"}